Workbook

Sheet Etat des lieux
A1: Avancement
A3: Validée | B3: =COUNTIFS('Datalayer BPCE vtravail'!E2:E155,"Validée") -> 77
A4: A préciser | B4: =COUNTIFS('Datalayer BPCE vtravail'!E3:E209,"A préciser") -> 0
A5: A implémenter | B5: =COUNTIFS('Datalayer BPCE vtravail'!E4:E210,"A implémenter") -> 0
A6: A supprimer | B6: =COUNTIFS('Datalayer BPCE vtravail'!E5:E211,"A supprimer") -> 79
A7: Reste à analyser | B7: =COUNTIFS('Datalayer BPCE vtravail'!E6:E212,"") -> 4

Sheet Repérages report suite
B1: Statut | C1: Nom de la report suite | E1: CE | F1: principale report suite, sur laquelle les variables devraient être
B2: Archivé | C2: bpcebpcetestdev
B3: Archivé | C3: bpceriarwddev
B4: Archivé | C4: bpcetemplate
B5: B2B & institutionnel | C5: bpce89c3production
B6: B2B & institutionnel | C6: bpce89c3recette
B7: B2B & institutionnel | C7: bpceapp.pulsar.89c3..recette
B8: CE | C8: bpceceprod11315
B9: CE | C9: bpceceprod11425
B10: CE | C10: bpceceprod12135
B11: CE | C11: bpceceprod12579
B12: CE | C12: bpceceprod13135
B13: CE | C13: bpceceprod13335
... B48: Paylib | C48: bpceappexternerecette

Sheet Audit variables Adobe
B1: Introduction au document
B3: Définition du OK : nom est à la norme dans Adobe Analytics et dans la doc. La doc et Adobe sont cohérents.
B4: Définition du Erreur : une correction doit être apportée (A corriger), ou une incertitude demeure dans les specs qui doit être confirmée (A clarifier)
B5: Certaines actions ne génèrent pas d'erreur, mais génèrent cependant de l'incertitude, et sont marquées par une action A clarifier
C7: CE | F7: BP | I7: Erreur globale BP | J7: Mapping
A8: Numéro variable | B8: Nom variable dans la documentation | C8: Verdict | D8: Action | E8: Commentaire | F8: Verdict2 | G8: Action2 | H8: Commentaire2 | I8: Tous les noms doivent être mis à la norme "nom de la variable (propX/evarX/eventX)"
A9: prop1 | B9: Code Etablissement Client (prop1) | C9: OK | F9: OK
A10: prop2 | B10: Id Client (prop2) | C10: OK | F10: OK
A11: prop3 | B11: Statut Client (prop3) | C11: OK | F11: OK
A12: prop4 | B12: Marché Client (prop4) | C12: OK | F12: OK
A13: prop5 | B13: Code réduit Etablissement de la page (prop5) | C13: OK | F13: OK
A14: prop6 | B14: Type Applicatif (prop6) | C14: OK | F14: OK
A15: prop7 | B15: Nom de l applicatif (prop7) | C15: OK | F15: OK
A16: prop8 | B16: Marché de navigation (prop8) | C16: OK | F16: OK
A17: prop9 | B17: Univers de navigation (prop9) | C17: OK | F17: OK
A18: prop10 | B18: Type de la page (prop10) | C18: OK | F18: OK
A19: prop11 | B19: Is ABTesting (prop11) | C19: OK | F19: OK
A20: prop12 | B20: Id ABTesting(prop12) | C20: OK | F20: OK
... A27: prop19 | B27: Nom de la tuile (prop19) | C27: OK | F27: OK
A28: prop20 | B28: Home - libellé de toutes les vignettes (prop20) | C28: Erreur | D28: A clarifier | E28: Renseignée mais en doublon par rappor tà la list var 1 et souvent tronquée faute nb caractère suffisant. Pas trouvées dans le datalayer pour voir prioppriété et variable (compléter doc interne) | F28: Erreur | G28: A clarifier | H28: Renseignée mais en doublon par rappor tà la list var 1 et souvent tronquée faute nb caractère suffisant. Pas trouvées dans le datalayer pour voir prioppriété et variable (compléter doc interne)
A29: prop21 | B29: Home - libellé vignette principale (prop21) | C29: Erreur | D29: A clarifier | E29: Disabled, utile ? Doublon par rapport à la list var 1. Pas trouvées dans le datalayer pour voir prioppriété et variable (compléter doc interne) | F29: Erreur | G29: A clarifier | H29: Disabled, utile ? Doublon par rapport à la list var 1. Pas trouvées dans le datalayer pour voir prioppriété et variable (compléter doc interne). Signalement coquille : incohérent entre BP prod et le reste (BP recette et CE), variable est "Code Etablissement BP" + est disabled vs "Home - libelle vignette principale"
A30: prop22 | B30: Age(s) et Lien de parenté (prop22) | C30: Erreur | D30: A réutiliser pour EDL | E30: Donnee personnelle, à retirer ? Renseignée en 2017, plus en 2018 ou 2019. | F30: Erreur | G30: A réutiliser pour EDL | H30: Donnee personnelle, à retirer ? Renseignée en 2017, plus en 2018 ou 2019.
A31: prop23 | B31: Temps de chargement de la page | C31: Erreur | D31: A trancher (abandonner deux propositions et notifier Natixis Assurance) | E31: Conflit ==> dans CE c'est "Type de virement (prop23)", dans 89c3 c'est "Auto : infos" (repris par Natixis dans la prop75), et doc centrale c'est "Temps de chargement de la page". A conserver pour historique ? | F31: Erreur | G31: A trancher (abandonner deux propositions et notifier Natixis Assurance) | H31: Conflit ==> dans Adobe c'est "Auto : infos" (repris par Natixis dans la prop75), et doc centrale c'est "Temps de chargement de la page". A conserver pour historique ?
A32: prop24 | B32: type de dossier | C32: Erreur | D32: A trancher (abandonner deux propositions et notifier Natixis Assurance) | E32: Conflit ==> dans CE c'est "Montant du virement (prop24)", dans 89c3 c'est "Auto : infos" (repris par Natixis dans la prop75) et doc centrale c'est "type de dossier". A conserver pour historique ? | F32: Erreur | G32: A trancher (abandonner deux propositions et notifier Natixis Assurance) | H32: Conflit ==> dans Adobe c'est "Auto : infos" (repris par Natixis dans la prop75), et doc centrale c'est "type dossier". A conserver pour historique ?
A33: prop25 | B33: "type de document Auto: Assureur précédent (prop25)" | C33: Erreur | D33: A conserver/supprimer (notifier Natixis Assurance) ? | E33: Conflit ==> dans Adobe c'est "Auto infos" et dans doc centrale "type de document" non réutilisées par Natixis car pas représentatives des écrans pour le nouveau parcours. Actuellement disabled. A conserver pour historique ? | F33: Erreur | G33: A conserver/supprimer (notifier Natixis Assurance) ? | H33: Conflit ==> dans Adobe c'est "Auto infos" et dans doc centrale "type de document" non réutilisées par Natixis car pas représentatives des écrans pour le nouveau parcours. Actuellement disabled. A conserver pour historique ?
A34: prop26 | B34: MRH: type résidence; monument; dependance; nb pièces; nb chambre; superficie; dev durable; jacuzzi; piscine (prop26) | C34: Erreur | D34: A conserver/supprimer (notifier Natixis Assurance) ? | E34: MRH infos, non réutilisées par Natixis car pas représentatives des écrans pour le nouveau parcours. Actuellement disabled. A conserver pour historique ? | F34: Erreur | G34: A conserver/supprimer (notifier Natixis Assurance) ? | H34: MRH infos, non réutilisées par Natixis car pas représentatives des écrans pour le nouveau parcours. Actuellement disabled. A conserver pour historique ?
A35: prop27 | B35: MRH: souhaite assurer pour; occupant scolarise moins 25ans; choix formule (prop27) | C35: Erreur | D35: A conserver/supprimer (notifier Natixis Assurance) ? | E35: MRH infos, non réutilisées par Natixis car pas représentatives des écrans pour le nouveau parcours. Actuellement disabled. A conserver pour historique ? | F35: Erreur | G35: A conserver/supprimer (notifier Natixis Assurance) ? | H35: MRH infos, non réutilisées par Natixis car pas représentatives des écrans pour le nouveau parcours. Actuellement disabled. A conserver pour historique ?
A36: prop28 | B36: MRH: année construction; nb bénéficiaires; ages bénéficiaires (prop28) | C36: Erreur | D36: A conserver/supprimer (notifier Natixis Assurance) ? | E36: MRH infos, non réutilisées par Natixis car pas représentatives des écrans pour le nouveau parcours. Actuellement disabled. A conserver pour historique ? | F36: Erreur | G36: A conserver/supprimer (notifier Natixis Assurance) ? | H36: MRH infos, non réutilisées par Natixis car pas représentatives des écrans pour le nouveau parcours. Actuellement disabled. A conserver pour historique ?
A37: prop29 | B37: MRH: Code postal; type Habitation; NB pièces; Vous etes; type résidence; Mes attentes (prop29) | C37: Erreur | D37: A conserver/supprimer (notifier Natixis Assurance) ? | E37: MRH infos, non réutilisées par Natixis car pas représentatives des écrans pour le nouveau parcours. Actuellement disabled. A conserver pour historique ? | F37: Erreur | G37: A conserver/supprimer (notifier Natixis Assurance) ? | H37: MRH infos, non réutilisées par Natixis car pas représentatives des écrans pour le nouveau parcours. Actuellement disabled. A conserver pour historique ?
A38: prop30 | B38: Résultat nul (prop30) | C38: OK | F38: OK
A39: prop31 | B39: Pagename (prop31) | C39: OK | D39: A clarifier | E39: Règle de gestion manquante | F39: OK | G39: A clarifier | H39: Règle de gestion manquante
A40: prop32 | B40: Pagename page précédente (prop32) | C40: OK | D40: A clarifier | E40: Règle de gestion manquante | F40: OK | G40: A clarifier | H40: Règle de gestion manquante
A41: prop33 | B41: Libellé clic page précédente (prop33) | C41: OK | D41: A clarifier | E41: Règle de gestion manquante | F41: OK | G41: A clarifier | H41: Règle de gestion manquante
A42: prop34 | B42: Banner (prop34) | C42: OK | F42: OK
A43: prop35 | B43: Nombre de cartes actives differentes (prop35) | C43: OK | F43: OK
A44: prop36 | B44: Nombre de cartes opposées différentes (prop36) | C44: OK | F44: OK
A45: prop37 | B45: Nombre de cartes commandées ou expédiées (prop37) | C45: OK | F45: OK
A46: prop38 | B46: Nombre de cartes actives et verrouillées temporairement (prop38) | C46: OK | F46: OK
A47: prop39 | B47: Nombre de cartes actives et paiements en ligne désactivés (prop39) | C47: OK | F47: OK
A48: prop40 | B48: Nombre de cartes actives et paiements a l etranger desactivés (prop40) | C48: OK | F48: OK
A49: prop41 | B49: Nombre de cartes enrolement (prop41) | C49: OK | F49: OK
A50: prop42 | B50: Paylib type (prop42) | C50: OK | F50: OK
A51: prop43 | B51: Mode de paiement (prop43) | C51: OK | F51: OK
A52: prop44 | B52: Montant reglette (prop44) | C52: OK | F52: OK | H52: Disabled, utile ?
A53: prop45 | B53: Total nombre de compte détenus (prop45) | C53: OK | E53: Disabled, utile ? | F53: OK
A54: prop46 | B54: Code produit repris (prop46) | C54: OK | E54: Disabled, utile ? | F54: OK | H54: Disabled, utile ?
A55: prop47 | B55: Libelle transaction incorrect (prop47) | C55: OK | E55: Disabled, utile ? | F55: OK
A56: prop48 | B56: Switch (prop48) | C56: OK | E56: Disabled, utile ? | F56: OK
A57: prop49 | B57: Numero de contrat (natixis) (prop49) | C57: En attente | D57: A trancher (mapper ou pas) | E57: non présente, intérêt dans Adobe Analytics BPCE à challenger ? | F57: OK | H57: Disabled, utile ?
A58: prop50 | B58: Version tealium (prop50) | C58: En attente | D58: A trancher (mapper ou pas) | E58: non présente, intérêt dans Adobe Analytics BPCE à challenger ? | F58: OK
A59: prop51 | B59: Code Etablissement Page Libelle (prop51) | C59: OK | F59: OK
A60: prop52 | B60: Code banque/reseau client (prop52) | C60: OK | F60: OK
A61: prop53 | B61: ID Client Natixis Assurances (prop53) | C61: OK | F61: OK
A62: prop54 | B62: Timestamp (prop54) | C62: OK | D62: A clarifier | E62: Règle de gestion manquante | F62: OK | G62: A clarifier | H62: Règle de gestion manquante
A63: prop74 | B63: identification adresse IP (prop74) | C63: OK | D63: A clarifier | E63: Règle de gestion manquante | F63: OK | G63: A clarifier | H63: Règle de gestion manquante
A64: prop75 | B64: agregation formulaire (prop75) | C64: OK | F64: OK
A65: evar1 | B65: Code etablissement client (evar1) | C65: OK | D65: A clarifier | E65: Règle de gestion manquante | F65: OK | G65: A clarifier | H65: Règle de gestion manquante
A66: evar2 | B66: Id client (evar2) | C66: OK | D66: A clarifier | E66: Règle de gestion manquante | F66: OK | G66: A clarifier | H66: Règle de gestion manquante
A67: evar3 | B67: Statut client (evar3) | C67: OK | D67: A clarifier | E67: Règle de gestion manquante | F67: OK | G67: A clarifier | H67: Règle de gestion manquante
A68: evar4 | B68: Marché client (evar4) | C68: OK | D68: A clarifier | E68: Règle de gestion manquante | F68: OK | G68: A clarifier | H68: Règle de gestion manquante
A69: evar5 | B69: Libellé clic (evar5) | C69: OK | F69: OK
A70: evar6 | B70: Type de clic (evar6) | C70: OK | F70: OK
A71: evar7 | B71: Mot-clé recherché (evar7) | C71: OK | F71: OK | J71: Harmoniser le mapping à "Hit" pour toutes les report suite régionales
A72: evar8 | B72: Nombre de résultats de recherche (evar8) | C72: OK | F72: OK | J72: Harmoniser le mapping à "Hit" pour toutes les report suite régionales
A73: evar9 | B73: Nom du réseau social (evar9) | C73: OK | F73: OK
A74: evar10 | B74: Url du lien (evar10) | C74: OK | D74: A clarifier | E74: Règle de gestion manquante | F74: OK | G74: A clarifier | H74: Règle de gestion manquante
A75: evar11 | B75: ABTesting 1 (evar11) | C75: OK | F75: OK
A76: evar12 | B76: ABTesting 2 (evar12) | C76: OK | F76: OK
A77: evar13 | B77: Url de la page (evar13) | C77: OK | F77: OK
A78: evar14 | B78: Nom du formulaire (evar14) | C78: OK | F78: OK
A79: evar15 | B79: Libellé bloc multi panel push (evar15) | C79: Erreur | D79: A modifier | E79: Modifier en "ID étape" | F79: Erreur | G79: A modifier | H79: Modifier en "ID étape"
A80: evar16 | B80: Thème du push (prop16) | C80: OK | D80: A clarifier | E80: Règle de gestion manquante | F80: OK | G80: A clarifier | H80: Règle de gestion manquante
A81: evar17 | B81: Type de push (evar17) | C81: OK | D81: A clarifier | E81: Règle de gestion manquante | F81: OK | G81: A clarifier | H81: Règle de gestion manquante
A82: evar18 | B82: Titre du push (evar18) | C82: OK | D82: A clarifier | E82: Règle de gestion manquante | F82: OK | G82: A clarifier | H82: Règle de gestion manquante
A83: evar19 | B83: Configuration Dashboard (evar19) | C83: OK | D83: A clarifier | E83: Règle de gestion manquante | F83: OK | G83: A clarifier | H83: Règle de gestion manquante
A84: evar20 | B84: Configuration Virement (evar20) | C84: OK | D84: A clarifier | E84: Règle de gestion manquante | F84: OK | G84: A clarifier | H84: Règle de gestion manquante
A85: evar21 | B85: VIDE | C85: Erreur | D85: A corriger | E85: Variable mappée uniquement pour le réseau BP et manquante dans documentation "Nom de la publicité (prop21)" | F85: OK
A86: evar22 | B86: Type du compte (evar22) | C86: OK | D86: A clarifier | E86: Règle de gestion manquante | F86: OK | G86: A clarifier | H86: Règle de gestion manquante
A87: evar23 | B87: Type de virement (evar23) | C87: OK | F87: OK
A88: evar24 | B88: Montant du virement (evar24) | C88: OK | F88: OK
A89: evar25 | B89: Numéro de raison du message (evar25) | C89: OK | F89: OK
A90: evar26 | B90: VIDE | C90: Erreur | D90: A corriger | E90: Variable mappée uniquement pour le réseau BP et manquante dans documentation "Jour de prélèvement (prop26)" | F90: OK
A91: evar27 | B91: Nom du PDF (evar27) | C91: OK | F91: OK
A92: evar28 | B92: Formule choisie (evar28) | C92: OK | F92: OK
A93: evar29 | B93: Durée (evar29) | C93: OK | D93: A clarifier | E93: Règle de gestion manquante | F93: OK | G93: A clarifier | H93: Règle de gestion manquante
A94: evar30 | B94: Designation du véhicule (evar30) | C94: OK | D94: A conserver/supprimer (notifier Natixis Assurance) ? | F94: OK | G94: A conserver/supprimer (notifier Natixis Assurance) ?
A95: evar31 | B95: Mode de financement (evar31) | C95: OK | D95: A conserver/supprimer (notifier Natixis Assurance) ? | F95: OK | G95: A conserver/supprimer (notifier Natixis Assurance) ?
A96: evar32 | B96: Nombre de conducteurs sur simulation (evar32) | C96: OK | D96: A conserver/supprimer (notifier Natixis Assurance) ? | F96: OK | G96: A conserver/supprimer (notifier Natixis Assurance) ?
A97: evar33 | B97: Conducteur supplémentaire en conduite accompagnée (evar33) | C97: OK | D97: A conserver/supprimer (notifier Natixis Assurance) ? | F97: OK | G97: A conserver/supprimer (notifier Natixis Assurance) ?
A98: evar34 | B98: proprietaire ou locataire (evar34) | C98: OK | D98: A conserver/supprimer (notifier Natixis Assurance) ? | F98: OK | G98: A conserver/supprimer (notifier Natixis Assurance) ?
A99: evar35 | B99: je cherche a assurer (evar35) | C99: OK | D99: A conserver/supprimer (notifier Natixis Assurance) ? | F99: OK | G99: A conserver/supprimer (notifier Natixis Assurance) ?
A100: evar36 | B100: Bien en location: nb bien en location (evar36) | C100: OK | D100: A conserver/supprimer (notifier Natixis Assurance) ? | F100: OK | G100: A conserver/supprimer (notifier Natixis Assurance) ?
A101: evar37 | B101: Habitation en travaux (evar37) | C101: OK | D101: A conserver/supprimer (notifier Natixis Assurance) ? | F101: OK | G101: A conserver/supprimer (notifier Natixis Assurance) ?
A102: evar38 | B102: Valeur des capitaux mobiliers (evar38) | C102: OK | D102: A conserver/supprimer (notifier Natixis Assurance) ? | F102: OK | G102: A conserver/supprimer (notifier Natixis Assurance) ?
A103: evar39 | B103: Valeur des capitaux en objets (evar39) | C103: OK | D103: A conserver/supprimer (notifier Natixis Assurance) ? | F103: OK | G103: A conserver/supprimer (notifier Natixis Assurance) ?
A104: evar40 | B104: VIDE | C104: Vide | D104: A clarifier | E104: Variable manquante dans datalayer et règle de gestion manquante | F104: Vide
A105: evar41 | B105: Montant initial (evar41) | C105: OK | F105: OK
A106: evar42 | B106: Montant des mensualités (evar42) | C106: OK | F106: OK
A107: evar43 | B107: Taux (evar43) | C107: OK | F107: OK
A108: evar44 | B108: Nombre d'univers par visite (evar44) | C108: Erreur | D108: A clarifier | E108: Conflit entre doc datalayer et Adobe CE "Dernier univers visité (evar44)" vs "Nombre d'univers par visite (evar44)" BP | F108: Erreur | G108: A clarifier | H108: Conflit entre doc datalayer et Adobe CE "Dernier univers visité (evar44)" vs "Nombre d'univers par visite (evar44)" BP
...

Sheet Echantillon valeurs BP
B1: BP
A3: prop4 | B3: prop7 | C3: prop8 | E3: prop9 | H3: prop10 | K3: prop14 | L3: prop15 | M3: prop16 | O3: prop17 | R3: prop18 | U3: prop 19 | V3: prop 20 | W3: prop 22 | X3: prop 30 | Y3: prop 31 | Z3: evar 1 | AA3: evar 2 | AB3: evar 3 | AC3: evar 4 | AD3: evar 5 | AE3: evar 6 | AH3: evar 14 | AI3: evar 27 | AJ3: evar 30 | AK3: evar 31 | AL3: evar 32 | AM3: evar 33 | AN3: evar 34 | AO3: evar 35 | AP3: evar 36 | AQ3: evar 37 | AR3: evar 38 | AS3: evar 39 | AT3: evar 45 | AU3: evar 46 | AV3: evar 50
E4: Démêler ce qui relève du scrap, de ce qui est implémenté en dur | H4: inutilisable d'un point de vue analyse | K4: Valeurs à vocation à être adaptatives (+10K valeurs) | O4: 535 valeurs, ne correspond pas à l'attendun (probablement objet d'un scrapping) | U4: pas remontée, aucun référentiel de valeurs | V4: pas remontée, aucun référentiel de valeurs | W4: pas remontée, aucun référentiel de valeurs | X4: pas remontée, aucun référentiel de valeurs | Y4: Valeurs à vocation à être adaptatives (+10K valeurs) | Z4: ISO à prop1 | AA4: ISO à prop2 | AB4: ISO à prop3 | AC4: ISO à prop4 | AD4: Valeurs à vocation à être adaptatives (14K valeurs) | AE4: Liste de valeurs doivent être fixes, renseignées dans consolidé | AH4: ISO à prop14 | Valeurs à vocation à être adaptatives (78 valeurs, sensément exhaustives sur les applicatifs) | AI4: pas remontée, aucun référentiel de valeurs | AU4: pas remontée, aucun référentiel de valeurs | AV4: Valeurs à vocation à être adaptatives
A5: particulier | B5: selfcare | C5: particulier | D5: 15798451 | E5: accompagner | F5: 69 | G5: agences et distributeurs | H5: accueil | I5: 40206136 | J5: conseil | K5: virement | L5: 0 | M5: transactionnel | N5: 4209082103 | O5: banque à distance | P5: 410923 | Q5: assurance | R5: cyberplus | S5: 270507 | T5: assepargne | AD5: validation | AE5: navigation | AF5: 86406361 | AG5: action | AH5: virement
A6: particuliers | B6: tunnel | C6: particuliers | D6: 10828791 | E6: accueil | F6: 20665188 | G6: assistance | H6: acces et securite | I6: 24 | J6: consultation | K6: credit immo | L6: 100 | M6: Commercial | N6: 615808020 | O6: accéder à votre banque 24h24 7 jours7 | P6: 621 | Q6: bancarisation | R6: 3d secure | S6: 55 | T6: assurance 2 roues | W6: =CONCATENATE(U6," ",V6) | AD6: nouveau virement | AE6: action | AF6: 3360046 | AG6: annuler | AH6: Devis Auto
A7: fonction publique | B7: harvest | C7: fonction publique | D7: 4432834 | E7: aider et transmettre | F7: 1326 | G7: assurer | H7: accueil marche | I7: 339759 | J7: contact | K7: ajout beneficiaire | L7: 22.1 | M7: interne | N7: 12611021 | O7: accéder à votre banque 24h24 7jours7 | P7: 8555 | Q7: credit conso | R7: accompagnement de la clientele fragile financierement | S7: 579 | T7: assurance auto | W7: =CONCATENATE(U7," ",V7) | AD7: consulter notifications | AE7: validation | AF7: 2130033 | AG7: cta | AH7: rendez vous en ligne
A8: artisans commerçants | B8: store 89c3 | C8: artisans commerçants | D8: 3014242 | E8: aider protéger et transmettre | F8: 87 | G8: au quotidien | H8: accueil univers | I8: 141857 | J8: document | K8: sim credit conso | L8: … | N8: 30435 | O8: accompagnement start-up | P8: 68 | Q8: credit immo | R8: accompagnement start-up | S8: 62 | T8: assurance emprunteur | W8: =CONCATENATE(U8," ",V8) | AD8: effectuer virement externe | AE8: cta | AF8: 205393 | AG8: envoyer | AH8: credit immo
A9: gestion privée | B9: hub digital | C9: gestion privée | D9: 1651975 | E9: anticiper les imprévus | F9: 2007 | G9: banque au quotidien et assurance | H9: accueilexpertise | I9: 1 | J9: edito | K9: demande rdv | L9: … | N9: 9126 | O9: accroître la performance | P9: 47 | Q9: credit pro | R9: actiflow encaissements | S9: 107 | T9: assurance moyen paiement | W9: =CONCATENATE(U9," ",V9) | AD9: ne sais pas | AE9: ajout | AF9: 66692 | AG9: menu | AH9: …
A10: entreprises | B10: cyber | C10: entreprises | D10: 1176493 | E10: assurance | F10: 27313 | G10: connexion | H10: actualite | I10: 4929 | J10: erreur | K10: virement paylib | L10: … | N10: 2826 | O10: acheter sa résidence principale | P10: 268 | Q10: epargne financiere | R10: affinea | S10: 1988 | T10: assurance mrh | W10: =CONCATENATE(U10," ",V10) | AD10: en détail | AE10: valider | AF10: 65164 | AG10: navigation | AH10: …
A11: professions libérales | B11: ecommerce | C11: professions libérales | D11: 932918 | E11: assurer | F11: 69006 | G11: contact | H11: avis | I11: 3 | J11: faq | K11: credit pro | N11: 1846 | O11: acheter un bien immobilier | P11: 778 | Q11: epargne liquide | R11: agrilismat | S11: 362 | T11: assurance resp civile | W11: =CONCATENATE(U11," ",V11) | AD11: consulter alertes | AE11: supprimer | AF11: 9347 | AG11: plus tard | AH11: …
A12: jeunes actifs | B12: Banque Pop | C12: jeunes actifs | D12: 695743 | E12: au quotidien | F12: 3916 | G12: emprunter | H12: baseform | I12: 163289 | J12: formulaire | K12: sim auto express | N12: 1042 | O12: acheter votre résidence principale | P12: 3083 | R12: assurance auto | S12: 23657 | T12: assurance voyage | W12: =CONCATENATE(U12," ",V12) | AD12: contact conseiller email | AE12: suivant | AF12: 3942 | AG12: rechercher
A13: institutionnels | B13: deep purple | C13: institutionnels | D13: 588867 | E13: candidature | F13: 51 | G13: epargner | H13: basepageedito | I13: 17 | J13: gammes | K13: credit conso demande | N13: 706 | O13: acquérir pour louer | P13: 1072 | R13: assurance auto assur-bp auto | S13: 44 | T13: bourse | W13: =CONCATENATE(U13," ",V13) | AD13: suivant | AE13: telechargement | AF13: 3250 | AG13: sortie
A14: fonctionnaires | C14: fonctionnaires | D14: 498700 | E14: compte | F14: 469 | G14: financement | H14: beneficiaires | I14: 472151 | J14: home | K14: sim perso auto | N14: 380 | O14: acquérir votre voiture | P14: 428 | R14: assurance famille | S14: 3409 | T14: carte | W14: =CONCATENATE(U14," ",V14) | AD14: en detail | AE14: sortie | AF14: 2579 | AG14: telechargement
A15: banque privée | C15: banque privée | D15: 399238 | E15: Comptes | F15: 929421 | G15: gestion privee | H15: carte | I15: 527216 | J15: information | K15: opposition en ligne carte | N15: 374 | O15: acquisition cession transmission | P15: 29 | R15: assurance mrh | S15: 3570 | T15: cat | W15: =CONCATENATE(U15," ",V15) | AD15: historique virement | AE15: activer | AF15: 1917 | AG15: valider
A16: artisan commerçant | C16: artisan commerçant | D16: 300904 | E16: concrétiser son projet | F16: 145 | G16: ma banque pratique | H16: communique | I16: 5 | J16: marche | K16: modification email | N16: 351 | O16: activité au quotidien | P16: 18 | R16: assurance multirisque professionnelle | S16: 459 | T16: cel | W16: =CONCATENATE(U16," ",V16) | AD16: autre charge non | AE16: … | AG16: vignette
A17: service public | C17: service public | D17: 286061 | E17: connexion | F17: 569 | G17: ma synthese | H17: consultation | I17: 2924 | J17: operation | K17: sous cyberplus | N17: 299 | O17: affacturage | P17: 14 | R17: assurance obseques | S17: 568 | T17: cfn | W17: =CONCATENATE(U17," ",V17) | AD17: personnalisation label | AE17: …
A18: bfc banque privée | C18: bfc banque privée | D18: 278138 | E18: contact | F18: 106381 | G18: mes assurances | H18: contact | I18: 16722 | J18: page_ccd | K18: sous carte | N18: 116 | O18: aider mes proches | P18: 137 | R18: assurance proprietaire non occupant | S18: 406 | T18: compte-courant | W18: =CONCATENATE(U18," ",V18) | AD18: cartes et services
A19: entreprise | C19: entreprise | D19: 207726 | E19: credit | F19: 143510 | G19: mes cartes et paiement | H19: contenu animation transactionnelle | I19: 1797015 | J19: popin | K19: sim habitat express | N19: 103 | O19: aider vos proches | P19: 68 | R19: assurance rapatriement de corps | S19: 51 | T19: credit conso auto | W19: =CONCATENATE(U19," ",V19) | AD19: statut proprietaire
A20: professionnel | C20: professionnel | D20: 189990 | E20: crédit | F20: 9899 | G20: mes comptes | H20: coordonnees | I20: 88 | J20: produit | K20: sim habitat perso | N20: 42 | O20: améliorer la vie au quotidien | P20: 27 | R20: assurance responsabilite civile du celibataire | S20: 155 | T20: credit conso etudiant | W20: =CONCATENATE(U20," ",V20) | AD20: achat ancien
A21: agriculteurs | C21: agriculteurs | D21: 165032 | E21: créer | F21: 1813 | G21: mes credits | H21: coordoonnees | I21: 24048 | J21: profil | K21: sim frais notaire | N21: 29 | O21: améliorer leur quotidien | P21: 345 | R21: assurance synergie | S21: 104 | T21: credit conso travaux | W21: =CONCATENATE(U21," ",V21) | AD21: recherche
A22: enfants etudiants apprentis | C22: enfants etudiants apprentis | D22: 93562 | E22: découvrir bfc banque privée | F22: 961 | G22: messagerie | H22: credit pro | I22: 21628 | J22: recherche | K22: modification numero fixe | N22: 14 | O22: aménagement spécifique | P22: 102 | R22: assurance vehicules divers | S22: 502 | T22: credit conso tresorie | W22: =CONCATENATE(U22," ",V22) | AD22: achat maison
A23: franchise | C23: franchise | D23: 90682 | E23: défiscaliser | F23: 21 | G23: mon agence | H23: ctformcontactadvisor | I23: 2597 | J23: recherche agence | K23: en savoir plus | N23: 11 | O23: analyser votre patrimoine | P23: 44 | R23: assurance vie | S23: 74 | T23: credit immo | W23: =CONCATENATE(U23," ",V23) | AD23: …
A24: lycéens etudiants apprentis | C24: lycéens etudiants apprentis | D24: 83819 | E24: développer | F24: 87 | G24: mon coffre fort | H24: ctmobileredirect | I24: 9 | J24: univers | K24: sim cel | N24: 2 | O24: apprendre à gérer son budget | P24: 135 | R24: assurance vie horizeo | S24: 2505 | T24: credit immo primo | W24: =CONCATENATE(U24," ",V24) | AD24: …
A25: 16 ans et plus | C25: 16 ans et plus | D25: 83029 | E25: développer votre patrimoine | F25: 5522 | G25: mon epargne | H25: demo | I25: 15 | K25: sim prevoyance pro | N25: 2 | O25: apprendre à gérer votre budget | P25: 61 | R25: assur-bp auto | S25: 162 | T25: credit pro | W25: =CONCATENATE(U25," ",V25) | AD25: …
A26: 16-28 ans | C26: 16-28 ans | D26: 60594 | E26: digital briefcase | F26: 9154 | G26: mon profil | H26: detail de compte | I26: 50 | K26: sim retraite | N26: 2 | O26: assurance | P26: 310 | R26: assur-bp auto des particuliers | S26: 5775 | T26: eparfix | W26: =CONCATENATE(U26," ",V26)
A27: profession libérale | C27: profession libérale | D27: 57093 | E27: document | F27: 225867 | G27: parametres | H27: dossier client | I27: 3473 | K27: sim impot sur revenu | N27: 1 | O27: assurance de personnes | P27: 8687 | R27: assur-bp auto du pro | S27: 237 | T27: gav | W27: =CONCATENATE(U27," ",V27)
A28: jeune actif | C28: jeune actif | D28: 55926 | E28: edito | F28: 21074220 | G28: placement | H28: dossier client - produit | I28: 395 | K28: sim pel | N28: 1 | O28: assurance de responsabilité | P28: 78 | R28: assur-bp camping-car ambulance bazar forain vehicule de collection | S28: 112 | T28: internet | W28: =CONCATENATE(U28," ",V28)
A29: agriculture – viticulture | C29: agriculture – viticulture | D29: 31049 | E29: emprunter | F29: 384695 | G29: politique sociale | H29: editorial | I29: 1508572 | K29: sim madelin | N29: 1 | O29: assurance des appareils nomades | P29: 787 | R29: assur-bp enfant | S29: 1185 | T29: ldd | W29: =CONCATENATE(U29," ",V29)
A30: agriculteur viticulteur | C30: agriculteur viticulteur | D30: 29603 | E30: encaisser et payer | F30: 152 | G30: prelevements | H30: erreur | I30: 101837 | K30: souscription auto | O30: assurance des biens | P30: 201 | R30: assur-bp habitat | S30: 4326 | T30: lep | W30: =CONCATENATE(U30," ",V30)
A31: frontalier | C31: frontalier | D31: 24287 | E31: enfants | F31: 599 | G31: virements | H31: etablissement | I31: 71 | K31: sim prevoyance | O31: assurance des comptes | P31: 1471 | R31: assur-bp horizon | S31: 1045 | T31: livret a | W31: =CONCATENATE(U31," ",V31)
A32: associations et institutionnels | C32: associations et institutionnels | D32: 22608 | E32: épargne | F32: 6487 | H32: expertise | I32: 2 | K32: sim droit succession | O32: assurance des habitations | P32: 8704 | R32: assur-bp moto | S32: 481 | T32: livret b | W32: =CONCATENATE(U32," ",V32)
A33: apprentisetudiants | C33: apprentisetudiants | D33: 19019 | E33: epargner | F33: 37612 | H33: formulaire | I33: 286321 | K33: sim fiscal perp | O33: assurance des moyens de paiement | P33: 631 | R33: assur-bp sante | S33: 814 | T33: livret grand format | W33: =CONCATENATE(U33," ",V33)
A34: etudiants | C34: etudiants | D34: 18859 | E34: épargner | F34: 58453 | H34: gammes | I34: 176543 | K34: modification numero mobile | O34: assurance des personnes | P34: 782 | R34: assur-bp sante collective | S34: 50 | T34: livret grand prix | W34: =CONCATENATE(U34," ",V34)
A35: agriculteurs viticulteurs | C35: agriculteurs viticulteurs | D35: 18067 | E35: expertiser | F35: 6 | H35: historique | I35: 244219 | K35: sim isf | O35: assurance des véhicules | P35: 8898 | R35: assur-bp sante profil pro | S35: 69 | T35: livret jeune | W35: =CONCATENATE(U35," ",V35)
A36: institutionnels associations | C36: institutionnels associations | D36: 11861 | E36: financer | F36: 14566 | H36: home | I36: 13922930 | K36: sim credit immo PTZ | O36: assurance iard | P36: 27227 | R36: assurez votre activite professionnelle | S36: 42 | T36: obseques | W36: =CONCATENATE(U36," ",V36)
A37: associations | C37: associations | D37: 9774 | E37: financer vos projets | F37: 9 | H37: i-frame | I37: 2 | O37: assurance véhicules divers | P37: 74 | R37: atlantique bail plaisance | S37: 66 | T37: opcvm | W37: =CONCATENATE(U37," ",V37)
A38: jeunes adultes | C38: jeunes adultes | D38: 6942 | E38: flux | F38: 755 | H38: landing page | I38: 209 | O38: assurance vie | P38: 7377 | R38: autonomis | S38: 206 | T38: paiement | W38: =CONCATENATE(U38," ",V38)
A39: collégiens etudiants apprentis | C39: collégiens etudiants apprentis | D39: 3961 | E39: flux et trésorerie | F39: 480 | H39: page | I39: 51285 | O39: assurance vie : les atouts d un « bon contrat » | P39: 30 | R39: autorisation de decouvert | S39: 69 | T39: pea | W39: =CONCATENATE(U39," ",V39)
A40: 0-15 ans | C40: 0-15 ans | D40: 3182 | E40: gérer | F40: 64570 | H40: page daide cyber | I40: 20689 | O40: assurance vie capi pour optimiser vos placements | P40: 13 | R40: autorisation de decouvert acef | S40: 60 | T40: pel | W40: =CONCATENATE(U40," ",V40)
A41: enfants - étudiants - apprentis | C41: enfants - étudiants - apprentis | D41: 3181 | E41: gerer au quotidien | F41: 655 | H41: page darticle | I41: 2649 | O41: assurance vie et contrat de capitalisation | P41: 71 | R41: autorisations de decouvert | S41: 307 | T41: pj | W41: =CONCATENATE(U41," ",V41)
A42: PAR | C42: PAR | D42: 2680 | E42: gérer au quotidien | F42: 539822 | H42: page deconnexion | I42: 6208602 | O42: assurance vie et contrats de capitalisation | P42: 1064 | R42: avance 1ers salaires | S42: 172 | T42: retrait inter | W42: =CONCATENATE(U42," ",V42)
A43: etudiants apprentis | C43: etudiants apprentis | D43: 2633 | E43: gérer le quotidien | F43: 170 | H43: pass cyber | I43: 788797 | O43: assurances des comptes | P43: 70 | R43: avance en devises | S43: 348 | T43: sante | W43: =CONCATENATE(U43," ",V43)
A44: boutique en ligne | C44: boutique en ligne | D44: 2334 | E44: haut de bilan | F44: 68 | H44: paylib | I44: 77876 | O44: assurer la pérennité de l entreprise | P44: 30 | R44: avance premiers salaires | S44: 42 | T44: securmedia | W44: =CONCATENATE(U44," ",V44)
A45: ecoliers collégiens | C45: ecoliers collégiens | D45: 1363 | E45: hub digital b2b | F45: 3519 | H45: popin | I45: 28 | O45: assurer ses moyens de paiement | P45: 81 | R45: avance sur bourse allouee par le crous | S45: 174 | T45: visuel carte | W45: =CONCATENATE(U45," ",V45)
A46: professionels | C46: professionels | D46: 1013 | E46: immobilier | F46: 266 | H46: produit | I46: 691027 | O46: assurer son logement | P46: 159 | R46: banque a deux | S46: 72 | W46: =CONCATENATE(U46," ",V46)
A47: 0-16 ans | C47: 0-16 ans | D47: 878 | E47: ingenierie financiere | F47: 21 | H47: recherche | I47: 1 | O47: assurer son véhicule | P47: 111 | R47: banque en ligne | S47: 118079 | W47: =CONCATENATE(U47," ",V47)
A48: 12 - 18 ans | C48: 12 - 18 ans | D48: 575 | E48: ingénierie sociale | F48: 149 | H48: rubrique | I48: 4577 | O48: assurer vos appareils nomades | P48: 220 | R48: bpn’international | S48: 102 | W48: =CONCATENATE(U48," ",V48)
A49: fondation | C49: fondation | D49: 446 | E49: international | F49: 3404 | H49: section | I49: 12 | O49: assurer vos biens | P49: 584 | R49: ca do cheque culture | S49: 72 | W49: =CONCATENATE(U49," ",V49)
A50: profesionnel | C50: profesionnel | D50: 211 | E50: la fondation | F50: 72 | H50: securpass | I50: 10 | O50: assurer vos logements | P50: 1018 | R50: carte | S50: 1402 | W50: =CONCATENATE(U50," ",V50)
A51: agriculteurs-viticulteurs | C51: agriculteurs-viticulteurs | D51: 165 | E51: MesComptes | F51: 5721919 | H51: segment | I51: 2110 | O51: assurer vos moyens de paiement | P51: 2196 | R51: carte affaires mission plus | S51: 184 | W51: =CONCATENATE(U51," ",V51)
A52: start-up | C52: start-up | D52: 156 | E52: MesOperations | F52: 1035020 | H52: simulateur | I52: 9643 | O52: assurer vos moyens de paiement et vos comptes | P52: 37 | R52: carte budj | S52: 750 | W52: =CONCATENATE(U52," ",V52)
A53: institutionnel | C53: institutionnel | D53: 53 | E53: MonEspace | F53: 394753 | H53: souscription | I53: 68 | O53: assurer vos véhicules | P53: 1315 | R53: carte businesscard mastercard | S53: 63 | W53: =CONCATENATE(U53," ",V53)
A54: moins de 15 ans | C54: moins de 15 ans | D54: 32 | E54: motiver | F54: 1376 | H54: synthese | I54: 1492 | O54: assurer votre activité | P54: 1698 | R54: carte deposia | S54: 67 | W54: =CONCATENATE(U54," ",V54)
A55: ENT | C55: ENT | D55: 28 | E55: motiver et protéger | F55: 5 | H55: texte libre | I55: 30766 | O55: assurer votre logement | P55: 344 | R55: carte mastercard | S55: 2072 | W55: =CONCATENATE(U55," ",V55)
A56: jeunes | C56: jeunes | D56: 23 | E56: motiver vos collaborateurs | F56: 44 | H56: type de compte | I56: 2855 | O56: assurer votre véhicule | P56: 92 | R56: carte point argent | S56: 54 | W56: =CONCATENATE(U56," ",V56)
A57: jeune | C57: jeune | D57: 3 | E57: moyens de paiement | F57: 525078 | H57: virement | I57: 7864368 | O57: assurez-vous dès la création | P57: 25 | R57: carte point argent plus | S57: 93 | W57: =CONCATENATE(U57," ",V57)
E58: nos lauréats | F58: 34 | H58: wiki page | I58: 4329 | O58: autres cartes | P58: 15 | R58: carte visa business | S58: 739 | W58: =CONCATENATE(U58," ",V58)
E59: Operations | F59: 458773 | O59: autres moyens de paiement | P59: 3774 | R59: carte visa business electron | S59: 186 | W59: =CONCATENATE(U59," ",V59)
E60: optimiser | F60: 165 | O60: autres moyens de paiements | P60: 840 | R60: carte visa classic | S60: 10575 | W60: =CONCATENATE(U60," ",V60)
E61: optimiser vos placements | F61: 12 | O61: autres services de paiement | P61: 344 | R61: carte visa classic facelia | S61: 5576 | W61: =CONCATENATE(U61," ",V61)
E62: optimiser votre fiscalité | F62: 1526 | O62: avance | P62: 407 | R62: carte visa classic facelia voile | S62: 59 | W62: =CONCATENATE(U62," ",V62)
E63: placer | F63: 219 | O63: avantages acef | P63: 332 | R63: carte visa classic voile | S63: 53 | W63: =CONCATENATE(U63," ",V63)
E64: professionnels | F64: 59 | O64: avantages associations | P64: 251 | R64: carte visa creodis | S64: 151 | W64: =CONCATENATE(U64," ",V64)
E65: profil | F65: 24072 | O65: avantages casden | P65: 4595 | R65: carte visa electron | S65: 2854 | W65: =CONCATENATE(U65," ",V65)
E66: protéger | F66: 3808 | O66: avantages fonction publique | P66: 345 | R66: carte visa electron voile | S66: 42 | W66: =CONCATENATE(U66," ",V66)
E67: protéger et motiver | F67: 54 | O67: bancarisation | P67: 3577 | R67: carte visa gold business | S67: 480 | W67: =CONCATENATE(U67," ",V67)
E68: protéger sa famille | F68: 77 | O68: banque en ligne | P68: 18 | R68: carte visa infinite | S68: 2123 | W68: =CONCATENATE(U68," ",V68)
E69: quotidien | F69: 75081 | O69: bénéficier d un programme de fildélité | P69: 308 | R69: carte visa platinum | S69: 2836 | W69: =CONCATENATE(U69," ",V69)
E70: reglage | F70: 61503 | O70: bénéficier de solutions adaptées | P70: 35 | R70: carte visa platinum business | S70: 210 | W70: =CONCATENATE(U70," ",V70)
... E84: vous installer | F84: 78 | O84: cartes haut de gamme | P84: 29 | R84: certificat numerique certeurope | S84: 648 | W84: =CONCATENATE(U84," ",V84)
O85: cartes jeunes | P85: 2147 | R85: cesu prefinance | S85: 102 | W85: =CONCATENATE(U85," ",V85)
O86: cartes voile | P86: 467 | R86: change dynamique | S86: 131 | W86: =CONCATENATE(U86," ",V86)
O87: cat | P87: 131 | R87: cheque de banque | S87: 246 | W87: =CONCATENATE(U87," ",V87)
O88: caution bancaire | P88: 31 | R88: chequier | S88: 291 | W88: =CONCATENATE(U88," ",V88)
O89: caution de marche | P89: 21 | R89: choisir un terminal de paiement tpe | S89: 122 | W89: =CONCATENATE(U89," ",V89)
O90: centralisation des flux | P90: 98 | R90: choix utilisateur | S90: 341 | W90: =CONCATENATE(U90," ",V90)
O91: centraliser vos flux | P91: 130 | R91: choozeo | S91: 81 | W91: =CONCATENATE(U91," ",V91)
O92: changer de banque | P92: 1239 | R92: codevair | S92: 1147 | W92: =CONCATENATE(U92," ",V92)
O93: choisir ma carte de paiement | P93: 358 | R93: codevair tria | S93: 197 | W93: =CONCATENATE(U93," ",V93)
O94: choisir vos services liés aux cartes | P94: 24 | R94: coffre-fort numerique | S94: 468 | W94: =CONCATENATE(U94," ",V94)
O95: choisir votre carte | P95: 383 | R95: compte a terme | S95: 1848 | W95: =CONCATENATE(U95," ",V95)
O96: comité d entreprise | P96: 128 | R96: compte a terme cash boost | S96: 56 | W96: =CONCATENATE(U96," ",V96)
... O104: constituer votre patrimoine immobilier | P104: 95 | R104: compte sur livret casden | S104: 701 | W104: =CONCATENATE(U104," ",V104)
G105: 6 | O105: convention de compte | P105: 65 | R105: comptes a terme rythmic | S105: 114 | W105: =CONCATENATE(U105," ",V105)
O106: convention de comptes | P106: 46 | R106: compte-titres ordinaire | S106: 348 | W106: =CONCATENATE(U106," ",V106)
O107: convention de relation | P107: 76 | R107: compte-titres ordinaire - cto | S107: 105 | W107: =CONCATENATE(U107," ",V107)
O108: conventions | P108: 6872 | R108: contrat de prevoyance fructi-professionnel | S108: 78 | W108: =CONCATENATE(U108," ",V108)
O109: conventions de compte | P109: 988 | R109: contrat de retraite fructi-professionnel | S109: 172 | W109: =CONCATENATE(U109," ",V109)
O110: conventions de relation | P110: 193 | R110: convention a 1 € | S110: 64
O111: couvrir vos risques | P111: 14 | R111: convention affinea | S111: 1493
O112: cr��dit bail et location | P112: 33 | R112: convention frequence asso | S112: 93
O113: creance net | P113: 96 | R113: convention jeunes | S113: 86
O114: crédit | P114: 573 | R114: couverture de change... | S114: 48
O115: crédit bail et location | P115: 68 | R115: creanceplus | S115: 47
O116: credit conso | P116: 58982 | R116: creancepro tempo | S116: 76
O117: credit immo | P117: 205801 | R117: credit a linnovation innovplus | S117: 246
O118: credit pro | P118: 13544 | R118: credit a taux fixe | S118: 5307
O119: crédit renouvelable | P119: 234 | R119: credit a taux variable | S119: 178
O120: crédit-bail et location | P120: 201 | R120: credit bail immobilier banque populaire lease immo | S120: 100
O121: crédits immobiliers | P121: 13783 | R121: credit conso auto | S121: 10509
...

Sheet Datalayer BPCE vdef
A2: En cours de modification par Charlotte et Agathe (01/04/2020)
A6: Colonne2 | B6: ID | C6: Numéro variable AA | D6: Nom | E6: Description | F6: Présence d'une extension ou transco Tealium | G6: Statut | H6: Action | I6: Type de variable | J6: Variable datalayer | K6: Nomenclature datalayer | L6: Variable cookie | M6: Règle Tealium | N6: Scope evar | O6: Allocation | P6: Commentaire | Q6: Valeurs | R6: Classification | S6: Commentaire BP Hortense | T6: web composant transverse & datalayer 89c3 | U6: web CE | V6: web BP | W6: application CE | X6: application BP | Y6: Propiété | Z6: variable | AA6: Description2 | AB6: Description3 | AC6: Description4 | AD6: Description5 | AE6: Description6 | AF6: Description7 | AG6: Description8 | AH6: Description9 | AI6: Description10 | AJ6: Description11
A7: 1 | B7: Custom variable #1 | C7: prop1 | D7: Code Etablissement Client (prop1) | F7: X | G7: Validée | I7: Datalayer | N7: hit | T7: clients.idEnttGrpe | U7: client.idEnttGrpe | V7: clients.idEnttGrpe | W7: clients.idEnttGrpe | X7: clients.idEnttGrpe | Y7: clients | Z7: idEnttGrpe | AA7: "Contient le Code Etablissement de rattachement du Client (code interbancaire (CE) ou COTEB (BP) caractères), vide si prospect Règle de gestion : - récupération via BAPI - si BAPI pas présente/utilisable, récupération via un cookie (cookie le + récent) 1) CE : nom du cookie = ""ez_track"" et ""EZ_CONTEXTE"" et les valeurs sont : en mode identifié : ez_track = creg%3D{ne pas prendre}%26nab%3D%26nodape%3D{idclient} EZ_CONTEXTE = mar%3D{marcheclient}%26reg%3D{codeetablissement} en mode authentifié : cmar%3D{marcheclient}%26creg%3D{codeetablissement}%26nab%3D11a7723955fd8e2bba6a87cb42dd18dc%26nodape%3D{idclient} ex:ez_track identifié : creg%3D11315%26nab%3D48543044ddffb3ec7177aec5154655b9%26nodape%3D907562536 ez_track authentifié : cmar%3D101%26creg%3D17515%26nab%3D11a7723955fd8e2bba6a87cb42dd18dc%26nodape%3D065584064 EZ_CONTEXTE : mar%3D101%26reg%3D17515 2) BP : Il s’agit du cookie « tealiumClientDataCookie », dont la valeur correspond à : idclient-marche- idEnttGrpe"
A8: 2 | B8: Custom variable #2 | C8: prop2 | D8: Id Client (prop2) | F8: X | G8: Documentation à modifier (89c3 - performance digitale) | I8: Datalayer | N8: hit | T8: clients.id | U8: client.id | V8: clients.id | W8: clients.clientid | X8: clients.clientid | Y8: clients | Z8: clientid | AA8: "Identifiant validé juridiquement et au niveau de la sécurité comme donnée non personnelle et non sensible qui peut être envoyé à des prestataires externes pour des campagnes marketing digital. CE : contient l’identifiant Client MySys (NODAPE) du client authentifié ou identifié. Donnée numérique sur 7 ou 9 caractères contenant les « 0 » non significatifs. BP : COTE identifiant numérique sur 10 caractères Règle de gestion : - récupération via BAPI - si BAPI pas présente, récupération via un cookie (cookie le + récent) 1) CE : nom du cookie = ""ez_track"" et ""EZ_CONTEXTE"" et les valeurs sont : en mode identifié : ez_track = creg%3D{ne pas prendre}%26nab%3D%26nodape%3D{idclient} EZ_CONTEXTE = mar%3D{marcheclient}%26reg%3D{codeetablissement} en mode authentifié : cmar%3D{marcheclient}%26creg%3D{codeetablissement}%26nab%3D11a7723955fd8e2bba6a87cb42dd18dc%26nodape%3D{idclient} ex:ez_track identifié : creg%3D11315%26nab%3D48543044ddffb3ec7177aec5154655b9%26nodape%3D907562536 ez_track authentifié : cmar%3D101%26creg%3D17515%26nab%3D11a7723955fd8e2bba6a87cb42dd18dc%26nodape%3D065584064 EZ_CONTEXTE : mar%3D101%26reg%3D17515 2) BP : Il s’agit du cookie « tealiumClientDataCookie », dont la valeur correspond à : idclient-marche- idEnttGrpe"
A9: 3 | B9: Custom variable #3 | C9: prop3 | D9: Statut Client (prop3) | G9: Validée | H9: X | I9: Datalayer | N9: hit | T9: clients.status | U9: client.statut | V9: clients.statut | W9: clients.statut | X9: clients.statut ET clients.clientStatus | Y9: clients | Z9: statut | AA9: "Contient le niveau de connaissance du client. Authentifié = logué dans la session Identifié = logué dans une session antérieure Prospect = jamais connecté côté CE - Authentifié : cookie ez-track est présent et le cookie SES est présent et possède la valeur auth=1  renvoyer les valeurs du cookie ez-track selon le découpage en règle de gestion sharepoint pour prop1, 2, 4 et pour prop3 valoriser en dur « authentifié » - Identifié : cookie ez-track est présent et le cookie SES est présent et possède la valeur auth=0  renvoyer les valeurs du cookie ez-track selon le découpage en règle de gestion sharepoint pour prop1, 2, 4 et pour prop3 valoriser en dur « identifié » - Prospect : cookie ez-track n’existe pas  ne pas valoriser prop1, 2, 4, mais valoriser prop3 en dur à « prospect » Côté BP - Authentifié : cookie TealiumIDUser est présent et tealiumClientDatacookie présent  renvoyer les valeurs du cookie tealiumClientDatacookie selon le découpage en règle de gestion sharepoint pour prop1, 2, 4 et pour prop3 valoriser en dur « authentifié » - Identifié : cookie tealiumClientDatacookie est présent et TealiumIDUser absent  renvoyer les valeurs du cookie tealiumClientDatacookie selon le découpage en règle de gestion sharepoint pour prop1, 2, 4 et pour prop3 valoriser en dur « identifié » - Prospect : cookie TealiumIDUser et tealiumClientDataCookie ne sont pas présents  ne pas valoriser prop1, 2, 4, mais valoriser prop3 en dur à « prospect » "
A10: 4 | B10: Custom variable #4 | C10: prop4 | D10: Marché Client (prop4) | F10: X | I10: Datalayer | N10: hit | T10: clients.marche | U10: client.marche | V10: clients.marche | W10: clients.marche | X10: clients.marche | Y10: clients | Z10: marche | AA10: "Contient le marché du client authentifié ou identifié, vide si prospect Règle de gestion : - récupération via BAPI - si BAPI pas présente, récupération via un cookie (cookie le + récent) 1) CE : nom du cookie = ""ez_track"" et ""EZ_CONTEXTE"" et les valeurs sont : en mode identifié : ez_track = creg%3D{ne pas prendre}%26nab%3D%26nodape%3D{idclient} EZ_CONTEXTE = mar%3D{marcheclient}%26reg%3D{codeetablissement} en mode authentifié : cmar%3D{marcheclient}%26creg%3D{codeetablissement}%26nab%3D11a7723955fd8e2bba6a87cb42dd18dc%26nodape%3D{idclient} ex:ez_track identifié : creg%3D11315%26nab%3D48543044ddffb3ec7177aec5154655b9%26nodape%3D907562536 ez_track authentifié : cmar%3D101%26creg%3D17515%26nab%3D11a7723955fd8e2bba6a87cb42dd18dc%26nodape%3D065584064 EZ_CONTEXTE : mar%3D101%26reg%3D17515 2) BP : Il s’agit du cookie « tealiumClientDataCookie », dont la valeur correspond à : idclient-marche- idEnttGrpe"
A11: 5 | B11: Custom variable #5 | C11: prop5 | D11: Code réduit Etablissement de la page (prop5) | F11: X | G11: Documentation à modifier (89c3 - performance digitale) | I11: Datalayer | N11: hit | T11: pages.CodeEnttGrpe | U11: page.CodeEnttGrpe | V11: pages.CodeEnttGrpe | W11: pages.codeEnttGrpe | X11: pages.codeEnttGrpe | Y11: pages | Z11: CodeEnttGrpe | AA11: "Code réduit de l'établissement de rattachement de la page Format : - 5 lettres pour CE (CEPAC, CEAULS...) - 3 chiffres pour BP (038, 552...)"
A12: 6 | B12: Custom variable #6 | C12: prop6 | D12: Type Applicatif (prop6) | G12: Validée | I12: Datalayer | N12: hit | T12: pages.applicationType | U12: page.applicationType | V12: pages.applicationType | W12: pages.applicationType | X12: pages.applicationType | Y12: pages | Z12: applicationType | AA12: Permet de distinguer de le type d'applicatif à l'origine du tag
A13: 7 | B13: Custom variable #7 | C13: prop7 | D13: Nom de l applicatif (prop7) | G13: Validée | I13: Datalayer | N13: hit | T13: pages.applicationName | U13: page.applicationName | V13: pages.applicationName | W13: pages.applicationName | X13: pages.applicationName | Y13: pages | Z13: applicationName | AA13: Permet de distinguer de quel applicatif provient le tag
A14: 8 | B14: Custom variable #8 | C14: prop8 | D14: Marché de navigation (prop8) | G14: Validée | H14: ? | I14: Datalayer | N14: hit | T14: pages.marche | U14: page.marche | V14: pages.marche | W14: pages.marche | X14: pages.marche | Y14: pages | Z14: marche | AA14: Correspond au marché en cours lors de la navigation
A15: 9 | B15: Custom variable #9 | C15: prop9 | D15: Univers de Navigation (prop9) | G15: Documentation à modifier (89c3 - performance digitale) | H15: Catégorisations à préciser | I15: Datalayer | N15: hit | P15: 88 valeurs, ne correspondant pas à l'attendu (probablement objet d'un scrapping) | S15: ok | T15: pages.univers | U15: page.univers | V15: pages.univers | W15: pages.univers | X15: pages.univers | Y15: pages | Z15: univers | AA15: Nom de l’univers en cours lors de la navigation (nom de l'onglet de navigation)
A16: 10 | B16: Custom variable #10 | C16: prop10 | D16: Type de la page (prop10) | G16: Documentation à modifier (89c3 - performance digitale) | H16: Catégorisations à préciser | I16: Datalayer | N16: hit | P16: inutilisable d'un point de vue analyse à cause de la diversité des valeurs | S16: ok | T16: pages.pageType | U16: page.pageType | V16: pages.pageType | W16: pages.pageType | X16: pages.pageType | Y16: pages | Z16: pageType | AA16: Type de la page
A17: 11 | B17: Custom variable #11 | C17: prop11 | D17: is ABTesting (prop11) | G17: Validée | I17: Kameleoon | N17: hit | S17: ok | T17: NA | U17: NA | V17: NA | W17: NA | X17: NA | AA17: ABTesting : nom du test ab - variable remplie par Kameleoon
A18: 12 | B18: Custom variable #12 | C18: prop12 | D18: Id ABTesting(prop12) | G18: Validée | I18: Kameleoon | N18: hit | T18: NA | U18: NA | V18: NA | W18: NA | X18: NA | AA18: ABTesting : nom du test ab - variable remplie par Kameleoon
A19: 13 | B19: Custom variable #13 | C19: prop13 | D19: Url de la page (prop13) | G19: Validée | I19: Tealium | N19: hit | P19: Variable Tealium pas implémentée partout | S19: ok | T19: NA | U19: NA | V19: NA | W19: NA | X19: NA | AA19: Url de la Page
A20: 14 | B20: Custom variable #14 | C20: prop14 | D20: Nom du Formulaire (prop14) | G20: Validée | I20: Datalayer | N20: hit | P20: Variable pas implémentée partout | S20: ok | T20: form.nom | U20: form.nom | Y20: form | Z20: nom | AA20: Nom du formulaire
A21: 15 | B21: Custom variable #15 | C21: prop15 | D21: Identifiant etape Formulaire (prop15) | G21: Validée | I21: Datalayer | N21: hit | P21: Valeurs à vocation à être adaptative | S21: ok | T21: form.idEtape | U21: form.idEtape | Y21: form | Z21: idEtape | AA21: Identifiant étape
A22: 16 | B22: Custom variable #16 | C22: prop16 | D22: Objet de l applicatif (prop16) | G22: Validée | I22: Datalayer | N22: hit | P22: Variable pas implémentée partout, action côté webmestres et côté développeurs pour remplir les champs CMS ou les projets | S22: : Nous avons très peu de codes produits qui remontent seulement 1 par produit en semaine ? | T22: pages.espace | U22: page.espace | V22: pages.espace | W22: pages.espace | X22: pages.espace | Y22: pages | Z22: espace | AA22: Type de l'application (commercial = portail, transactionnel = espace connecté)
A23: 17 | B23: Custom variable #17 | C23: prop17 | D23: Gamme de produit de Navigation (prop17) | G23: Documentation à modifier (89c3 - performance digitale) | H23: Catégorisations à préciser, règle de gestion à renseigner | I23: Datalayer | N23: hit | P23: Variable pas implémentée partout, action côté webmestres et côté développeurs pour remplir les champs CMS ou les projets | S23: Pas de données | T23: produits.gamme | U23: produit.gamme | V23: produits.gamme | Y23: produits | Z23: gamme | AA23: Gamme de produit dont traite la page (au sens métier) (liste non exhaustive)
A24: 18 | B24: Custom variable #18 | C24: prop18 | D24: Code Produit de navigation (prop18) | G24: Documentation à modifier (89c3 - performance digitale) | H24: Catégorisations à préciser, règle de gestion à renseigner | I24: Datalayer | N24: hit | P24: Variable pas implémentée partout, action côté webmestres et côté développeurs pour remplir les champs CMS ou les projets | S24: ok | T24: produits.code | U24: produit.code | V24: produits.code | Y24: produits | Z24: code | AA24: Code du produit dont traite la page (au sens métier) (liste non exhaustive)
A25: 20 | B25: Custom variable #20 | C25: prop24 | D25: type de dossier (prop20) | G25: Validée | I25: Datalayer | N25: hit | T25: pages.TypeDossier | U25: page.TypeDossier | Y25: pages | Z25: TypeDossier | AA25: Type de dossier selectionné dans le portail KYC- connaissance client
A26: 21 | B26: Custom variable #21 | C26: prop31 | D26: Page | G26: Validée | H26: OK Octobre 2019 | I26: Tealium | N26: hit | T26: NA | U26: NA | V26: NA | W26: NA | X26: NA | Y26: pages | Z26: pageName | AA26: Page pour les clics, ne pas implémenter sur les évènements pages vues, implémenter uniquement sur les click event.
A27: 22 | B27: Custom variable #22 | C27: prop32 | D27: Pagename page précédente (prop32) | G27: Validée | I27: Tealium | N27: hit | T27: NA | U27: NA | V27: NA | W27: NA | X27: NA | AA27: Donne le pagename précédent sur les évènements de page, et donne le pagename de navigation pour un click event. Ne fonctionne pas sur les parcours non passés sous Tealium.
A28: 23 | B28: Custom variable #23 | C28: prop35 | D28: Nombre de cartes actives differentes (prop35) | G28: Validée | I28: Datalayer | N28: hit | T28: custom.NombreCartesActives | V28: custom.NombreCartesActives | W28: custom.NombreCartesActives | X28: custom.NombreCartesActives | Y28: custom | Z28: NombreCartesActives | AA28: (pilotage de la carte) deep purple - page carrousel
A29: 24 | B29: Custom variable #24 | C29: prop36 | D29: Nombre de cartes opposées différentes (prop36) | G29: Validée | I29: Datalayer | N29: hit | T29: custom.NombreCartesOpposees | V29: custom.NombreCartesOpposees | W29: custom.NombreCartesOpposees | X29: custom.NombreCartesOpposees | Y29: custom | Z29: NombreCartesOpposees | AA29: (pilotage de la carte) deep purple - page carrousel
A30: 25 | B30: Custom variable #25 | C30: prop37 | D30: Nombre de cartes commandées ou expédiées (prop37) | G30: Validée | I30: Datalayer | N30: hit | T30: custom.NombreCartesCommandees | V30: custom.NombreCartesCommandees | W30: custom.NombreCartesCommandees | X30: custom.NombreCartesCommandees | Y30: custom | Z30: NombreCartesCommandees | AA30: (pilotage de la carte) deep purple - page carrousel
A31: 26 | B31: Custom variable #26 | C31: prop38 | D31: Nombre de cartes actives et verrouillées temporairement (prop38) | G31: Validée | I31: Datalayer | N31: hit | T31: custom.NombreCartesVerrouilleesTemp | V31: custom.NombreCartesVerrouilleesTemp | W31: custom.NombreCartesVerrouilleesTemp | X31: custom.NombreCartesVerrouilleesTemp | Y31: custom | Z31: NombreCartesVerrouilleesTemp | AA31: (pilotage de la carte) deep purple - page carrousel
A32: 27 | B32: Custom variable #27 | C32: prop39 | D32: Nombre de cartes actives et paiements en ligne désactivés (prop39) | G32: Validée | I32: Datalayer | N32: hit | T32: custom.NombreCartesPaiementDistanceOFF | V32: custom.NombreCartesPaiementDistanceOFF | W32: custom.NombreCartesPaiementDistanceOFF | X32: custom.NombreCartesPaiementDistanceOFF | Y32: custom | Z32: NombreCartesPaiementDistanceOFF | AA32: (pilotage de la carte) deep purple - page carrousel
A33: 28 | B33: Custom variable #28 | C33: prop40 | D33: Nombre de cartes actives et paiements a l etranger desactivés (prop40) | G33: Validée | I33: Datalayer | N33: hit | T33: custom.NombreCartesPaiementEtrangerOFF | V33: custom.NombreCartesPaiementEtrangerOFF | W33: custom.NombreCartesPaiementEtrangerOFF | X33: custom.NombreCartesPaiementEtrangerOFF | Y33: custom | Z33: NombreCartesPaiementEtrangerOFF | AA33: (pilotage de la carte) deep purple - page carrousel
A34: 29 | B34: Custom variable #29 | C34: prop41 | D34: Nombre de cartes enrolement | G34: Validée | I34: Datalayer | N34: hit | T34: custom.NbCartesEnrolement | V34: custom.NbCartesEnrolement | W34: custom.NbCartesEnrolement | X34: custom.NbCartesEnrolement | Y34: custom | Z34: NbCartesEnrolement | AA34: (pilotage de la carte) deep purple - page choix des cartes à enroler (parcours enrolement paylib)
A35: 30 | B35: Custom variable #30 | C35: prop45 | D35: Total nombre de compte détenus | G35: Validée | I35: Datalayer | N35: hit | T35: custom.nombreComptes | U35: custom.nombreComptes | V35: custom.nombreComptes | W35: custom.nombreComptes | X35: custom.nombreComptes | Y35: custom | Z35: nombreComptes | AA35: selfcare: page synthese, remonte le nombre de compte détenus par l'utilisateur (courant, epargne, financiere)
A36: 31 | B36: Custom variable #31 | C36: prop47 | D36: libelle transaction incorrect | G36: Validée | I36: Datalayer | N36: hit | T36: custom.libelleIncorrect | U36: custom.libelleIncorrect | V36: custom.libelleIncorrect | W36: custom.libelleIncorrect | X36: custom.libelleIncorrect | Y36: custom | Z36: libelleIncorrect | AA36: Mes Comptes : sur ecran detail d'une transaction, si l'user clique sur "libelle erroné", remonte les 5 qualificatifs suivants[ [originalText;sub_text;transactionTypeCode; external_merchant_identifier; transaction_date]
A37: 32 | B37: Custom variable #32 | C37: prop48 | D37: switch | G37: Validée | H37: Préciser la description | I37: Datalayer | N37: hit | T37: custom.switch | U37: custom.switch | V37: custom.switch | W37: custom.switch | X37: custom.switch | Y37: custom | Z37: switch | AA37: securpass enrolement - choix on ou off sur la page "enrolement - [touch id/fingerprint/faceid]
A38: 33 | B38: Custom variable #33 | C38: prop49 | D38: numero de contrat (natixis) | G38: Validée | H38: Préciser la description | I38: Non défini ou implémenté | N38: hit | T38: custom.numeroContrat | U38: custom.numeroContrat | V38: custom.numeroContrat | W38: custom.numeroContrat | X38: custom.numeroContrat | Y38: custom | Z38: numeroContrat | AA38: (parcours natixis virement credit renouvelable) pousser le numero de contrat associé au credit renouvelable du client en question (id coté natixis)
A39: 34 | B39: Custom variable #34 | C39: prop50 | D39: version tealium | G39: Validée | H39: Préciser la description | I39: Tealium | N39: hit | T39: NA | U39: NA | V39: NA | W39: NA | X39: NA | AA39: Variable générée par Tealium (pas datalayer). Concatène le nom du compte Tealium, le profil, l'environnement et la version pour chaque hit. Permet de vérifier le déploiement correct de Tealium et de pointer une version particulière en cas de bug
A40: 40 | B40: Custom variable #35 | C40: prop51 | D40: Code établissement page (prop51) | G40: Validée | H40: Préciser la description | I40: Datalayer | N40: hit | T40: NA | U40: NA | V40: NA | W40: NA | X40: NA | Y40: custom | AA40: Correspond au code établissement de rattachement de client en Lettres
A41: 35 | B41: Custom variable #36 | C41: prop52 | D41: Code banque/reseau client (prop52) | G41: Validée | H41: Préciser la description | I41: Tealium | N41: hit | P41: Mettre à jour documentation (Natixis ?) | T41: clients.idGrpe | U41: clients.idGrpe | V41: clients.idGrpe | W41: clients.idGrpe | X41: clients.idGrpe | Y41: clients | Z41: idGrpe
A42: 36 | B42: Custom variable #37 | C42: prop53 | D42: ID Client Natixis Assurances (prop53) | G42: Validée | H42: Préciser la description | I42: Non défini ou implémenté | N42: hit | P42: Mettre à jour documentation (Natixis ?) | T42: clients.idClientNxs | U42: clients.idClientNxs | V42: clients.idClientNxs | W42: clients.idClientNxs | X42: clients.idClientNxs | Y42: clients | Z42: idClientNxs
A43: 37 | B43: Custom variable #38 | C43: prop54 | D43: Timestamp | G43: Validée | H43: Préciser la description | I43: Non défini ou implémenté | N43: hit | T43: NA | U43: NA | V43: NA | W43: NA | X43: NA | AA43: Date et heure du hit
A44: 38 | B44: Custom variable #39 | C44: prop74 | D44: type opposition identification adresse IP | G44: Validée | H44: Préciser la description | I44: Tealium | N44: hit | P44: Revoir la pertinence métiers à long terme (IP dynamiques pour collaborateurs) | T44: custom.typeOpposition | U44: custom.typeOpposition | V44: custom.typeOpposition | W44: custom.typeOpposition | X44: custom.typeOpposition | Y44: custom | Z44: typeOpposition | AA44: Permet d'identifier les groupes d'IP à inclure/exclure des analyses
A45: 39 | B45: Custom variable #40 | C45: prop75 | D45: agregation formulaire | G45: Validée | H45: Préciser la description | I45: Datalayer | N45: hit | T45: custom.aggregation | U45: custom.aggregation | V45: custom.aggregation | W45: custom.aggregation | X45: custom.aggregation | Y45: custom | Z45: agregation | AA45: aggrégation des champs qui sont choisis dans un formulaire par les métiers
A46: 41 | B46: Custom variable #41 | C46: evar1 | D46: Code Etablissement Client (evar1) | G46: Validée | H46: Demander à Natixis de gérer les transco dans Tealium | I46: Tealium | N46: hit | P46: "Pb sur le parcours sous conso avec les codes finissant par un 7 BP : -Unspecified sur certaines applicatifs (tunnel / ecommerce / digital briefcase / Turbo SE pour le desktop | selfcare / Deep purple / cyber pour appli) - Code à 5 chiffres qui remontent sur Turbo / tunnel)" | T46: NA | U46: NA | V46: NA | W46: NA | X46: NA | Y46: clients | Z46: idEnttGrpe | AA46: Contient le Code Etablissement de rattachement du Client (5 (CE) ou 3 (BP) caractères), vide si prospect
A47: 42 | B47: Custom variable #42 | C47: evar2 | D47: Id Client (evar2) | G47: Validée | H47: Créer les tickets d'anos selon les commentaires | I47: Tealium | N47: hit | P47: "Sur mobile : - si prospect remonte unspecified - si identifié remonte N/A (au lieu de l'identifiant) - si IOS remonte undefined (cause pb client id identifié) Sur le web : - si prospect - DEM remonte s/o - Tunnel remonte 0000000 - si identifie remonte unspecified sur ecommerce et cenet (au lieu de l'identifiant) BP : '"" 0000000 "" au lieu d'absence de valeur pour les applicatifs tunnel et ecommerce" | T47: NA | U47: NA | V47: NA | W47: NA | X47: NA | Y47: clients | Z47: id | AA47: Identifiant validé juridiquement et au niveau de la sécurité comme donnée non personnelle et non sensible qui peut être envoyé à des prestataires externes pour des campagnes marketing digital. CE : contient l’identifiant Client MySys (NODAPE) du client authentifié ou identifié. Donnée numérique sur 7 ou 9 caractères contenant les « 0 » non significatifs. BP : identifiant à définir
A48: 43 | B48: Custom variable #43 | C48: evar3 | D48: Statut Client (evar3) | G48: Validée | H48: Créer les tickets d'anos selon les commentaires | I48: Tealium | N48: hit | P48: "sur mobile : - [dynamique] sur pages pulsar Web : - Unspecified sur rendez en ligne BP : - [""dynamique""] sur l'appli" | T48: NA | U48: NA | V48: NA | W48: NA | X48: NA | Y48: clients | Z48: statut | AA48: Contient le niveau de connaissance du client. Authentifié = logué dans la session Identifié = logué dans une session antérieure Prospect = jamais connecté
A49: 44 | B49: Custom variable #44 | C49: evar4 | D49: Marché Client (evar4) | G49: Validée | H49: Créer les tickets d'anos selon les commentaires | I49: Tealium | N49: hit | P49: "mobile - pulsar remonte particulier - historique remonte profesionnels Web - ecommerce remonte 101 ... BP : - s/o sur tunnel - Particuliers sur les simulateurs auto et habitations Desktop et dur DP Appli - entreprises et professionnels sur le hub digital - ""Type inconnu"" sur ecommerce - PAR et ENT sur certaines pages Appli Banque Pop - profesionnel sur certaines pages appli BP" | T49: NA | U49: NA | V49: NA | W49: NA | X49: NA | Y49: clients | Z49: marche | AA49: Contient le marché du client authentifié ou identifié, vide si prospect
A50: 45 | B50: Custom variable #45 | C50: evar5 | D50: Libellé Clic (evar5) | G50: Validée | H50: Créer les tickets d'anos selon les commentaires | I50: Datalayer | N50: hit | T50: clics.libelle | U50: clic.libelle | V50: clics.libelle | W50: clic.libelle | X50: clic.libelle | Y50: clics | Z50: libelle | AA50: Nom du clic
A51: 46 | B51: Custom variable #46 | C51: evar6 | D51: Type de Clic (evar6) | G51: Validée | H51: Proposer des catefs de clics (LP, nouveau portail, parcours similaires) pour faire des benchs de taux de clics | I51: Datalayer | N51: hit | P51: BP : Sur l'appli, même valeur que libellé clic | T51: clics.type | U51: clic.type | V51: clics.type | W51: clic.type | X51: clic.type | Y51: clics | Z51: type | AA51: Type de clic
A52: 47 | B52: Custom variable #47 | C52: evar7 | D52: Mot-Clé recherché (evar7) | G52: Validée | H52: OK Octobre 2019 | I52: Tealium ou Datalayer | N52: hit | U52: search.keyword | AA52: Recherche - Mot clé recherché
A53: 48 | B53: Custom variable #48 | C53: evar8 | D53: Nombre de résultats de recherche (evar8) | G53: A implémenter (89c3 - Quentin) | H53: BP et CE | I53: Tealium | N53: hit | U53: search.notFound | Y53: search | Z53: notFound | AA53: Recherche - Nombre de résultats
A54: 49 | B54: Custom variable #49 | C54: evar10 | D54: Url du lien (evar10) | G54: A implémenter (89c3 - Quentin) | H54: BP et CE | I54: Tealium | N54: hit | P54: "seulement 50 résultats sur le web 0 sur le mobile" | U54: clics.url | Y54: clics | Z54: url | AA54: URL du lien
A55: 50 | B55: Custom variable #50 | C55: evar11 | D55: ABTesting 1 (eVar11) | G55: Validée | I55: Kameleoon | N55: hit | T55: NA | U55: NA | V55: NA | W55: NA | X55: NA | AA55: ABTesting : nom du test ab - variable remplie par Kameleoon
A56: 51 | B56: Custom variable #51 | C56: evar12 | D56: ABTesting 2 (evar12) | G56: Validée | I56: Kameleoon | N56: hit | T56: NA | U56: NA | V56: NA | W56: NA | AA56: AB Testing : nom de la variation de l'ab test - variable remplie par Kameleoon
A57: 52 | B57: Custom variable #52 | C57: evar13 | D57: Url de la page (evar13) | G57: Validée | I57: Tealium | N57: hit | T57: NA | U57: NA | V57: NA | W57: NA | X57: NA | AA57: Url de la Page
A58: 53 | B58: Custom variable #53 | C58: evar14 | D58: Nom du formulaire (evar14) | G58: Validée | H58: Demander si utilité du doublon en prop, si non ==> supprimer prop | I58: Adobe Analytics ou Tealium | N58: hit | T58: form.nom | U58: form.nom | Y58: form | Z58: nom | AA58: Nom du formulaire
A59: 54 | B59: Custom variable #54 | C59: evar15 | D59: Identifiant étape (evar15) | G59: Validée | H59: Demander si utilité du doublon en prop, si non ==> supprimer prop | I59: Adobe Analytics ou Tealium | N59: hit | P59: Mauvais nom, étape formulaire | T59: form.idEtape | U59: form.idEtape | Y59: form | Z59: idEtape | AA59: Push - libellé bloc gamme
A60: 55 | B60: Custom variable #55 | C60: evar22 | D60: Type du compte (evar22) | G60: Validée | I60: Datalayer | N60: hit | T60: . | U60: . | AA60: Libellé du compte sans info personnelle (CDD, AssVie,…)
A61: 56 | B61: Custom variable #56 | C61: evar23 | D61: Type de virement (evar23) | G61: Validée | I61: Datalayer | N61: hit | T61: custom.typeVirement | U61: custom.typeVirement | Y61: custom | Z61: typeVirement | AA61: Type de virement (externe ou interne)
A62: 57 | B62: Custom variable #57 | C62: evar24 | D62: Montant du virement (evar24) | G62: Validée | I62: Datalayer | N62: hit | T62: custom.montantVirement | U62: custom.montantVirement | Y62: custom | Z62: montantVirement | AA62: Montant du virement
A63: 58 | B63: Custom variable #58 | C63: evar25 | D63: Numéro de Raison du message (evar25) | G63: A implémenter (89c3 - MT) | H63: Modifier le nom et créer l'ano pour corriger | I63: Datalayer | N63: hit | T63: . | U63: . | AA63: Numéro de Raison du message
A64: 59 | B64: Custom variable #59 | C64: evar27 | D64: Nom du PDF (evar27) | G64: Validée | I64: Datalayer | N64: hit | T64: doc.name | U64: doc.name | Y64: doc | Z64: name | AA64: Nom du PDF
A65: 60 | B65: Custom variable #60 | C65: evar28 | D65: Formule choisie (evar28 | G65: Validée | I65: Datalayer | N65: hit | T65: . | U65: . | AA65: Formule choisie
A66: 61 | B66: Custom variable #61 | C66: evar29 | D66: Montant de la remise (evar29) | G66: Validée | I66: Datalayer | N66: hit | T66: custom.montantRemise | AA66: Montant de la promotion, ou remise commerciale visible par l'utilisateur au moment d'une action (affichage d'une page, popin, clic…). Remise sous forme de pourcentage, format "0.5" pour 50%..0.5
A67: 62 | B67: Custom variable #62 | C67: evar35 | D67: je cherche a assurer (evar35) | G67: Validée | I67: Datalayer | N67: hit | P67: Variables implémentées mais non utilisée par BPCE central et bientôt désuètes vs le nouveau plan de taggage INNOV2025 | U67: object.type | Y67: object | Z67: type | AA67: Dans Devis et simulations / Obtenir un tarif (HABITATION) étape 1
A68: 63 | B68: Custom variable #63 | C68: evar41 | D68: Montant initial (evar41) | G68: Validée | I68: Datalayer | N68: hit | T68: custom.montantInitial / custom.montantIni | U68: custom.montantInitial / montantIni | Y68: custom | Z68: montantInitial / montantIni | AA68: Montant du versement initial lors des formulaires devis et souscriptions de crédit
A69: 64 | B69: Custom variable #64 | C69: evar42 | D69: Montant des mensualités (eVar42) | G69: Validée | I69: Datalayer | N69: hit | T69: custom.montantMensualite / montantMens | U69: custom.montantMensualite / montantMens | Y69: custom | Z69: montantMensualite / montantMens | AA69: Montant des mensualités lors des formulaires devis et souscriptions de crédit
A70: 65 | B70: Custom variable #65 | C70: evar43 | D70: Taux (eVar43) | G70: Validée | I70: Datalayer | N70: hit | T70: custom.taux | U70: custom.taux | Y70: custom | Z70: taux | AA70: Taux du prêt lors des formulaires devis et souscriptions de crédit
A71: 66 | B71: Custom variable #66 | C71: evar44 | D71: Dernier univers visité (eVar44) | G71: Documentation à modifier (89c3 - performance digitale) | H71: A modifier dans le sharepoint, propriété et variable terminée | I71: ? | N71: hit | T71: . | U71: .
A72: 67 | B72: Custom variable #67 | C72: evar46 | D72: Type consultation Devis (evar46) | G72: Validée | I72: Datalayer | N72: hit | T72: act.mode | U72: act.mode | Y72: act | Z72: mode
A73: 68 | B73: Custom variable #68 | C73: evar49 | D73: suivi vignette | G73: Validée | I73: Tealium | N73: hit | T73: NA | U73: NA
A74: 69 | B74: Custom variable #69 | C74: evar50 | D74: page | G74: Validée | I74: Tealium | N74: hit | T74: NA | U74: NA | Y74: pages | Z74: pageName | AA74: Nom de la page
A75: 70 | B75: Custom variable #70 | C75: evar51 | D75: marche | G75: Validée | I75: Tealium | N75: hit | T75: NA | U75: NA | Y75: pages | Z75: CodeEnttGrpe | AA75: Nom du marché de la page
A76: 71 | B76: Custom variable #71 | C76: evar53 | D76: type de financement | G76: Validée | I76: Datalayer | N76: hit | T76: custom.typeFinancement | U76: custom.typeFinancement | Y76: custom | Z76: typeFinancement | AA76: Choix du type de financement
A77: 72 | B77: Custom variable #72 | C77: evar54 | D77: type de credit | G77: Validée | I77: Datalayer | N77: hit | T77: custom.typeCredit | U77: custom.typeCredit | Y77: custom | Z77: typeCredit | AA77: Choix du type de credit
A78: 73 | B78: Custom variable #73 | C78: evar56 | D78: Option BL / non optin | G78: Validée | H78: Alimentation à corriger Documentation à corriger, ce sont les options clients pour configurer l'offre BL | I78: Datalayer | N78: hit | T78: . | U78: . | AA78: Non optin CRM
A79: 74 | B79: Custom variable #74 | C79: evar57 | D79: Dernier produit | G79: A remplacer | H79: Double alimentation / Verifier l'utilisation du dernier produit côté CE, dans ce cas voir pour changer la variable credit conso A supprimer | I79: Datalayer | N79: hit | T79: .assuranceEmprunteur | U79: .assuranceEmprunteur | Z79: assuranceEmprunteur | AA79: Dernier porduit consulté pour erebond
A80: 75 | B80: Custom variable #75 | C80: evar59 | D80: type de souscription de carte | G80: Validée | I80: Datalayer | N80: visit | T80: custom.typeDemandeCarte | U80: custom.typeDemandeCarte | Y80: custom | Z80: typeDemandeCarte | AA80: type de la demande de souscription carte : remplacement ou nouvelle carte
A81: 76 | B81: Custom variable #76 | C81: evar66 | D81: nombre de simulation effectué (sim credit conso) | G81: Validée | I81: Datalayer | N81: visit | T81: custom.nombreSimulation | U81: custom.nombreSimulation | Y81: custom | Z81: nombreSimulation | AA81: Remonte le nombre de simulation (modification reglette/champ) à pousser sur la page suivante de navigation
A82: 77 | B82: Custom variable #77 | C82: evar67 | D82: Profil client | G82: Validée | I82: Datalayer | N82: hit | T82: custom.profilClientDemande | U82: custom.profilClientDemande | Y82: custom | Z82: profilClientDemande | AA82: profil du client (formulaires ACL)
A83: 78 | B83: Custom variable #78 | C83: evar68 | D83: Score souscription | G83: A implémenter (89c3 - MT) | H83: Implémenter côté CE | I83: Datalayer | N83: hit | T83: custom.score | U83: custom.score | Y83: custom | Z83: score | AA83: Score lors d'une souscription credit conso
A84: 79 | B84: Custom variable #79 | C84: evar69 | D84: Nombre de justificatifs uploadés | G84: Validée | I84: Datalayer | N84: hit | T84: custom.nombrejustificatifs | U84: custom.nombrejustificatifs | Y84: custom | Z84: nombrejustificatifs | AA84: [formulaire enjoy] dernière étape, nombre de justificatifs téléchargés par l'utilisateur
A85: 80 | B85: Custom variable #80 | C85: evar70 | D85: numero user | G85: Validée | I85: Datalayer | N85: hit | T85: . | U85: . | AA85: Identifiant du user lors d'une connexion à CENET
A86: 81 | B86: Custom variable #81 | C86: evar72 | D86: conjoint CoEmprunteur | G86: Validée | H86: Mapping prévu Novembre 2019 | I86: Datalayer | N86: hit | T86: . | U86: . | AA86: tunnel souscription credit conso : si le conjoint est co emprunteur ou non
A87: 82 | B87: Custom variable #82 | C87: evar73 | D87: assurance coemprunteur | G87: Validée | I87: Datalayer | N87: hit | T87: . | U87: . | AA87: si conjoint coemprunteur (tunnel credit conso), adhere t'il a l'assurance proposé ou non
A88: 83 | B88: Custom variable #83 | C88: evar74 | D88: typeOpposition | G88: A implémenter (89c3 - Alex) | H88: A implémenter sur BP | I88: Datalayer | N88: hit | T88: custom.typeOpposition | U88: custom.typeOpposition | Y88: custom | Z88: typeOpposition | AA88: pilotage de la carte: opposition en ligne : type d'opposition
A89: 84 | B89: Custom variable #84 | C89: evar75 | D89: type d'erreur | G89: A implémenter (89c3 - Nicolas) | H89: A implémenter sur BP | I89: Datalayer | N89: hit | T89: custom.typeErreur | U89: custom.typeErreur | Y89: custom | Z89: typeErreur
A90: 85 | B90: Custom variable #85 | C90: evar80 | D90: cid | G90: Validée | I90: Tealium | N90: hit | T90: NA | U90: NA | AA90: Récupérer l'information contenu dans le CID (paramètre de l'URL)
A91: 86 | B91: Custom variable #86 | C91: evar82 | D91: Nom du projet | G91: Validée | H91: En cours d'intégration Novembre 2019 | I91: Datalayer | N91: hit | T91: custom.NomDuProjet | U91: custom.NomDuProjet | Y91: custom | Z91: NomDuProjet | AA91: Récupérer le nom du projet
A92: 87 | B92: Custom variable #87 | C92: evar83 | D92: hash | G92: Validée | I92: Datalayer | N92: hit | T92: custom.hash | U92: custom.hash | Y92: custom | Z92: hash | AA92: Hash du nom, prénom et date de naissance pour constituer un identifiant prospect
A93: 88 | B93: Custom variable #88 | C93: evar84 | D93: Numéro de SIREN | G93: A mapper (89c3 - Nicolas) | H93: A mapper côté BP | I93: Datalayer | N93: hit | T93: custom.NumeroSiren | U93: custom.NumeroSiren | Y93: custom | Z93: NumeroSiren | AA93: SIREN de la collectivité ayant demandé le dossier
A94: 89 | B94: Custom variable #89 | C94: evar85 | D94: Nom de la Collectivité | G94: A mapper (89c3 - Nicolas) | H94: A mapper côté BP | I94: Datalayer | N94: hit | T94: custom.NomDeCollectivite | U94: custom.NomDeCollectivite | Y94: custom | Z94: NomDeCollectivite | AA94: Nom de la collectivité ayant demandé le dossier
A95: 90 | B95: Custom variable #90 | C95: evar86 | D95: Durée du prêt | G95: A mapper (89c3 - Nicolas) | H95: A mapper côté BP | I95: Datalayer | N95: hit | T95: custom.DureeDuPret | U95: custom.DureeDuPret | Y95: custom | Z95: DureeDuPret | AA95: Durée de prêt choisie en mois
A96: 91 | B96: Custom variable #91 | C96: evar87 | D96: Périodicité du prêt | G96: A mapper (89c3 - Nicolas) | H96: A mapper côté BP | I96: Datalayer | N96: hit | T96: custom.PeriodiciteDePret | U96: custom.PeriodiciteDePret | Y96: custom | Z96: PeriodiciteDePret | AA96: Périodicité du prêt choisi (en mois)
A97: 92 | B97: Custom variable #92 | C97: evar89 | D97: fonctionnalite | G97: Documentation à modifier (89c3 - performance digitale) | H97: Clarifier le naming | I97: Datalayer | N97: hit | T97: custom.fonctionnalite | U97: custom.fonctionnalite | Y97: custom | Z97: fonctionnalite | AA97: Décris la fonctionnalité securpass sur laqulle se trouve l'utilisateur
A98: 93 | B98: Custom variable #93 | C98: evar90 | D98: provenance | G98: Documentation à modifier (89c3 - performance digitale) | H98: Revoir le wording de la variable (provenance usage) | I98: Datalayer | N98: hit | T98: custom.provenance | U98: custom.provenance | Y98: custom | Z98: provenance | AA98: Décris si une opération est inband ou outband
A99: 94 | B99: Custom variable #94 | C99: evar91 | D99: type | G99: Documentation à modifier (89c3 - performance digitale) | H99: Clarifier le naming / Remplir la doc | I99: Datalayer | N99: hit | T99: custom.type | U99: custom.type | Y99: custom | Z99: type | AA99: Famille SecurPass et mes comptes
A100: 95 | B100: Custom variable #95 | C100: evar92 | D100: contexte | G100: Documentation à modifier (89c3 - performance digitale) | H100: Clarifier le naming / Remplir la doc | I100: Datalayer | N100: hit | T100: custom.contexte | U100: custom.contexte | Y100: custom | Z100: contexte | AA100: Contexte de l'usage securpass
A101: 96 | B101: Custom variable #96 | C101: evar93 | D101: typeFamille - à supprimer de Tealium et Adobe | G101: Documentation à modifier (89c3 - performance digitale) | H101: Voir si pas intéressant de découper l'evar91 en deux pour renseigner le type de compte ici | I101: Datalayer | N101: hit | T101: custom.typeFamille | U101: custom.typeFamille | Y101: custom | Z101: typeFamille | AA101: type de compte sur le parcours mes comptes
A102: 97 | B102: Custom variable #97 | C102: evar94 | D102: libelle | G102: Validée | H102: Remplir la doc pour préciser la contenu (Meniga / DP Web ?) | I102: Datalayer | N102: hit | T102: custom.libelle | U102: custom.libelle | Y102: custom | Z102: libelle | AA102: libellé de l'action / produit / recherche
A103: 98 | B103: Custom variable #98 | C103: evar95 | D103: ABTesting 3 (evar95) | G103: Validée | I103: Kameleoon | N103: hit | T103: NA | U103: NA | Y103: AA en dur | AA103: ABTesting : nom du test ab - variable remplie par Kameleoon
A104: 99 | B104: Custom variable #99 | C104: evar96 | D104: ABTesting 4 (eVar96) | G104: Validée | I104: Kameleoon | N104: hit | T104: NA | U104: NA | Y104: AA en dur | AA104: ABTesting : nom du test ab - variable remplie par Kameleoon
...

Sheet Datalayer BPCE vtravail
A1: Action | B1: Type de variable | C1: Scope evar | D1: Numéro | E1: Statut | F1: Pertinent (métiers et CRM) (O/N) | G1: Implémenté CE (O/N) | H1: Implémenté BP (O/N) | I1: Valeurs attendues (O/N) | J1: Commentaire | K1: Commentaire BP Hortense | L1: Nom | M1: Propiété | N1: variable | O1: Description | P1: Valeurs | Q1: Valeurs2 | R1: Valeurs3 | S1: Valeurs4 | T1: Valeurs5 | U1: Valeurs6 | V1: Valeurs7 | W1: Valeurs8 | X1: Valeurs9 | Y1: Valeurs10 | Z1: Valeurs11 | AA1: Valeurs12 | AB1: Valeurs13 | AC1: Valeurs14 | AD1: Valeurs15 | AE1: Valeurs16 | AF1: Valeurs17 | AG1: Valeurs18 | AH1: Valeurs19 | AI1: Valeurs20 | AJ1: Valeurs21 | AK1: Valeurs22 | AL1: Valeurs23 | AM1: Valeurs24 | AN1: Valeurs25 | AO1: Valeurs26 | AP1: Valeurs27 | AQ1: Valeurs28 | AR1: Valeurs29 | AS1: Valeurs30 | AT1: Valeurs31 | AU1: Valeurs32 | AV1: Valeurs33 | AW1: Valeurs34 | AX1: Valeurs35 | AY1: Valeurs36 | AZ1: Valeurs37 | BA1: Valeurs38 | BB1: Valeurs39 | BC1: Valeurs40 | BD1: Valeurs41
B2: prop | D2: 1 | E2: Validée | F2: O | G2: O | H2: Conserver | I2: O | K2: "sur BP: - les 14 premiers codes établissements sont à 3 chiffres le reste à 5 chiffres ( avec peu de connexions ) | L2: Code Etablissement Client (prop1) | M2: clients | N2: idEnttGrpe | O2: Description : Contient le Code Etablissement de rattachement du Client Format : (5 (CE) ou 3 (BP) caractères), Règle de gestion : rempli si client authentifié ou identifié, vide si prospect | P2: 16705 | Q2: 13335 | R2: 18715 | S2: 12135 | T2: 14445 | U2: 18315 | V2: 17515 | W2: 13485 | X2: 14505 | Y2: 14265 | Z2: 15135 | AA2: 13135 | AB2: 16275 | AC2: 11425 | AD2: 18025 | AE2: 11315 | AF2: 13825 | AG2: 99999 | AH2: 002 | AI2: 008 | AJ2: 009 | AK2: 019 | AL2: 035 | AM2: 038 | AN2: 039 | AO2: 046 | AP2: 047 | AQ2: 066 | AR2: 067 | AS2: 068 | AT2: 078 | AU2: 087 | AV2: 534 | AW2: 536 | AX2: 537 | AY2: 552
A3: Faire un état des lieux sur le COTE | B3: prop | D3: 2 | E3: Documentation à modifier (89c3 - performance digitale) | F3: O | G3: O | H3: Modifier | I3: O | J3: Faire un état des lieux sur le COTE | K3: Les COTE sont tous alpha numériques ( normal non ?) | L3: Id Client (prop2) | M3: clients | N3: clientid | O3: Identifiant validé juridiquement et au niveau de la sécurité comme donnée non personnelle et non sensible qui peut être envoyé à des prestataires externes pour des campagnes marketing digital. CE : contient l’identifiant Client MySys (NODAPE) du client authentifié ou identifié. Donnée numérique sur 7 ou 9 caractères contenant les « 0 » non significatifs. BP : COTE identifiant numérique sur 10 caractères
A4: Modifier référentiel | B4: prop | D4: 3 | E4: Validée | F4: O | G4: O | H4: Conserver | I4: O | J4: Préciser la règle de gestion (proposition dans le référentiel datalayer sharepoint) | K4: ok | L4: Statut Client (prop3) | M4: clients | N4: statut | O4: Contient le niveau de connaissance du client. Authentifié = logué dans la session Identifié = logué dans une session antérieure Prospect = jamais connecté | P4: authentifie | Q4: identifie | R4: prospect
A5: Homogénéiser les valeurs | B5: prop | D5: 4 | E5: Documentation à modifier (89c3 - performance digitale) | F5: O | G5: O | H5: Conserver | I5: N | J5: Casse et orthographe très différent (particuliers/Particulier/particulier/professionnel/Profesionel) : - soit anomalie dans chacun des applicatif, - soit majorité des retraitements gérés par composant transverse et modification peut être aisée ==> étude du composant transverse | K5: Marchés clients sont toujours à homogénéiser si possibles: - Particulier/ pParticuliers - Entreprise/ entreprises - il y a 4 types de professionnel/professionnels/profesionnel/ Professionnels Mapping Tealium, processing rule ? | L5: Marché Client (prop4) | M5: clients | N5: marche | O5: Contient le marché du client authentifié ou identifié, vide si prospect | P5: associations, fondations, mutuelles – mandataires judiciaires a la protection des majeurs | Q5: entreprises | R5: hors marche | S5: immobilier professionnel | T5: logement social - economie mixte | U5: particuliers | V5: professionnels | W5: secteur public | X5: fonction publique | Y5: sans comerçants | Z5: gestion privee | AA5: professions libérales | AB5: jeunes actifs | AC5: institutionnels | AD5: fonctionnaires | AE5: banque privée | AF5: service publique | AG5: bfc banque privée | AH5: agriculteurs | AI5: professions libérales | AJ5: lycéens étudiants apprentis | AK5: enfants étudiants apprentis | AL5: 16 ans et plus | AM5: franchise | AN5: jeune actif | AO5: 16-28 ans | AP5: viticulture | AQ5: frontaliers | AR5: institutionnels associations | AS5: associations | AT5: jeunes adultes | AU5: startup | AV5: professionels
A6: Homogénéiser les valeurs | B6: prop | D6: 5 | E6: Documentation à modifier (89c3 - performance digitale) | F6: O | G6: O | H6: Modifier | I6: N | J6: Différents orthographes de la variable datalayer | K6: codes établissements de la page - on retiendra le forma en chiffres pour le datalayer - des formats en lettres resteront pour la prop51 dans la majorité des projets " | L6: Code réduit Etablissement de la page (prop5) | M6: pages | N6: CodeEnttGrpe | O6: Code réduit de l'établissement de rattachement de la page, (Lettres pour CE, 3chiffres pour BP) | P6: CEALS | Q6: CEAPC | R6: CEAUL | S6: CEBFC | T6: CEBPL | U6: CECAZ | V6: CEIDF | W6: CELRO | X6: CELCE | Y6: CELDA | Z6: CELCA | AA6: CEMIP | AB6: CEHDF | AC6: CENOR | AD6: CEHDF | AE6: CEPAC | AF6: CERHA | AG6: CENAT | AH6: BPRI | AI6: BPBFC | AJ6: BPACA | AK6: BPAURA | AL6: BPN | AM6: BPATL | AN6: BPAURA | AO6: BPMED | AP6: BPALC | AQ6: BPS | AR6: BPO | AS6: BPAURA | AT6: BPOC | AU6: BPVF | AV6: CMMBN | AW6: CMMATL | AX6: CMMLSO | AY6: BQSAV
B7: prop | D7: 6 | E7: Validée | F7: O | G7: O | H7: Conserver | K7: ok | L7: Type Applicatif (prop6) | M7: pages | N7: applicationType | O7: Permet de distinguer de le type d'applicatif à l'origine du tag | P7: application | Q7: site
A8: A préciser référentiel | B8: prop | D8: 7 | E8: Validée | F8: O | G8: O | H8: Conserver | I8: O | J8: Préciser la mécanique : se base sur l'applicatif, ou bien sur le plan de marquage ? Ex : des pages PISP sont valorisées cyber | K8: ok | L8: Nom de l applicatif (prop7) | M8: pages | N8: applicationName | O8: Permet de distinguer de quel applicatif provient le tag (à mettre à jour avec les données BP) | P8: banque | Q8: ce net | R8: dea | S8: dei [part/pro] | T8: dei part | U8: dei pp | V8: dei pro | W8: dei sp | X8: dem | Y8: ecommerce | Z8: evi | AA8: harvest | AB8: mbl | AC8: ngi | AD8: tunnel
A9: ? | B9: prop | D9: 8 | E9: Validée | F9: O | G9: O | H9: Conserver | I9: N | J9: Différences de format et remontées inégales (côté BP et côté CE) | K9: "rajouté quelques valeurs BP dans le datalayer - startup, franchise, gestion privée, étudiant " | L9: Marché de navigation (prop8) | M9: pages | N9: marche | O9: Correspond au marché en cours lors de la navigation | P9: associations, fondations, mutuelles – mandataires judiciaires a la protection des majeurs | Q9: entreprises | R9: hors marche | S9: immobilier professionnel | T9: logement social - economie mixte | U9: particuliers | V9: professionnels | W9: secteur public
A10: Catégorisations à préciser | B10: prop | D10: 9 | E10: Documentation à modifier (89c3 - performance digitale) | F10: O | G10: O | H10: Conserver | I10: N | J10: 88 valeurs, ne correspondant pas à l'attendu (probablement objet d'un scrapping) | K10: ok | L10: Univers de Navigation (prop9) | M10: pages | N10: univers | O10: Nom de l’univers en cours lors de la navigation (nom de l'onglet de navigation) | P10: agences et distributeurs | Q10: assistance | R10: assurer | S10: au quotidien | T10: banque au quotidien et assurance | U10: connexion | V10: contact | W10: emprunter | X10: epargner | Y10: financement | Z10: gestion privee | AA10: ma banque pratique | AB10: ma synthese | AC10: mes assurances | AD10: mes cartes et paiement | AE10: mes comptes | AF10: mes credits | AG10: messagerie | AH10: mon agence | AI10: mon coffre fort | AJ10: mon epargne | AK10: mon profil | AL10: parametres | AM10: placement | AN10: politique sociale | AO10: prelevements | AP10: virements
A11: Catégorisations à préciser | B11: prop | D11: 10 | E11: Documentation à modifier (89c3 - performance digitale) | F11: O | G11: O | H11: Conserver | I11: N | J11: inutilisable d'un point de vue analyse à cause de la diversité des valeurs | K11: ok | L11: Type de la page (prop10) | M11: pages | N11: pageType | O11: Type de la page | P11: conseil | Q11: consultation | R11: contact | S11: document | T11: edito | U11: erreur | V11: faq | W11: formulaire | X11: gammes | Y11: home | Z11: information | AA11: marche | AB11: operation | AC11: page_ccd | AD11: popin | AE11: produit | AF11: profil | AG11: recherche | AH11: recherche agence | AI11: univers
B12: prop | D12: 11 | E12: Validée | F12: O | G12: O | H12: Conserver | K12: ok | L12: is ABTesting (prop11) | O12: ABTesting : nom du test ab - variable remplie par Kameleoon
B13: prop | D13: 12 | E13: Validée | F13: O | G13: O | H13: Conserver | K13: ok | L13: Id ABTesting(prop12) | O13: ABTesting : nom du test ab - variable remplie par Kameleoon
A14: OK Octobre 2019 | B14: prop | D14: 13 | E14: Validée | F14: O | G14: O | H14: Conserver | I14: O | J14: Variable Tealium pas implémentée partout | K14: ok | L14: Url de la page (prop13) | O14: Url de la Page
A15: Demander si utilité du doublon en evar ? Ne pas supprimer car entraine des modifs de paramétrages importants | B15: prop | D15: 14 | E15: Validée | F15: O | G15: O | H15: Conserver | I15: O | J15: Variable pas implémentée partout | K15: ok | L15: Nom du Formulaire (prop14) | M15: form | N15: nom | O15: Nom du formulaire
A16: Demander si utilité du doublon en prop, si non ==> supprimer prop | B16: prop | D16: 15 | E16: Validée | F16: O | G16: O | H16: Conserver | I16: O | J16: Valeurs à vocation à être adaptative | K16: ok | L16: Identifiant etape Formulaire (prop15) | M16: form | N16: idEtape | O16: Identifiant étape
B17: prop | D17: 16 | E17: Validée | F17: O | G17: O | H17: Conserver | I17: N | J17: Variable pas implémentée partout, action côté webmestres et côté développeurs pour remplir les champs CMS ou les projets | K17: : Nous avons très peu de codes produits qui remontent seulement 1 par produit en semaine ? | L17: Objet de l applicatif (prop16) | M17: pages | N17: espace | O17: Type de l'application (commercial = portail, transactionnel = espace connecté) | P17: commercial | Q17: externe | R17: transactionnel | S17: interne
A18: Catégorisations à préciser, règle de gestion à renseigner | B18: prop | D18: 17 | E18: Documentation à modifier (89c3 - performance digitale) | F18: O | G18: O | H18: Conserver | I18: N | J18: Variable pas implémentée partout, action côté webmestres et côté développeurs pour remplir les champs CMS ou les projets | K18: Pas de données | L18: Gamme de produit de Navigation (prop17) | M18: produits | N18: gamme | O18: Gamme de produit dont traite la page (au sens métier) (liste non exhaustive) | P18: assurance | Q18: bancarisation | R18: credit conso | S18: credit immo | T18: credit pro | U18: epargne financiere | V18: epargne liquide | W18: service b2b | X18: service b2c
A19: Catégorisations à préciser, règle de gestion à renseigner | B19: prop | D19: 18 | E19: Documentation à modifier (89c3 - performance digitale) | F19: O | G19: O | H19: Conserver | I19: N | J19: Variable pas implémentée partout, action côté webmestres et côté développeurs pour remplir les champs CMS ou les projets | K19: ok | L19: Code Produit de navigation (prop18) | M19: produits | N19: code | O19: Code du produit dont traite la page (au sens métier) (liste non exhaustive) | P19: assepargne | Q19: assurance 2 roues | R19: assurance auto | S19: assurance emprunteur | T19: assurance moyen paiement | U19: assurance mrh | V19: assurance resp civile | W19: assurance voyage | X19: bourse | Y19: carte | Z19: cat | AA19: cel | AB19: cfn | AC19: compte-courant | AD19: credit conso auto | AE19: credit conso etudiant | AF19: credit conso travaux | AG19: credit conso tresorie | AH19: credit immo | AI19: credit immo primo | AJ19: credit pro | AK19: eparfix | AL19: gav | AM19: internet | AN19: ldd | AO19: lep | AP19: livret a | AQ19: livret b | AR19: livret grand format | AS19: livret grand prix | AT19: livret jeune | AU19: obseques | AV19: opcvm | AW19: paiement | AX19: pea | AY19: pel | AZ19: pj | BA19: retrait inter | BB19: sante | BC19: securmedia | BD19: visuel carte
B20: prop | D20: 19 | E20: A supprimer | F20: O | G20: O | H20: Conserver | I20: N | J20: 500K valeurs | L20: Nom de la tuile (prop19)
B21: prop | D21: 20 | E21: A supprimer | F21: O | G21: O | H21: Conserver | I21: N | J21: implémentée, mais inutilisable | L21: tags article utilises
A22: A supprimer, valeur seulement mappée pour la report suite BPACA, et côté CE, prop sur les vignettes mappée mais pas utilisée | B22: prop | D22: 21 | E22: A supprimer | F22: ? | G22: N | I22: ? | J22: redondant avec propclient et proppages | L22: Code établissement BP
B23: prop | D23: 22 | E23: A supprimer | F23: ? | G23: N | I23: N | J23: non implémentée, aucun référentiel de valeurs | L23: tags article utilises
A24: Voir utilité de la métrique Time spent on page pour les PO ? | B24: prop | D24: 23 | E24: A supprimer | L24: Temps de chargement de la page | M24: pages | N24: loadingTime
A25: Changer le nom de la variable Adobe | B25: prop | D25: 24 | E25: Validée | L25: type de dossier | M25: pages | N25: TypeDossier | O25: Type de dossier selectionné dans le portail KYC- connaissance client
B26: prop | D26: 25 | E26: A supprimer | F26: N | G26: O | I26: O | J26: Variables implémentées mais non utilisée par BPCE central et bientôt désuètes vs le nouveau plan de taggage INNOV2020 | L26: type de document | M26: pages | N26: TypeDocument | O26: type de document séléctionné dans le portail : KYC / Numairic | P26: kbis | Q26: bilan | R26: status | S26: declaration | T26: Beneficiaire effectif | U26: bilan du dernier excercice | V26: Bilan supplémentaire precedent | W26: bilan supplémentaire antérieur
B27: prop | D27: 26 | E27: A supprimer | F27: N | G27: O | I27: O | J27: Variables implémentées mais non utilisée par BPCE central et bientôt désuètes vs le nouveau plan de taggage INNOV2020 | L27: vide
B28: prop | D28: 27 | E28: A supprimer | F28: N | G28: O | I28: O | J28: Variables implémentées mais non utilisée par BPCE central et bientôt désuètes vs le nouveau plan de taggage INNOV2020 | L28: vide
B29: prop | D29: 28 | E29: A supprimer | F29: N | G29: O | I29: O | J29: Variables implémentées mais non utilisée par BPCE central et bientôt désuètes vs le nouveau plan de taggage INNOV2020 | L29: vide
B30: prop | D30: 29 | E30: A supprimer | F30: N | G30: O | I30: O | J30: Variables implémentées mais non utilisée par BPCE central et bientôt désuètes vs le nouveau plan de taggage INNOV2020 | L30: vide
A31: Créer un event de décompte résultat nul | B31: prop | D31: 30 | E31: A supprimer | F31: ? | L31: Résultat nul (prop30) | M31: custom | N31: resultatNul
A32: OK Octobre 2019 | B32: prop | D32: 31 | E32: Validée | F32: O | G32: O | H32: N | I32: N | J32: Valeurs à vocation à être adaptative Règle de gestion non précisée ==> non implémentée par Natixis dans leur Tealium | L32: page | M32: pages | N32: pageName | O32: Page pour les clics
A33: OK Octobre 2019 | B33: prop | D33: 32 | E33: Validée | F33: O | G33: N | H33: N | I33: NA | J33: Variable Tealium paramétrable | L33: pagename page précédente
A34: Pas pertinent pour l'analyse de parcours vs la page précédente | B34: prop | D34: 33 | E34: A supprimer | F34: O | G34: N | H34: N | I34: NA | J34: Variable Tealium paramétrable | L34: libellé clic page précédente
B35: prop | D35: 34 | E35: A supprimer | L35: banner | O35: affichage d'une bannière / popin
B36: prop | D36: 35 | E36: Validée | L36: Nombre de cartes actives differentes | M36: custom | N36: NombreCartesActives | O36: (pilotage de la carte) deep purple - page carrousel | P36: 1 | Q36: 2 | R36: 3 | S36: 4 | T36: etc
B37: prop | D37: 36 | E37: Validée | L37: Nombre de cartes opposées différentes | M37: custom | N37: NombreCartesOpposees | O37: (pilotage de la carte) deep purple - page carrousel | P37: 1 | Q37: 2 | R37: 3 | S37: 4 | T37: etc
B38: prop | D38: 37 | E38: Validée | L38: Nombre de cartes commandées ou expédiées | M38: custom | N38: NombreCartesCommandees | O38: (pilotage de la carte) deep purple - page carrousel | P38: 1 | Q38: 2 | R38: 3 | S38: 4 | T38: etc
B39: prop | D39: 38 | E39: Validée | L39: Nombre de cartes actives et verrouillées temporairement | M39: custom | N39: NombreCartesVerrouilleesTemp | O39: (pilotage de la carte) deep purple - page carrousel | P39: 1 | Q39: 2 | R39: 3 | S39: 4 | T39: etc
B40: prop | D40: 39 | E40: Validée | L40: Nombre de cartes actives et paiements en ligne désactivés | M40: custom | N40: NombreCartesPaiementDistanceOFF | O40: (pilotage de la carte) deep purple - page carrousel | P40: 1 | Q40: 2 | R40: 3 | S40: 4 | T40: etc
B41: prop | D41: 40 | E41: Validée | L41: Nombre de cartes actives et paiements a l etranger desactivés | M41: custom | N41: NombreCartesPaiementEtrangerOFF | O41: (pilotage de la carte) deep purple - page carrousel | P41: 1 | Q41: 2 | R41: 3 | S41: 4 | T41: etc
B42: prop | D42: 41 | E42: Validée | L42: Nombre de cartes enrolement | M42: custom | N42: NbCartesEnrolement | O42: (pilotage de la carte) deep purple - page choix des cartes à enroler (parcours enrolement paylib) | P42: 1 | Q42: 2 | R42: 3
B43: prop | D43: 42 | E43: A supprimer | L43: paylib type | M43: custom | N43: paylibType | O43: (appli visa) lors d'un ticket transmis | P43: credit | Q43: debit
B44: prop | D44: 43 | E44: A supprimer | L44: modePaiement | M44: custom | N44: modePaiement | O44: (appli visa) lors d'un ticket transmis | P44: tap ed | Q44: tap ed tap | R44: ed tap
B45: prop | D45: 44 | E45: A supprimer | L45: Montant reglette | M45: custom | N45: montantReglette | O45: paylib application: seuil fixé pour paiement sans contact (dans preferences) - 30 € max | P45: 20 | Q45: 30
B46: prop | D46: 45 | E46: Validée | L46: Total nombre de compte détenus | M46: custom | N46: nombreComptes | O46: selfcare: page synthese, remonte le nombre de compte détenus par l'utilisateur (courant, epargne, financiere)
A47: A revoir avec Nicolas ==> Variable déjà désactivée dans Adobe BP | B47: prop | D47: 46 | E47: A supprimer | L47: Code produit repris | M47: custom | N47: codeProduitRepris | O47: BP: formulaire ACL, au clic sur la reprise d'une souscription : remonter quel produit concerné | P47: pel | Q47: cel | R47: csl etc
B48: prop | D48: 47 | E48: Validée | L48: libelle transaction incorrect | M48: custom | N48: libelleIncorrect | O48: Mes Comptes : sur ecran detail d'une transaction, si l'user clique sur "libelle erroné", remonte les 5 qualificatifs suivants[ [originalText;sub_text;transactionTypeCode; external_merchant_identifier; transaction_date]
A49: Préciser la description | B49: prop | D49: 48 | E49: Validée | L49: switch | M49: custom | N49: switch | O49: securpass enrolement - choix on ou off sur la page "enrolement - [touch id/fingerprint/faceid] | P49: on | Q49: off
A50: Préciser la description | B50: prop | D50: 49 | E50: Validée | L50: numero de contrat (natixis) | M50: custom | N50: numeroContrat | O50: (parcours natixis virement credit renouvelable) pousser le numero de contrat associé au credit renouvelable du client en question (id coté natixis)
A51: Préciser la description | B51: prop | D51: 50 | E51: Validée | L51: version tealium | O51: Variable générée par Tealium (pas datalayer). Concatène le nom du compte Tealium, le profil, l'environnement et la version pour chaque hit. Permet de vérifier le déploiement correct de Tealium et de pointer une version particulière en cas de bug
A52: Préciser la description | B52: prop | D52: 52 | E52: Validée | J52: Mettre à jour documentation (Natixis ?) | L52: Code banque/reseau client (prop52) | M52: clients | N52: idGrpe | P52: CE | Q52: BP
A53: Préciser la description | B53: prop | D53: 53 | E53: Validée | J53: Mettre à jour documentation (Natixis ?) | L53: ID Client Natixis Assurances (prop53) | M53: clients | N53: idClientNxs
A54: Préciser la description | B54: prop | D54: 54 | E54: Validée | L54: Timestamp | N54: A CREER | O54: Date et heure du hit | Q54: Date et heure du hit
A55: Préciser la description | B55: prop | D55: 74 | E55: Validée | J55: Revoir la pertinence métiers à long terme (IP dynamiques pour collaborateurs) | L55: type opposition identification adresse IP | M55: custom | N55: typeOpposition | O55: Permet d'identifier les groupes d'IP à inclure/exclure des analyses | P55: IP collaborateur
A56: Préciser la description | B56: prop | D56: 75 | E56: Validée | L56: agregation formulaire | M56: custom | N56: agregation | O56: aggrégation des champs qui sont choisis dans un formulaire par les métiers
A57: Préciser la description | B57: prop | D57: 51? | E57: Validée | L57: code établissement page | M57: custom | O57: Correspond au code établissement de rattachement de client en Lettres
A58: Demander à Natixis de gérer les transco dans Tealium | B58: evar | C58: visit | D58: 1 | E58: Validée | F58: O | G58: O | H58: O | I58: "CE : Code à 5 chiffre finissant par un 5 BP : Code à 3 chiffres" | J58: "Pb sur le parcours sous conso avec les codes finissant par un 7 BP : -Unspecified sur certaines applicatifs (tunnel / ecommerce / digital briefcase / Turbo SE pour le desktop | selfcare / Deep purple / cyber pour appli) - Code à 5 chiffres qui remontent sur Turbo / tunnel)" | L58: Code Etablissement Client (evar1) | M58: clients | N58: idEnttGrpe | O58: Contient le Code Etablissement de rattachement du Client (5 (CE) ou 3 (BP) caractères), vide si prospect | P58: 16705 | Q58: 13335 | R58: 18715 | S58: 12135 | T58: 14445 | U58: 18315 | V58: 17515 | W58: 13485 | X58: 14505 | Y58: 14265 | Z58: 15135 | AA58: 13135 | AB58: 16275 | AC58: 11425 | AD58: 18025 | AE58: 11315 | AF58: 13825 | AG58: 99999 | AH58: 2 | AI58: 8 | AJ58: 9 | AK58: 19 | AL58: 35 | AM58: 38 | AN58: 39 | AO58: 46 | AP58: 47 | AQ58: 66 | AR58: 67 | AS58: 68 | AT58: 78 | AU58: 87 | AV58: 534 | AW58: 536 | AX58: 537 | AY58: 552
A59: Créer les tickets d'anos selon les commentaires | B59: evar | C59: visit | D59: 2 | E59: Validée | F59: O | G59: O | H59: O | I59: Nodape (CE) / COTE (BP) | J59: "Sur mobile : - si prospect remonte unspecified - si identifié remonte N/A (au lieu de l'identifiant) - si IOS remonte undefined (cause pb client id identifié) Sur le web : - si prospect - DEM remonte s/o - Tunnel remonte 0000000 - si identifie remonte unspecified sur ecommerce et cenet (au lieu de l'identifiant) BP : '"" 0000000 "" au lieu d'absence de valeur pour les applicatifs tunnel et ecommerce" | L59: Id Client (evar2) | M59: clients | N59: id | O59: Identifiant validé juridiquement et au niveau de la sécurité comme donnée non personnelle et non sensible qui peut être envoyé à des prestataires externes pour des campagnes marketing digital. CE : contient l’identifiant Client MySys (NODAPE) du client authentifié ou identifié. Donnée numérique sur 7 ou 9 caractères contenant les « 0 » non significatifs. BP : identifiant à définir
A60: Créer les tickets d'anos selon les commentaires | B60: evar | C60: visit | D60: 3 | E60: Validée | F60: O | G60: O | H60: O | I60: "authentifie identifie prospect" | J60: "sur mobile : - [dynamique] sur pages pulsar Web : - Unspecified sur rendez en ligne BP : - [""dynamique""] sur l'appli" | L60: Statut Client (evar3) | M60: clients | N60: statut | O60: Contient le niveau de connaissance du client. Authentifié = logué dans la session Identifié = logué dans une session antérieure Prospect = jamais connecté | P60: authentifie | Q60: identifie | R60: prospect
A61: Créer les tickets d'anos selon les commentaires | B61: evar | C61: visit | D61: 4 | E61: Validée | F61: O | G61: O | H61: O | I61: "particuliers professionnels entreprises" | J61: "mobile - pulsar remonte particulier - historique remonte profesionnels Web - ecommerce remonte 101 ... BP : - s/o sur tunnel - Particuliers sur les simulateurs auto et habitations Desktop et dur DP Appli - entreprises et professionnels sur le hub digital - ""Type inconnu"" sur ecommerce - PAR et ENT sur certaines pages Appli Banque Pop - profesionnel sur certaines pages appli BP" | L61: Marché Client (evar4) | M61: clients | N61: marche | O61: Contient le marché du client authentifié ou identifié, vide si prospect | P61: associations, fondations, mutuelles – mandataires judiciaires a la protection des majeurs | Q61: entreprises | R61: hors marche | S61: immobilier professionnel | T61: logement social - economie mixte | U61: particuliers | V61: professionnels | W61: secteur public
A62: Créer les tickets d'anos selon les commentaires | B62: evar | C62: hit | D62: 5 | E62: Validée | F62: O | G62: O | H62: O | I62: multiples | L62: Libellé Clic (evar5) | M62: clics | N62: libelle | O62: Nom du clic
A63: Proposer des catefs de clics (LP, nouveau portail, parcours similaires) pour faire des benchs de taux de clics | B63: evar | C63: hit | D63: 6 | E63: Validée | F63: O | G63: O | H63: O | I63: multiples | J63: BP : Sur l'appli, même valeur que libellé clic | L63: Type de Clic (evar6) | M63: clics | N63: type | O63: Type de clic | P63: action | Q63: annuler | R63: cta | S63: envoyer | T63: menu | U63: navigation | V63: plus tard | W63: rechercher | X63: sortie | Y63: telechargement | Z63: Validée | AA63: vignette
A64: OK Octobre 2019 | B64: evar | C64: hit | D64: 7 | E64: Validée | F64: O | G64: N | H64: N | I64: multiples | L64: Mot-Clé recherché (evar7) | O64: Recherche - Mot clé recherché
A65: BP et CE | B65: evar | D65: 8 | E65: A implémenter (89c3 - Quentin) | F65: O | G65: N | H65: N | I65: multiples | L65: Nombre de résultats de recherche (evar8) | M65: search | N65: notFound | O65: Recherche - Nombre de résultats
A66: Préciser nouvelle variable EDL | B66: evar | D66: 9 | E66: A supprimer | F66: N | G66: O | H66: O | I66: multiples | J66: "uniquement web BP : KO Beaucoup de valeurs qui ne correspondent pas tous à des noms de réseaux sociaux" | L66: Nom du réseau social (evar9) | O66: Nom du réseau social
A67: BP et CE | B67: evar | D67: 10 | E67: A implémenter (89c3 - Quentin) | F67: O | G67: N | H67: N | J67: "seulement 50 résultats sur le web 0 sur le mobile" | L67: Url du lien (evar10) | M67: clics | N67: url | O67: URL du lien
B68: evar | D68: 11 | E68: Validée | F68: O | G68: NA | H68: O | L68: ABTesting 1 (eVar11) | O68: ABTesting : nom du test ab - variable remplie par Kameleoon
B69: evar | D69: 12 | E69: Validée | F69: O | G69: NA | H69: O | L69: ABTesting 2 (evar12) | O69: AB Testing : nom de la variation de l'ab test - variable remplie par Kameleoon
B70: evar | D70: 13 | E70: Validée | F70: O | G70: O | H70: O | L70: Url de la page (evar13) | O70: Url de la Page
A71: Demander si utilité du doublon en prop, si non ==> supprimer prop | B71: evar | D71: 14 | E71: Validée | F71: O | G71: O | H71: O | L71: Nom du formulaire (evar14) | M71: form | N71: nom | O71: Nom du formulaire
A72: Demander si utilité du doublon en prop, si non ==> supprimer prop | B72: evar | D72: 15 | E72: Validée | F72: ? | H72: O | J72: Mauvais nom, étape formulaire | L72: Identifiant étape (evar15) | M72: form | N72: idEtape | O72: Push - libellé bloc gamme
A73: Préciser nouvelle variable EDL | B73: evar | D73: 16 | E73: A supprimer | F73: N | G73: N | H73: N | J73: redondant avec le tracking des vignettes | L73: theme du push | O73: Push - theme (Conseil/Produit)
A74: Préciser nouvelle variable EDL | B74: evar | D74: 17 | E74: A supprimer | F74: N | G74: N | H74: N | J74: redondant avec le tracking des vignettes | L74: Type de Push (evar17) | O74: Push - type (Majeur/Mineur)
A75: Préciser nouvelle variable EDL | B75: evar | D75: 18 | E75: A supprimer | F75: N | G75: N | H75: N | J75: redondant avec le tracking des vignettes | L75: Titre du Push (evar18) | O75: Push - Titre
A76: Préciser nouvelle variable EDL | B76: evar | D76: 19 | E76: A supprimer | F76: ? | G76: N | H76: N | J76: très peu de volume | L76: Configuration Dashboard (evar19) | O76: Configuration Dashboard
A77: Préciser nouvelle variable EDL | B77: evar | D77: 20 | E77: A supprimer | F77: ? | G77: N | H77: N | J77: très peu de volume | L77: Configuration Virement (evar20) | O77: Configuration Virement
B78: evar | D78: 22 | E78: Validée | L78: Type du compte (evar22) | O78: Libellé du compte sans info personnelle (CDD, AssVie,…)
B79: evar | D79: 23 | E79: Validée | L79: Type de virement (evar23) | M79: custom | N79: typeVirement | O79: Type de virement (externe ou interne)
B80: evar | D80: 24 | E80: Validée | L80: Montant du virement (evar24) | M80: custom | N80: montantVirement | O80: Montant du virement
A81: Modifier le nom et créer l'ano pour corriger | B81: evar | D81: 25 | E81: A implémenter (89c3 - MT) | L81: Numéro de Raison du message (evar25) | O81: Numéro de Raison du message
B82: evar | D82: 27 | E82: Validée | L82: Nom du PDF (evar27) | M82: doc | N82: name | O82: Nom du PDF
B83: evar | D83: 28 | E83: Validée | L83: Formule choisie (evar28 | O83: Formule choisie
A84: Informer avant suppression | B84: evar | D84: 29 | E84: A supprimer | L84: Durée (evar29)
A85: Préciser nouvelle variable EDL | B85: evar | D85: 30 | E85: A supprimer | J85: Variables implémentées mais non utilisée par BPCE central et bientôt désuètes vs le nouveau plan de taggage INNOV2020 | L85: Designation du véhicule (evar30) | M85: object | N85: name | O85: Dans formulaire assurance AUTO étape 1
A86: Préciser nouvelle variable EDL | B86: evar | D86: 31 | E86: A supprimer | J86: Variables implémentées mais non utilisée par BPCE central et bientôt désuètes vs le nouveau plan de taggage INNOV2021 | L86: Mode de financement (evar31) | M86: object | N86: financial | O86: Mode financement achat de mon véhicule
A87: Préciser nouvelle variable EDL | B87: evar | D87: 32 | E87: A supprimer | J87: Variables implémentées mais non utilisée par BPCE central et bientôt désuètes vs le nouveau plan de taggage INNOV2022 | L87: Nombre de conducteurs sur simulation (evar32) | M87: object | N87: nbDrivers | O87: Dans Devis et simulations / Obtenir un tarif (AUTO) étape 2
A88: Préciser nouvelle variable EDL | B88: evar | D88: 33 | E88: A supprimer | J88: Variables implémentées mais non utilisée par BPCE central et bientôt désuètes vs le nouveau plan de taggage INNOV2023 | L88: Conducteur supplémentaire en conduite accompagnée (evar33) | M88: object | N88: aacDriver | O88: Dans Devis et simulations / Obtenir un tarif (AUTO) étape 2
A89: Préciser nouvelle variable EDL | B89: evar | D89: 34 | E89: A supprimer | J89: Variables implémentées mais non utilisée par BPCE central et bientôt désuètes vs le nouveau plan de taggage INNOV2024 | L89: proprietaire ou locataire (evar34) | M89: object | N89: myLink | O89: Dans Devis et simulations / Obtenir un tarif (HABITATION) étape 1
B90: evar | D90: 35 | E90: Validée | J90: Variables implémentées mais non utilisée par BPCE central et bientôt désuètes vs le nouveau plan de taggage INNOV2025 | L90: je cherche a assurer (evar35) | M90: object | N90: type | O90: Dans Devis et simulations / Obtenir un tarif (HABITATION) étape 1
A91: Préciser nouvelle variable EDL | B91: evar | D91: 36 | E91: A supprimer | J91: Variables implémentées mais non utilisée par BPCE central et bientôt désuètes vs le nouveau plan de taggage INNOV2026 | L91: Bien en location: nb bien en location (evar36) | M91: object | N91: nbLoc | O91: Dans Devis et simulations / Obtenir un tarif (HABITATION) étape 1
A92: Préciser nouvelle variable EDL | B92: evar | D92: 37 | E92: A supprimer | J92: Variables implémentées mais non utilisée par BPCE central et bientôt désuètes vs le nouveau plan de taggage INNOV2027 | L92: Habitation en travaux (evar37) | M92: object | N92: workInProgress | O92: Dans Devis et simulations / Obtenir un tarif (HABITATION) étape 1
A93: Préciser nouvelle variable EDL | B93: evar | D93: 38 | E93: A supprimer | J93: Variables implémentées mais non utilisée par BPCE central et bientôt désuètes vs le nouveau plan de taggage INNOV2028 | L93: Valeur des capitaux mobiliers (evar38) | M93: object | N93: valueMob | O93: Devis et simulations / Obtenir un tarif (HABITATION) "Choisir cette formule" étape 3
A94: Préciser nouvelle variable EDL | B94: evar | D94: 39 | E94: A supprimer | J94: Variables implémentées mais non utilisée par BPCE central et bientôt désuètes vs le nouveau plan de taggage INNOV2029 | L94: Valeur des capitaux en objets (evar39) | M94: object | N94: valueCap | O94: Devis et simulations / Obtenir un tarif (HABITATION)"Choisir cette formule" étape 3
A95: Préciser nouvelle variable EDL | B95: evar | D95: 40 | E95: A supprimer
B96: evar | D96: 41 | E96: Validée | L96: Montant initial (evar41) | M96: custom | N96: montantInitial / montantIni | O96: Montant du versement initial lors des formulaires devis et souscriptions de crédit
B97: evar | D97: 42 | E97: Validée | L97: Montant des mensualités (eVar42) | M97: custom | N97: montantMensualite / montantMens | O97: Montant des mensualités lors des formulaires devis et souscriptions de crédit
B98: evar | D98: 43 | E98: Validée | L98: Taux (eVar43) | M98: custom | N98: taux | O98: Taux du prêt lors des formulaires devis et souscriptions de crédit
A99: A modifier dans le sharepoint, propriété et variable terminée | B99: evar | D99: 44 | E99: Documentation à modifier (89c3 - performance digitale) | L99: Dernier univers visité (eVar44)
A100: Informer Natixis | B100: evar | D100: 45 | E100: A supprimer | L100: Type de recherche (eVar 45) | M100: search | N100: type | O100: Moteur de recherche interne
...

Sheet Référentiel des valeurs
A1: # | B1: Statut | C1: Action | D1: Type de variable | E1: Numéro variable AA | F1: Scope evar | G1: Commentaire | H1: Commentaire BP Hortense | I1: Nom variable Adobe | J1: Description | K1: Configuration Tealium | L1: Nomenclature attendue | M1: Valeurs | N1: Valeurs2 | O1: Valeurs3 | P1: Valeurs4 | Q1: Valeurs5 | R1: Valeurs6 | S1: Valeurs7 | T1: Valeurs8 | U1: Valeurs9 | V1: Valeurs10 | W1: Valeurs11 | X1: Valeurs12 | Y1: Valeurs13 | Z1: Valeurs14 | AA1: Valeurs15 | AB1: Valeurs16 | AC1: Valeurs17 | AD1: Valeurs18 | AE1: Valeurs19 | AF1: Valeurs20 | AG1: Valeurs21 | AH1: Valeurs22 | AI1: Valeurs23 | AJ1: Valeurs24 | AK1: Valeurs25 | AL1: Valeurs26 | AM1: Valeurs27 | AN1: Valeurs28 | AO1: Valeurs29 | AP1: Valeurs30 | AQ1: Valeurs31 | AR1: Valeurs32 | AS1: Valeurs33 | AT1: Valeurs34 | AU1: Valeurs35 | AV1: Valeurs36 | AW1: Valeurs37 | AX1: Valeurs38 | AY1: Valeurs39 | AZ1: Valeurs40 | BA1: Valeurs41 | BB1: Valeurs42 | BC1: Valeurs43 | BD1: Valeurs44 | BE1: Valeurs45 | BF1: Valeurs46 | BG1: Valeurs47 | BH1: Valeurs48 | BI1: Valeurs49 | BJ1: Valeurs50 | BK1: Valeurs51 | BL1: Valeurs52 | BM1: Valeurs53 | BN1: Valeurs54 | BO1: Valeurs55 | BP1: Valeurs56 | BQ1: Valeurs57 | BR1: Valeurs58 | BS1: Valeurs59 | BT1: Valeurs60 | BU1: Valeurs61 | BV1: Valeurs62 | BW1: Valeurs63 | BX1: Valeurs64 | BY1: Valeurs65 | BZ1: Valeurs66 | CA1: Valeurs67 | CB1: Valeurs68 | CC1: Valeurs69 | CD1: Valeurs70 | CE1: Valeurs71 | CF1: Valeurs72 | CG1: Valeurs73 | CH1: Valeurs74 | CI1: Valeurs75 | CJ1: Valeurs76 | CK1: Valeurs77 | CL1: Valeurs78 | CM1: Valeurs79 | CN1: Valeurs80 | CO1: Valeurs81 | CP1: Valeurs82 | CQ1: Valeurs83 | CR1: Valeurs84 | CS1: Valeurs85 | CT1: Valeurs86 | CU1: Valeurs87 | CV1: Valeurs88 | CW1: Valeurs89 | CX1: Valeurs90 | CY1: Valeurs91 | CZ1: Valeurs92 | DA1: Valeurs93 | DB1: Valeurs94
A2: 1 | B2: Validée | D2: Datalayer | E2: prop1 | F2: hit | I2: Code Etablissement Client (prop1) | J2: Description : Contient le Code Etablissement de rattachement du Client Format : (5 (CE) ou 3 (BP) caractères), Règle de gestion : rempli si client authentifié ou identifié, vide si prospect | M2: 16705 | N2: 13335 | O2: 18715 | P2: 12135 | Q2: 14445 | R2: 18315 | S2: 17515 | T2: 13485 | U2: 14505 | V2: 14265 | W2: 15135 | X2: 13135 | Y2: 16275 | Z2: 11425 | AA2: 18025 | AB2: 11315 | AC2: 13825 | AD2: 99999 | AE2: 002 | AF2: 008 | AG2: 009 | AH2: 019 | AI2: 035 | AJ2: 038 | AK2: 039 | AL2: 046 | AM2: 047 | AN2: 066 | AO2: 067 | AP2: 068 | AQ2: 078 | AR2: 087 | AS2: 534 | AT2: 536 | AU2: 537 | AV2: 552
A3: 2 | B3: Documentation à modifier (89c3 - performance digitale) | D3: Datalayer | E3: prop2 | F3: hit | I3: Id Client (prop2) | J3: Identifiant validé juridiquement et au niveau de la sécurité comme donnée non personnelle et non sensible qui peut être envoyé à des prestataires externes pour des campagnes marketing digital. CE : contient l’identifiant Client MySys (NODAPE) du client authentifié ou identifié. Donnée numérique sur 7 ou 9 caractères contenant les « 0 » non significatifs. BP : COTE identifiant numérique sur 10 caractères | K3: Pour BP : si la variable n'est pas de 10 caractères => la prop n'est pas alimentée Pour CE : si la variable n'est pas de 9 caractères et contient des lettres => la prop n'est pas alimentée | M3: Exemple | N3: 075208131
A4: 3 | B4: Validée | D4: Datalayer | E4: prop3 | F4: hit | I4: Statut Client (prop3) | J4: Contient le niveau de connaissance du client. Authentifié = logué dans la session Identifié = logué dans une session antérieure Prospect = jamais connecté | M4: authentifie | N4: identifie | O4: prospect
A5: 4 | D5: Datalayer | E5: prop4 | F5: hit | I5: Marché Client (prop4) | J5: Contient le marché du client authentifié ou identifié, vide si prospect | M5: Variations existantes pour les 3 principaux marchés (pour autres marchés, voir onglet Valeurs consolidées) | N5: Particuliers | O5: Professionnels | P5: particulier | Q5: entreprises | R5: entreprise | S5: entreprises | T5: particulier | U5: particuliers | V5: profesionnel | W5: professionels | X5: professionnel | Y5: professionnels
A6: 5 | D6: Datalayer | E6: prop5 | F6: hit | I6: Code réduit Etablissement de la page (prop5) | J6: Code réduit de l'établissement de rattachement de la page, (Lettres pour CE, 3chiffres pour BP) | M6: CEALS | N6: CEAPC | O6: CEAUL | P6: CEBFC | Q6: CEBPL | R6: CECAZ | S6: CEIDF | T6: CELRO | U6: CELCE | V6: CELDA | W6: CELCA | X6: CEMIP | Y6: CEHDF | Z6: CENOR | AA6: CEHDF | AB6: CEPAC | AC6: CERHA | AD6: CENAT | AE6: 002 | AF6: 008 | AG6: 009 | AH6: 019 | AI6: 035 | AJ6: 038 | AK6: 039 | AL6: 046 | AM6: 047 | AN6: 066 | AO6: 067 | AP6: 068 | AQ6: 078 | AR6: 087 | AS6: 534 | AT6: 536 | AU6: 537 | AV6: 552
A7: 6 | B7: Validée | D7: Datalayer | E7: prop6 | F7: hit | I7: Type Applicatif (prop6) | J7: Permet de distinguer de le type d'applicatif à l'origine du tag | M7: application | N7: site | O7: webview
A8: 7 | B8: Validée | C8: A préciser référentiel | D8: Datalayer | E8: prop7 | F8: hit | G8: Préciser la mécanique : se base sur l'applicatif, ou bien sur le plan de marquage ? Ex : des pages PISP sont valorisées cyber | H8: ok | I8: Nom de l applicatif (prop7) | J8: Permet de distinguer de quel applicatif provient le tag, utile pour troubleshooter le taggage pour identifier une MEP | M8: Banque | N8: banque | O8: ecommerce | P8: eCommerce | Q8: tunnel | R8: selfcare | S8: cyber | T8: deep purple | U8: dp mobile | V8: dei part | W8: dei pp | X8: dei pro | Y8: dei sp | Z8: DEM | AA8: dem | AB8: DEA | AC8: dea | AD8: evi | AE8: harvest | AF8: lac | AG8: mbl | AH8: ngi | AI8: hub digital | AJ8: digital briefcase | AK8: store 89c3 | AL8: 89c3.com | AM8: BCP Net Part | AN8: ce net | AO8: cenet | AP8: visa | AQ8: communication | AR8: Banque Pop | AS8: CE | AT8: BDCL | AU8: communication | AV8: 89c3.com | AW8: digital briefcase | AX8: visa
A9: 8 | B9: Validée | C9: ? | D9: Datalayer | E9: prop8 | F9: hit | I9: Marché de navigation (prop8) | J9: Correspond au marché de la page naviguée par l'utilisateur ex : un client professionnel pourrait très bien naviguer sur une page particuliers, auquel cas sa prop4 sera "professionnel" et sa prop8 sera "particuliers" | M9: Variations existantes pour les 3 principaux marchés (pour autres marchés, voir onglet Valeurs consolidées) | N9: Particuliers | O9: Professionnels | P9: particulier | Q9: entreprises | R9: entreprise | S9: entreprises | T9: particulier | U9: particuliers | V9: profesionnel | W9: professionels | X9: professionnel | Y9: professionnels
A10: 9 | B10: Documentation à modifier (89c3 - performance digitale) | C10: Catégorisations à préciser | D10: Datalayer | E10: prop9 | F10: hit | H10: ok | I10: Univers de Navigation (prop9) | J10: Nom de l’univers en cours lors de la navigation (nom de l'onglet de navigation) | M10: agences et distributeurs | N10: assistance | O10: assurer | P10: au quotidien | Q10: banque au quotidien et assurance | R10: connexion | S10: contact | T10: emprunter | U10: epargner | V10: financement | W10: gestion privee | X10: ma banque pratique | Y10: ma synthese | Z10: mes assurances | AA10: mes cartes et paiement | AB10: mes comptes | AC10: mes credits | AD10: messagerie | AE10: mon agence | AF10: mon coffre fort | AG10: mon epargne | AH10: mon profil | AI10: parametres | AJ10: placement | AK10: politique sociale | AL10: prelevements | AM10: virements
A11: 10 | B11: Documentation à modifier (89c3 - performance digitale) | C11: Catégorisations à préciser | D11: Datalayer | E11: prop10 | F11: hit | H11: ok | I11: Type de la page (prop10) | J11: Type de la page | M11: conseil | N11: consultation | O11: contact | P11: document | Q11: edito | R11: erreur | S11: faq | T11: formulaire | U11: gammes | V11: home | W11: information | X11: marche | Y11: operation | Z11: page_ccd | AA11: popin | AB11: produit | AC11: profil | AD11: recherche | AE11: recherche agence | AF11: univers | AG11: collecte justificatif | AH11: landing page | AI11: iframe
A12: 11 | B12: Validée | D12: Kameleoon | E12: prop11 | F12: hit | H12: ok | I12: is ABTesting (prop11) | J12: ABTesting : nom du test ab - variable remplie par Kameleoon
A13: 12 | B13: Validée | D13: Kameleoon | E13: prop12 | F13: hit | H13: ok | I13: Id ABTesting(prop12) | J13: ABTesting : nom du test ab - variable remplie par Kameleoon
A14: 13 | B14: Validée | D14: Tealium | E14: prop13 | F14: hit | H14: ok | I14: Url de la page (prop13) | J14: Url de la Page
A15: 14 | B15: Validée | D15: Datalayer | E15: prop14 | F15: hit | H15: ok | I15: Nom du Formulaire (prop14) | J15: Nom du formulaire
A16: 15 | B16: Validée | D16: Datalayer | E16: prop15 | F16: hit | H16: ok | I16: Identifiant etape Formulaire (prop15) | J16: Identifiant étape
A17: 16 | B17: Validée | D17: Datalayer | E17: prop16 | F17: hit | G17: Variable pas implémentée partout, action côté webmestres et côté développeurs pour remplir les champs CMS ou les projets | H17: : Nous avons très peu de codes produits qui remontent seulement 1 par produit en semaine ? | I17: Objet de l applicatif (prop16) | J17: Type de l'application (commercial = portail, transactionnel = espace connecté) | M17: commercial | N17: externe | O17: transactionnel | P17: interne
A18: 17 | B18: Documentation à modifier (89c3 - performance digitale) | C18: Catégorisations à préciser | D18: Datalayer | E18: prop17 | F18: hit | G18: Variable pas implémentée partout, action côté webmestres et côté développeurs pour remplir les champs CMS ou les projets | H18: Pas de données | I18: Gamme de produit de Navigation (prop17) | J18: Gamme de produit dont traite la page (au sens métier) (liste non exhaustive) | M18: assurance | N18: bancarisation | O18: credit conso | P18: credit immo | Q18: credit pro | R18: epargne financiere | S18: epargne liquide | T18: service b2b | U18: service b2c
A19: 18 | B19: Documentation à modifier (89c3 - performance digitale) | C19: Catégorisations à préciser | D19: Datalayer | E19: prop18 | F19: hit | G19: Variable pas implémentée partout, action côté webmestres et côté développeurs pour remplir les champs CMS ou les projets | H19: ok | I19: Code Produit de navigation (prop18) | J19: Code du produit dont traite la page (au sens métier) (liste non exhaustive) | M19: assepargne | N19: assurance 2 roues | O19: assurance auto | P19: assurance emprunteur | Q19: assurance moyen paiement | R19: assurance mrh | S19: assurance resp civile | T19: assurance voyage | U19: bourse | V19: carte | W19: cat | X19: cel | Y19: cfn | Z19: compte-courant | AA19: credit conso auto | AB19: credit conso etudiant | AC19: credit conso travaux | AD19: credit conso tresorie | AE19: credit immo | AF19: credit immo primo | AG19: credit pro | AH19: eparfix | AI19: gav | AJ19: internet | AK19: ldd | AL19: lep | AM19: livret a | AN19: livret b | AO19: livret grand format | AP19: livret grand prix | AQ19: livret jeune | AR19: obseques | AS19: opcvm | AT19: paiement | AU19: pea | AV19: pel | AW19: pj | AX19: retrait inter | AY19: sante | AZ19: securmedia | BA19: visuel carte
A20: 19 | B20: Validée | D20: ? | E20: prop21 | F20: hit | G20: redondant avec propclient et proppages | I20: Code établissement BP
A21: 20 | B21: Validée | D21: Datalayer | E21: prop24 | F21: hit | I21: type de dossier | J21: Type de dossier selectionné dans le portail KYC- connaissance client
A22: 21 | B22: Validée | D22: Tealium | E22: prop31 | F22: hit | G22: Valeurs à vocation à être adaptative Règle de gestion non précisée ==> non implémentée par Natixis dans leur Tealium | I22: page | J22: Page pour les clics
A23: 22 | B23: Validée | D23: Tealium | E23: prop32 | F23: hit | G23: Variable Tealium paramétrable | I23: pagename page précédente
A24: 23 | B24: Validée | D24: Datalayer | E24: prop35 | F24: hit | I24: Nombre de cartes actives differentes | J24: (pilotage de la carte) deep purple - page carrousel | M24: 1 | N24: 2 | O24: 3 | P24: 4 | Q24: etc
A25: 24 | B25: Validée | D25: Datalayer | E25: prop36 | F25: hit | I25: Nombre de cartes opposées différentes | J25: (pilotage de la carte) deep purple - page carrousel | M25: 1 | N25: 2 | O25: 3 | P25: 4 | Q25: etc
A26: 25 | B26: Validée | D26: Datalayer | E26: prop37 | F26: hit | I26: Nombre de cartes commandées ou expédiées | J26: (pilotage de la carte) deep purple - page carrousel | M26: 1 | N26: 2 | O26: 3 | P26: 4 | Q26: etc
A27: 26 | B27: Validée | D27: Datalayer | E27: prop38 | F27: hit | I27: Nombre de cartes actives et verrouillées temporairement | J27: (pilotage de la carte) deep purple - page carrousel | M27: 1 | N27: 2 | O27: 3 | P27: 4 | Q27: etc
A28: 27 | B28: Validée | D28: Datalayer | E28: prop39 | F28: hit | I28: Nombre de cartes actives et paiements en ligne désactivés | J28: (pilotage de la carte) deep purple - page carrousel | M28: 1 | N28: 2 | O28: 3 | P28: 4 | Q28: etc
A29: 28 | B29: Validée | D29: Datalayer | E29: prop40 | F29: hit | I29: Nombre de cartes actives et paiements a l etranger desactivés | J29: (pilotage de la carte) deep purple - page carrousel | M29: 1 | N29: 2 | O29: 3 | P29: 4 | Q29: etc
A30: 29 | B30: Validée | D30: Datalayer | E30: prop41 | F30: hit | I30: Nombre de cartes enrolement | J30: (pilotage de la carte) deep purple - page choix des cartes à enroler (parcours enrolement paylib) | M30: 1 | N30: 2 | O30: 3
A31: 30 | B31: Validée | D31: Datalayer | E31: prop45 | F31: hit | I31: Total nombre de compte détenus | J31: selfcare: page synthese, remonte le nombre de compte détenus par l'utilisateur (courant, epargne, financiere)
A32: 31 | B32: Validée | D32: Datalayer | E32: prop47 | F32: hit | I32: libelle transaction incorrect | J32: Mes Comptes : sur ecran detail d'une transaction, si l'user clique sur "libelle erroné", remonte les 5 qualificatifs suivants[ [originalText;sub_text;transactionTypeCode; external_merchant_identifier; transaction_date]
A33: 32 | B33: Validée | D33: Datalayer | E33: prop48 | F33: hit | I33: switch | J33: securpass enrolement - choix on ou off sur la page "enrolement - [touch id/fingerprint/faceid] | M33: on | N33: off
A34: 33 | B34: Validée | D34: Non défini ou implémenté | E34: prop49 | F34: hit | I34: numero de contrat (natixis) | J34: (parcours natixis virement credit renouvelable) pousser le numero de contrat associé au credit renouvelable du client en question (id coté natixis)
A35: 34 | B35: Validée | D35: Tealium | E35: prop50 | F35: hit | I35: version tealium | J35: Variable générée par Tealium (pas datalayer). Concatène le nom du compte Tealium, le profil, l'environnement et la version pour chaque hit. Permet de vérifier le déploiement correct de Tealium et de pointer une version particulière en cas de bug
A36: 35 | B36: Validée | D36: Tealium | E36: prop51? | F36: hit | I36: code établissement page | J36: Correspond au code établissement de rattachement de client en lettres. Variable Tealium qui permet pour les BP de disposer d'un libellé lisible pour les établissements | K36: Pour CE : correspondance id/code etablissement envoyée dans la variable datalayer => pas de config Tealium Pour BP : correspondance id/code établissement faite par Tealium
A37: 36 | B37: Validée | D37: Non défini ou implémenté | E37: prop52 | F37: hit | I37: Code banque/reseau client (prop52) | J37: Variable provenant des parcours Natixis. Donne le réseau de provenance du client (format 2 lettres) | M37: CE | N37: BP
A38: 37 | B38: Validée | D38: Non défini ou implémenté | E38: prop53 | F38: hit | I38: ID Client Natixis Assurances (prop53) | J38: Variable provenant des parcours Natixis. Donne l'ID client (format non connu)
A39: 38 | B39: Validée | D39: Tealium | E39: prop54 | F39: hit | I39: Timestamp (prop54) | J39: Date et heure du hit (format ex:"2019-12-01T11:08:16") | N39: Date et heure du hit
A40: 39 | B40: Validée | D40: Adobe Analytics ou Tealium ? | E40: prop74 | F40: hit | I40: identification adresse IP | J40: Permet d'identifier les groupes d'IP à inclure/exclure des analyses, grâce à une liste d'IP régulièrement mise à jour d'IT-CE et iBP | M40: IP collaborateur | N40: IP sondes
A41: 40 | B41: Validée | D41: Datalayer | E41: prop75 | F41: hit | I41: agregation formulaire | J41: Aggrégation des informations saisies par l'utilisateur sur un simulateur ou parcours de souscription ex: "B11:Résidence principale;B12:Non;B13:Une maison à étages;B14:Oui;B15:2;B16:5;B17:240;B18:Capteurs 84" pour le parcours assurance MRH Chaine de caractère définie par le métiers et le CRM sur le format (1ère lettre choisie) et sur le fond
A42: 41 | B42: Validée | C42: Demander à Natixis de gérer les transco dans Tealium | D42: Tealium | E42: evar1 | F42: visit | G42: "Pb sur le parcours sous conso avec les codes finissant par un 7 BP : -Unspecified sur certaines applicatifs (tunnel / ecommerce / digital briefcase / Turbo SE pour le desktop | selfcare / Deep purple / cyber pour appli) - Code à 5 chiffres qui remontent sur Turbo / tunnel)" | I42: Code Etablissement Client (evar1) | J42: Contient le Code Etablissement de rattachement du Client (5 (CE) ou 3 (BP) caractères), vide si prospect | M42: 16705 | N42: 13335 | O42: 18715 | P42: 12135 | Q42: 14445 | R42: 18315 | S42: 17515 | T42: 13485 | U42: 14505 | V42: 14265 | W42: 15135 | X42: 13135 | Y42: 16275 | Z42: 11425 | AA42: 18025 | AB42: 11315 | AC42: 13825 | AD42: 99999 | AE42: 2 | AF42: 8 | AG42: 9 | AH42: 19 | AI42: 35 | AJ42: 38 | AK42: 39 | AL42: 46 | AM42: 47 | AN42: 66 | AO42: 67 | AP42: 68 | AQ42: 78 | AR42: 87 | AS42: 534 | AT42: 536 | AU42: 537 | AV42: 552
A43: 42 | B43: Validée | C43: Créer les tickets d'anos selon les commentaires | D43: Tealium | E43: evar2 | F43: visit | G43: "Sur mobile : - si prospect remonte unspecified - si identifié remonte N/A (au lieu de l'identifiant) - si IOS remonte undefined (cause pb client id identifié) Sur le web : - si prospect - DEM remonte s/o - Tunnel remonte 0000000 - si identifie remonte unspecified sur ecommerce et cenet (au lieu de l'identifiant) BP : '"" 0000000 "" au lieu d'absence de valeur pour les applicatifs tunnel et ecommerce" | I43: Id Client (evar2) | J43: Identifiant validé juridiquement et au niveau de la sécurité comme donnée non personnelle et non sensible qui peut être envoyé à des prestataires externes pour des campagnes marketing digital. CE : contient l’identifiant Client MySys (NODAPE) du client authentifié ou identifié. Donnée numérique sur 7 ou 9 caractères contenant les « 0 » non significatifs. BP : identifiant à définir | K43: Pour BP : si la variable n'est pas de 10 caractères => la prop n'est pas alimentée
A44: 43 | B44: Validée | C44: Créer les tickets d'anos selon les commentaires | D44: Tealium | E44: evar3 | F44: visit | G44: "sur mobile : - [dynamique] sur pages pulsar Web : - Unspecified sur rendez en ligne BP : - [""dynamique""] sur l'appli" | I44: Statut Client (evar3) | J44: Contient le niveau de connaissance du client. Authentifié = logué dans la session Identifié = logué dans une session antérieure Prospect = jamais connecté | M44: authentifie | N44: identifie | O44: prospect
A45: 44 | B45: Validée | C45: Créer les tickets d'anos selon les commentaires | D45: Tealium | E45: evar4 | F45: visit | G45: "mobile - pulsar remonte particulier - historique remonte profesionnels Web - ecommerce remonte 101 ... BP : - s/o sur tunnel - Particuliers sur les simulateurs auto et habitations Desktop et dur DP Appli - entreprises et professionnels sur le hub digital - ""Type inconnu"" sur ecommerce - PAR et ENT sur certaines pages Appli Banque Pop - profesionnel sur certaines pages appli BP" | I45: Marché Client (evar4) | J45: Contient le marché du client authentifié ou identifié, vide si prospect | K45: Pour CE : si la variable n'est pas de 9 caractères et contient des lettres => la prop n'est pas alimentée | M45: associations, fondations, mutuelles – mandataires judiciaires a la protection des majeurs | N45: entreprises | O45: hors marche | P45: immobilier professionnel | Q45: logement social - economie mixte | R45: particuliers | S45: professionnels | T45: secteur public
A46: 45 | B46: Validée | C46: Créer les tickets d'anos selon les commentaires | D46: Datalayer | E46: evar5 | F46: hit | I46: Libellé Clic (evar5) | J46: Nom du clic
A47: 46 | B47: Validée | C47: Proposer des catefs de clics (LP, nouveau portail, parcours similaires) pour faire des benchs de taux de clics | D47: Datalayer | E47: evar6 | F47: hit | G47: BP : Sur l'appli, même valeur que libellé clic | I47: Type de Clic (evar6) | J47: Type de clic | M47: action | N47: annuler | O47: cta | P47: envoyer | Q47: menu | R47: navigation | S47: plus tard | T47: rechercher | U47: sortie | V47: telechargement | W47: Validée | X47: vignette | Y47: afficher
A48: 47 | B48: Validée | C48: OK Octobre 2019 | D48: Tealium ou Datalayer | E48: evar7 | F48: hit | I48: Mot-Clé recherché (evar7) | J48: Recherche - Mot clé recherché
A49: 48 | B49: A implémenter (89c3 - Quentin) | C49: BP et CE | D49: Tealium | E49: evar8 | F49: hit | I49: Nombre de résultats de recherche (evar8) | J49: Recherche - Nombre de résultats
A50: 49 | B50: A implémenter (89c3 - Quentin) | C50: BP et CE | D50: Tealium | E50: evar10 | F50: hit | G50: "seulement 50 résultats sur le web 0 sur le mobile" | I50: Url du lien (evar10) | J50: URL du lien
A51: 50 | B51: Validée | D51: ? | E51: evar11 | F51: visit | I51: ABTesting 1 (eVar11) | J51: ABTesting : nom du test ab - variable remplie par Kameleoon
A52: 51 | B52: Validée | D52: ? | E52: evar12 | F52: visit | I52: ABTesting 2 (evar12) | J52: AB Testing : nom de la variation de l'ab test - variable remplie par Kameleoon
A53: 52 | B53: Validée | D53: Tealium | E53: evar13 | F53: hit | I53: Url de la page (evar13) | J53: Url de la Page
A54: 53 | B54: Validée | C54: Demander si utilité du doublon en prop, si non ==> supprimer prop | D54: Adobe Analytics ou Tealium ? | E54: evar14 | F54: hit | I54: Nom du formulaire (evar14) | J54: Nom du formulaire
A55: 54 | B55: Validée | C55: Demander si utilité du doublon en prop, si non ==> supprimer prop | D55: Adobe Analytics ou Tealium ? | E55: evar15 | F55: hit | I55: Identifiant étape (evar15) | J55: Identifiant étape
A56: 55 | B56: Validée | D56: Datalayer | E56: evar22 | F56: hit | I56: Type du compte (evar22) | J56: Libellé du compte sans info personnelle (CDD, AssVie,…)
A57: 56 | B57: Validée | D57: Datalayer | E57: evar23 | F57: hit | I57: Type de virement (evar23) | J57: Type de virement (externe ou interne)
A58: 57 | B58: Validée | D58: Datalayer | E58: evar24 | F58: hit | I58: Montant du virement (evar24) | J58: Montant du virement
A59: 58 | B59: A implémenter (89c3 - MT) | C59: Modifier le nom et créer l'ano pour corriger | D59: Datalayer | E59: evar25 | F59: hit | I59: Numéro de Raison du message (evar25) | J59: Numéro de Raison du message
A60: 59 | B60: Validée | D60: Datalayer | E60: evar27 | F60: hit | I60: Nom du PDF (evar27) | J60: Nom du PDF
A61: 60 | B61: Validée | D61: Datalayer | E61: evar28 | F61: hit | I61: Formule choisie (evar28 | J61: Formule choisie
A62: 61 | D62: Datalayer | E62: evar29 | F62: hit | I62: Montant de la remise (evar29) | J62: Montant de la promotion, ou remise commerciale visible par l'utilisateur au moment d'une action (affichage d'une page, popin, clic…). Remise sous forme de pourcentage, format "0.5" pour 50%. | M62: 0.5 | N62: 0.1 | O62: …
A63: 62 | B63: Validée | D63: Datalayer | E63: evar35 | F63: hit | I63: je cherche a assurer (evar35) | J63: Dans Devis et simulations / Obtenir un tarif (HABITATION) étape 1 Variables implémentées mais non utilisée par BPCE central et bientôt désuètes vs le nouveau plan de taggage INNOV2025
A64: 63 | B64: Validée | D64: Datalayer | E64: evar41 | F64: hit | I64: Montant initial (evar41) | J64: Montant du versement initial lors des formulaires devis et souscriptions de crédit
A65: 64 | B65: Validée | D65: Datalayer | E65: evar42 | F65: hit | I65: Montant des mensualités (eVar42) | J65: Montant des mensualités lors des formulaires devis et souscriptions de crédit
A66: 65 | B66: Validée | D66: Datalayer | E66: evar43 | F66: hit | I66: Taux (eVar43) | J66: Taux du prêt lors des formulaires devis et souscriptions de crédit
A67: 66 | B67: Documentation à modifier (89c3 - performance digitale) | C67: A modifier dans le sharepoint, propriété et variable terminée | D67: ? | E67: evar44 | F67: hit | I67: Dernier univers visité (eVar44)
A68: 67 | B68: Validée | D68: Datalayer | E68: evar46 | F68: hit | I68: Type consultation Devis (evar46)
A69: 68 | B69: Validée | D69: Tealium | E69: evar49 | F69: hit | I69: suivi vignette
A70: 69 | B70: Validée | D70: Tealium | E70: evar50 | F70: hit | I70: page | J70: Nom de la page
A71: 70 | B71: Validée | D71: Tealium | E71: evar51 | F71: hit | I71: marche | J71: Nom du marché de la page
A72: 71 | B72: Validée | D72: ? | E72: evar53 | F72: hit | I72: type de financement | J72: Choix du type de financement
A73: 72 | B73: Validée | D73: Datalayer | E73: evar54 | F73: hit | I73: type de credit | J73: Choix du type de credit
A74: 73 | B74: Validée | C74: Alimentation à corriger Documentation à corriger, ce sont les options clients pour configurer l'offre BL | D74: Datalayer | E74: evar56 | F74: hit | I74: Option BL / non optin | J74: Non optin CRM
A75: 74 | B75: A remplacer | C75: Double alimentation / Verifier l'utilisation du dernier produit côté CE, dans ce cas voir pour changer la variable credit conso A supprimer | D75: Datalayer | E75: evar57 | F75: hit | I75: Dernier produit | J75: Dernier porduit consulté pour erebond
A76: 75 | B76: Validée | D76: Datalayer | E76: evar59 | F76: hit | I76: type de souscription de carte | J76: type de la demande de souscription carte : remplacement ou nouvelle carte | M76: remplacement | N76: nouvelle carte
A77: 76 | B77: Validée | D77: Datalayer | E77: evar66 | F77: hit | I77: nombre de simulation effectué (sim credit conso) | J77: Remonte le nombre de simulation (modification reglette/champ) à pousser sur la page suivante de navigation
A78: 77 | B78: Validée | D78: Datalayer | E78: evar67 | F78: hit | I78: Profil client | J78: profil du client (formulaires ACL) | M78: particulier | N78: entreprise
A79: 78 | B79: A implémenter (89c3 - MT) | C79: Implémenter côté CE | D79: Datalayer | E79: evar68 | F79: hit | I79: Score souscription | J79: Score lors d'une souscription credit conso | M79: vert | N79: orange | O79: rouge
A80: 79 | B80: Validée | D80: Datalayer | E80: evar69 | F80: hit | I80: Nombre de justificatifs uploadés | J80: [formulaire enjoy] dernière étape, nombre de justificatifs téléchargés par l'utilisateur
A81: 80 | B81: Validée | D81: Datalayer | E81: evar70 | F81: hit | I81: numero user | J81: Identifiant du user lors d'une connexion à CENET
A82: 81 | B82: Validée | C82: Mapping prévu Novembre 2019 | D82: Datalayer | E82: evar72 | F82: hit | I82: conjoint CoEmprunteur | J82: tunnel souscription credit conso : si le conjoint est co emprunteur ou non | M82: conjoint coemprunteur oui | N82: conjoint coemprunteur non
A83: 82 | B83: Validée | D83: Datalayer | E83: evar73 | F83: hit | I83: assurance coemprunteur | J83: si conjoint coemprunteur (tunnel credit conso), adhere t'il a l'assurance proposé ou non | M83: conjoint adhesion assurance | N83: conjoint refus assurance
A84: 83 | B84: A implémenter (89c3 - Alex) | C84: A implémenter sur BP | D84: Datalayer | E84: evar74 | F84: hit | I84: typeOpposition | J84: pilotage de la carte: opposition en ligne : type d'opposition | M84: vol | N84: perte | O84: operations frauduleuses sur compte
A85: 84 | B85: A implémenter (89c3 - Nicolas) | C85: A implémenter sur BP | D85: Datalayer | E85: evar75 | F85: hit | I85: type d'erreur
A86: 85 | B86: Validée | D86: Tealium | E86: evar80 | F86: hit | I86: cid | J86: Récupérer l'information contenu dans le CID (paramètre de l'URL)
A87: 86 | B87: Validée | C87: En cours d'intégration Novembre 2019 | D87: Datalayer | E87: evar82 | F87: hit | I87: Nom du projet | J87: Récupérer le nom du projet
A88: 87 | B88: Validée | D88: Datalayer | E88: evar83 | F88: hit | I88: hash | J88: Hash du nom, prénom et date de naissance pour constituer un identifiant prospect
A89: 88 | B89: A mapper (89c3 - Nicolas) | C89: A mapper côté BP | D89: Datalayer | E89: evar84 | F89: hit | I89: Numéro de SIREN | J89: SIREN de la collectivité ayant demandé le dossier
A90: 89 | B90: A mapper (89c3 - Nicolas) | C90: A mapper côté BP | D90: Datalayer | E90: evar85 | F90: hit | I90: Nom de la Collectivité | J90: Nom de la collectivité ayant demandé le dossier
A91: 90 | B91: A mapper (89c3 - Nicolas) | C91: A mapper côté BP | D91: Datalayer | E91: evar86 | F91: hit | I91: Durée du prêt | J91: Durée de prêt choisie en mois
A92: 91 | B92: A mapper (89c3 - Nicolas) | C92: A mapper côté BP | D92: Datalayer | E92: evar87 | F92: hit | I92: Périodicité du prêt | J92: Périodicité du prêt choisi (en mois)
A93: 92 | B93: Documentation à modifier (89c3 - performance digitale) | C93: Clarifier le naming | D93: Datalayer | E93: evar89 | F93: hit | I93: fonctionnalite | J93: Décris la fonctionnalité sur laquelle se trouve l'utilisateur => permet de suivre quand un même parcours est décliné sous plusieurs formes (ex : plusieurs points d'entrée) | L93: minuscule, sans caractères spéciaux | M93: enrolement | N93: marketing digital | O93: transfert | P93: reinstallation | Q93: code sp oublié | R93: enrolement ptu | S93: code sp oublie usage
A94: 93 | B94: Documentation à modifier (89c3 - performance digitale) | C94: Revoir le wording de la variable (provenance usage) | D94: ? | E94: evar90 | F94: hit | I94: provenance | J94: Décris si une opération est inband ou outband | M94: outband | N94: inband
A95: 94 | B95: Documentation à modifier (89c3 - performance digitale) | C95: Clarifier le naming / Remplir la doc | D95: Datalayer | E95: evar91 | F95: hit | I95: type | J95: - Famille SecurPass et mes comptes - Collecte BP : type du document cliqué sur l'onglet Crédit ou Autre | L95: - Collecte : page "envoi de documents - credits" => variable : natureDossierVente (code produit - classification à mettre en place) - Collecte : page "envoi de documents - autres" => variable : typeDocument.label | M95: reglages | N95: usage | O95: connexion | P95: reglages biometrie
A96: 95 | B96: Documentation à modifier (89c3 - performance digitale) | C96: Clarifier le naming / Remplir la doc | D96: ? | E96: evar92 | F96: hit | I96: contexte | J96: Contexte de l'usage securpass
A97: 96 | B97: Documentation à modifier (89c3 - performance digitale) | C97: Voir si pas intéressant de découper l'evar91 en deux pour renseigner le type de compte ici | D97: ? | E97: evar93 | F97: hit | I97: typeFamille - à supprimer de Tealium et Adobe | J97: type de compte sur le parcours mes comptes
A98: 97 | B98: Validée | C98: Remplir la doc pour préciser la contenu (Meniga / DP Web ?) | D98: ? | E98: evar94 | F98: hit | I98: libelle | J98: libellé de l'action / produit / recherche
A99: 98 | B99: Validée | D99: Kameleoon | E99: evar95 | F99: hit | I99: ABTesting 3 (evar95) | J99: ABTesting : nom du test ab - variable remplie par Kameleoon
A100: 99 | B100: Validée | D100: Kameleoon | E100: evar96 | F100: hit | I100: ABTesting 4 (eVar96) | J100: ABTesting : nom du test ab - variable remplie par Kameleoon
...

Sheet Echantillon valeurs CE
B1: CE
A3: prop4 | B3: prop7 | C3: prop8 | D3: prop9 | G3: prop10 | J3: prop14 | K3: prop15 | L3: prop16 | N3: prop17 | Q3: prop18 | T3: prop 19 | U3: prop 20 | V3: prop 22 | W3: prop 30 | X3: prop 31 | Y3: evar 1 | Z3: evar 2 | AA3: evar 3 | AB3: evar 4 | AC3: evar 5 | AD3: evar 6 | AG3: evar 14 | AH3: evar 27 | AI3: evar 30 | AJ3: evar 31 | AK3: evar 32 | AL3: evar 33 | AM3: evar 34 | AN3: evar 35 | AO3: evar 36 | AP3: evar 37 | AQ3: evar 38 | AR3: evar 39 | AS3: evar 45 | AT3: evar 46 | AU3: evar 50
D4: 88 valeurs, ne correspondant pas à l'attendu (probablement objet d'un scrapping) | G4: inutilisable d'un point de vue analyse | J4: Nom pas en liste exhaustive, mais couvre le périmètre selfcare, assurance, souscription, portail commercial (223 valeurs sensément exhaustif) | T4: 500K valeurs | U4: implémentée, mais inutilisable | V4: non implémentée, aucun référentiel de valeurs | W4: implémenté sur plusieurs pages du parcours des devis auto et devis flash | X4: Valeurs à vocation à être adaptatives (136K valeurs) Règle de gestion : nom de la page déclenchée au moment du clic | Y4: ISO à prop1 | Z4: ISO à prop2 | AA4: ISO à prop3 | AB4: ISO à prop4 | AC4: Valeurs à vocation à être adaptatives (50K valeurs) | AG4: ISO à prop14 | Valeurs à vocation à être adaptatives, mais couvre le périmètre selfcare, assurance, souscription, portail commercial (223 valeurs, sensément exhaustif) | AH4: Valeurs à vocation à être adaptatives | AU4: Valeurs à vocation à être adaptatives Règle de gestion : nom de la page déclenchée au moment du clic
A5: Particuliers | B5: Banque | C5: Particuliers | D5: acces | E5: 13746 | F5: agences et distributeurs | G5: acces et securite | H5: 897 | I5: conseil | J5: virement | K5: 0 | L5: transactionnel | M5: 4209082103 | N5: Ecran d'identification | O5: 1103390194 | P5: assurance | Q5: 2Roues | R5: 9629 | S5: assepargne | W5: 1 | AC5: en savoir plus | AD5: Valider | AE5: 454858765 | AF5: action | AG5: virement | AH5: Attestation.pdf | AT5: Initial
A6: Professionnels | B6: dei part | C6: Professionnels | D6: accueil | E6: 57 | F6: assistance | G6: accueil | H6: 4 | I6: consultation | J6: Devis Auto | K6: 100 | L6: Commercial | M6: 615808020 | N6: transactionnel | O6: 1030512453 | P6: bancarisation | Q6: 3d nuances | R6: 588 | S6: assurance 2 roues | V6: =CONCATENATE(T6," ",U6) | AC6: validation | AD6: Tuile | AE6: 185298243 | AF6: annuler | AG6: Devis Auto | AH6: conditions_generales | AT6: Reprise
A7: particulier | B7: eCommerce | C7: particulier | D7: Agence | E7: 58002 | F7: assurer | G7: ajout document header | H7: 87 | I7: contact | J7: rendez vous en ligne | K7: 22.1 | L7: erreur | M7: 12611021 | N7: Tableau de bord | O7: 935889488 | P7: credit conso | Q7: a booklet | R7: 434682 | S7: assurance auto | V7: =CONCATENATE(T7," ",U7) | AC7: clic tuile | AD7: Navigation | AE7: 165225679 | AF7: cta | AG7: rendez vous en ligne | AH7: CG.pdf
A8: entreprises | B8: selfcare | C8: entreprises | D8: aide | E8: 1434 | F8: au quotidien | G8: ajout document liste | H8: 78119589 | I8: document | J8: credit immo | K8: … | L8: Commercredit immoal | M8: 30435 | N8: Mes comptes | O8: 218670633 | P8: credit immo | Q8: aikido | R8: 41 | S8: assurance emprunteur | V8: =CONCATENATE(T8," ",U8) | AC8: … | AD8: menu | AE8: 161374148 | AF8: envoyer | AG8: credit immo | AH8: Attestation
A9: associations fondations mutuelles - mandataires judiciaires la protection des majeurs | B9: cenet | C9: associations fondations mutuelles - mandataires judiciaires la protection des majeurs | D9: assurance | E9: 4 | F9: banque au quotidien et assurance | G9: assurances | H9: 1042 | I9: edito | J9: … | K9: … | L9: documents recents | M9: 9126 | N9: compte | O9: 207134076 | P9: credit pro | Q9: aïkido | R9: 46 | S9: assurance moyen paiement | V9: =CONCATENATE(T9," ",U9) | AC9: … | AD9: action | AE9: 56163588 | AF9: menu | AG9: …
A10: economie sociale et institutionnelle | B10: dei pro | C10: economie sociale et institutionnelle | D10: Assurer | E10: 875 | F10: connexion | G10: Assurer | H10: 116 | I10: erreur | J10: … | K10: … | L10: interne | M10: 2826 | N10: virements | O10: 182082641 | P10: epargne financiere | Q10: alertecureuil | R10: 561 | S10: assurance mrh | V10: =CONCATENATE(T10," ",U10) | AC10: … | AD10: Appel | AE10: 21440167 | AF10: navigation | AG10: …
A11: personne protegee | B11: DEM | C11: personne protegee | D11: Au quotidien | E11: 93771920 | F11: contact | G11: Attestations | H11: 4672339 | I11: faq | J11: … | L11: dossier personnel | M11: 1846 | N11: Barre de navigation | O11: 165255550 | P11: epargne liquide | Q11: applepay | R11: 1625 | S11: assurance resp civile | V11: =CONCATENATE(T11," ",U11) | AC11: … | AD11: validation | AE11: 17171095 | AF11: plus tard | AG11: …
A12: Associations, Fondations, Mutuelles - Mandataires Judiciaires a la Protection des Majeurs | B12: DEA | C12: Associations, Fondations, Mutuelles - Mandataires Judiciaires a la Protection des Majeurs | D12: authentification | E12: 3004635 | F12: emprunter | G12: Au quotidien | H12: 34 | I12: formulaire | L12: ajout document header | M12: 1042 | N12: erreur | O12: 54937689 | Q12: applismartphone | R12: 69 | S12: assurance voyage | V12: =CONCATENATE(T12," ",U12) | AD12: Activer | AE12: 16900384 | AF12: rechercher
A13: Immobilier professionnel | B13: tunnel | C13: Immobilier professionnel | D13: Avis | E13: 1662701 | F13: epargner | G13: authentification | H13: 445915 | I13: gammes | L13: dossier bancaire | M13: 706 | N13: Accès rapide | O13: 34178917 | Q13: Ass Compte | R13: 1568 | S13: bourse | V13: =CONCATENATE(T13," ",U13) | AD13: Besoin | AE13: 9248357 | AF13: sortie
A14: logement social - conomie mixte | B14: BCP Net Part | C14: logement social - conomie mixte | D14: Banque au quotidien et Assurance | E14: 1059088 | F14: financement | G14: Avis store | H14: 36865238 | I14: home | L14: historique modification | M14: 380 | N14: Prélèvement | O14: 26446417 | Q14: Ass Epargne | R14: 1649 | S14: carte | V14: =CONCATENATE(T14," ",U14) | AD14: Contact | AE14: 5703749 | AF14: telechargement
A15: Secteur public | B15: dei pp | C15: Secteur public | D15: Barre de navigation | E15: 90330464 | F15: gestion privee | G15: Banque au quotidien et Assurance | H15: 1 | I15: information | L15: dossier a classer | M15: 374 | N15: Messagerie | O15: 25844330 | Q15: assauto | R15: 625 | S15: cat | V15: =CONCATENATE(T15," ",U15) | AD15: sortie | AE15: 5068051 | AF15: valider
A16: institutionnels | B16: ngi | C16: institutionnels | D16: carte bancaire | E16: 1027335 | F16: ma banque pratique | G16: BCP Net | H16: 1673343 | I16: marche | L16: documents signales | M16: 351 | N16: Assurances | O16: 21154370 | Q16: assistancevie | R16: 33101 | S16: cel | V16: =CONCATENATE(T16," ",U16) | AD16: Parametrer | AE16: 3460771 | AF16: vignette
A17: Logement Social - Économie Mixte | B17: dp mobile | C17: Logement Social - Économie Mixte | D17: cartes bancaires | E17: 67 | F17: ma synthese | G17: beneficiaires | H17: 338895 | I17: operation | L17: ajout document liste | M17: 116 | N17: E-Documents | O17: 19751432 | Q17: assistant obsèques financement | R17: 65 | S17: cfn | V17: =CONCATENATE(T17," ",U17) | AD17: Vignette | AE17: 3315160
A18: financements spcialiss | B18: deep purple | C18: financements spcialiss | D18: chequiers | E18: 91 | F18: mes assurances | G18: bloc_thematiquemultipanels | H18: 5412292 | I18: page_ccd | L18: resultats recherche | M18: 103 | N18: RIB/IBAN | O18: 17815815 | Q18: assur.vie 1818 | R18: 55 | S18: compte-courant | V18: =CONCATENATE(T18," ",U18) | AD18: annuler | AE18: 3266040
A19: profesionnel | B19: mbl | C19: profesionnel | D19: choisir sa caisse | E19: 66695 | F19: mes cartes et paiement | G19: carte | H19: 12274731 | I19: popin | L19: profil | M19: 42 | N19: Météo / Agrégation / Budget | O19: 17720189 | Q19: assurance2roues | R19: 203 | S19: credit conso auto | V19: =CONCATENATE(T19," ",U19) | AD19: cta | AE19: 2954708
A20: logement social - économie mixte | B20: evi | C20: logement social - économie mixte | D20: code confidentiel oublie | E20: 352126 | F20: mes comptes | G20: code confidentiel oublie | H20: 21344093 | I20: produit | L20: organisme emetteur - tous les organismes emetteurs | M20: 29 | N20: bancarisation | O20: 16869593 | Q20: Assurance-auto | R20: 4096 | S20: credit conso etudiant | V20: =CONCATENATE(T20," ",U20) | AD20: identification | AE20: 2714280
A21: s/o | B21: harvest | C21: s/o | D21: code confidentiel oublié | E21: 2848679 | F21: mes credits | G21: collecte justificatif | H21: 19202392 | I21: profil | L21: organisme emetteur - impots | M21: 14 | N21: moyens de paiement | O21: 14627694 | Q21: assuranceautopro | R21: 91 | S21: credit conso travaux | V21: =CONCATENATE(T21," ",U21) | AD21: Telechargement | AE21: 2322902
B22: lac | D22: collectivites locales | E22: 2358 | F22: messagerie | G22: compte | H22: 1297924 | I22: recherche | L22: organisme emetteur - banque finance | M22: 11 | N22: Contact | O22: 8800506 | Q22: assurancehabitationsante | R22: 4036 | S22: credit conso tresorie | V22: =CONCATENATE(T22," ",U22) | AD22: Envoyer PDF | AE22: 1999246
B23: hub digital | D23: comptes | E23: 1009847926 | F23: mon agence | G23: comptes | H23: 11455 | I23: recherche agence | L23: organisme emetteur - emploi retraite | M23: 2 | N23: Crédit | O23: 7869611 | Q23: Assurance-MRH | R23: 38 | S23: credit immo | V23: =CONCATENATE(T23," ",U23) | AD23: Link | AE23: 1644476
B24: BDCL | D24: connexion | E24: 1719 | F24: mon coffre fort | G24: condition_generale | H24: 111504662 | I24: univers | L24: organisme emetteur - telephonie internet tv | M24: 2 | N24: Paramètres | O24: 7080764 | Q24: assurancemultirisquepro | R24: 340 | S24: credit immo primo | V24: =CONCATENATE(T24," ",U24) | AD24: button | AE24: 1336061
B25: dei sp | D25: Contact | E25: 12725715 | F25: mon epargne | G25: configuration | H25: 732752270 | L25: organisme emetteur - sante mutuelles de sante | M25: 2 | N25: Personnaliser tableau de bord | O25: 6664785 | Q25: assuranceprotectionjuridique | R25: 207 | S25: credit pro | V25: =CONCATENATE(T25," ",U25) | AD25: Pub | AE25: 1229357
B26: CE | D26: Credit | E26: 1686250 | F26: mon profil | G26: confirmation | H26: 96923 | L26: organisme emetteur - ecommerce | M26: 1 | N26: credit immo | O26: 5564038 | Q26: assurancesurcomptefamille | R26: 161 | S26: eparfix | V26: =CONCATENATE(T26," ",U26) | AD26: Vignette Majeure | AE26: 1228508
B27: banque | D27: Crédit | E27: 6892273 | F27: parametres | G27: conseil | H27: 67457 | L27: organisme emetteur - administration famille | M27: 1 | N27: Mot de passe oublie et id oublie | O27: 4735757 | Q27: Assurance-voyage | R27: 3593 | S27: gav | V27: =CONCATENATE(T27," ",U27) | AD27: Gestion | AE27: 953459
B28: communication | D28: credits | E28: 3459225 | F28: placement | G28: consultation | H28: 3427581 | L28: organisme emetteur - eau electricite gaz | M28: 1 | N28: Acces rapide | O28: 3273880 | Q28: assurecureuil | R28: 53 | S28: internet | V28: =CONCATENATE(T28," ",U28) | AD28: plus tard | AE28: 746003
B29: 89c3.com | D29: Didacticiel | E29: 382860 | F29: politique sociale | G29: Consultation contrat | H29: 22994864 | N29: Simulateurs Epargne | O29: 2729718 | Q29: assurécureuil | R29: 1578 | S29: ldd | V29: =CONCATENATE(T29," ",U29) | AD29: Retour | AE29: 705576
B30: digital briefcase | D30: Ecran d'identification | E30: 1047854905 | F30: prelevements | G30: Consultation devis | H30: 14402 | N30: Simulateurs Crédit | O30: 2720638 | Q30: assurtoit | R30: 2031 | S30: lep | V30: =CONCATENATE(T30," ",U30) | AD30: Rechercher | AE30: 689643
B31: store 89c3 | D31: emprunter | E31: 12149298 | F31: virements | G31: Consultation Edocument | H31: 5318848 | N31: credit conso | O31: 2612053 | Q31: assurtoitjeunes | R31: 3720 | S31: livret a | V31: =CONCATENATE(T31," ",U31) | AD31: search | AE31: 593881
B32: hub digital | D32: engagements par signature | E32: 5126 | G32: contact | H32: 40056 | N32: DEA | O32: 2588781 | Q32: asvalacarte | R32: 1926 | S32: livret b | V32: =CONCATENATE(T32," ",U32) | AD32: Vignette Mineure | AE32: 544060
B33: visa | D33: enrolement | E33: 10248 | G33: contenus_externes | H33: 2251898 | N33: Agences / Distributeurs | O33: 2424893 | Q33: Auto | R33: 53 | S33: livret grand format | V33: =CONCATENATE(T33," ",U33) | AD33: Téléchargement | AE33: 488495
D34: Epargner | E34: 5143237 | G34: coordoonnees | H34: 2032125 | N34: Virement | O34: 2191035 | Q34: AUTO3 | R34: 129 | S34: livret grand prix | V34: =CONCATENATE(T34," ",U34) | AD34: historique | AE34: 356839
D35: erreur | E35: 58503977 | G35: credit | H35: 278163 | N35: Prelevement | O35: 2177643 | Q35: AUTO4 | R35: 4409961 | S35: livret jeune | V35: =CONCATENATE(T35," ",U35) | AD35: Financement | AE35: 197452
D36: Financement | E36: 141097 | G36: credits | H36: 1601792 | N36: Retrait SMS | O36: 1924733 | Q36: autotaxi | R36: 129486 | S36: obseques | V36: =CONCATENATE(T36," ",U36) | AD36: Remboursement | AE36: 140977
D37: Financer | E37: 3718 | G37: Dec sin Parabancaire | H37: 143 | N37: Credit | O37: 1727816 | Q37: avancesurbourse | R37: 124434 | S37: opcvm | V37: =CONCATENATE(T37," ",U37) | AD37: Continuer | AE37: 108545
D38: Gérer | E38: 7687 | G38: Dec sin Secur Media | H38: 2520156 | N38: profil | O38: 816821 | Q38: banxo | R38: 51 | S38: paiement | V38: =CONCATENATE(T38," ",U38) | AD38: sim credit immo - valider | AE38: 73628
D39: gestion | E39: 11827 | G39: dei | H39: 60777 | N39: Identification | O39: 558838 | Q39: BCP PATRIMONIO CRESCENTE | R39: 37 | S39: pea | V39: =CONCATENATE(T39," ",U39) | AD39: naviguer | AE39: 64072
D40: gestion abonnement | E40: 55581 | G40: devies en ligne | H40: 53121 | N40: Assistance / opposition | O40: 555094 | Q40: bouquet liberte | R40: 100 | S40: pel | V40: =CONCATENATE(T40," ",U40) | AD40: erreur | AE40: 24286
D41: hub digital b2b | E41: 16389 | G41: Devis 2Roues | H41: 968722737 | N41: Mes crédits | O41: 518754 | Q41: bouquetliberte | R41: 594 | S41: pj | V41: =CONCATENATE(T41," ",U41) | AD41: Souscription | AE41: 20987
D42: identifiant oublie | E42: 300821 | G42: Devis Auto | H42: 2 | N42: Informations | O42: 493174 | Q42: bouquetlibertefamille | R42: 167285 | S42: retrait inter | V42: =CONCATENATE(T42," ",U42) | AD42: sim credit immo – autre sim | AE42: 10954
D43: identifiant oublié | E43: 1112143 | G43: Devis MRH | H43: 204343 | N43: Mes comptes favoris | O43: 428509 | Q43: bouquetlibertejeunes | R43: 1006 | S43: sante | V43: =CONCATENATE(T43," ",U43) | AD43: Itineraire | AE43: 10577
D44: identification | E44: 2357647 | G44: document | H44: 1595497 | N44: Cartes et paiement | O44: 397449 | Q44: bourseopcrecompenses | R44: 125 | S44: securmedia | V44: =CONCATENATE(T44," ",U44) | AD44: Noter | AE44: 8672
D45: Ma banque pratique | E45: 1101088 | G45: documents recents | H45: 782092 | N45: Didacticiel | O45: 384132 | Q45: campagneassurancevie | R45: 839 | S45: visuel carte | V45: =CONCATENATE(T45," ",U45) | AD45: sim credit immo – modifier | AE45: 6929
D46: ma messagerie | E46: 80610418 | G46: documents signales | H46: 11583 | N46: Simulateurs Credit | O46: 360203 | Q46: capciel | R46: 37 | V46: =CONCATENATE(T46," ",U46) | AD46: sim credit immo – annuler | AE46: 4668
D47: Ma synthese | E47: 122922952 | G47: dossier | H47: 9111 | N47: Simulateur Immo | O47: 293442 | Q47: captio croissance | R47: 227 | V47: =CONCATENATE(T47," ",U47) | AD47: Social | AE47: 2741
D48: Ma synthèse | E48: 1214592660 | G48: dossier a classer | H48: 351 | N48: sav | O48: 198081 | Q48: captio pre. | R48: 19536 | V48: =CONCATENATE(T48," ",U48) | AD48: oui | AE48: 2675
D49: Ma synth�se | E49: 20198095 | G49: dossier bancaire | H49: 480 | N49: Parametres | O49: 146468 | Q49: captioprestance | R49: 1911 | V49: =CONCATENATE(T49," ",U49) | AD49: non | AE49: 1766
D50: Mes assurances | E50: 23689961 | G50: dossier personnel | H50: 373 | N50: credit pro | O50: 89149 | Q50: Carte | R50: 2719 | V50: =CONCATENATE(T50," ",U50) | AD50: sim credit immo primo - valider | AE50: 1739
D51: Mes comptes | E51: 789978312 | G51: dossier_conseil | H51: 706 | N51: Assurance | O51: 65683 | Q51: carteachatpublic_sp | R51: 41 | V51: =CONCATENATE(T51," ",U51) | AD51: SEPAMAIL | AE51: 1287
D52: Mes credits | E52: 458575 | G52: eagence | H52: 1841 | N52: Simulateur Epargne | O52: 55155 | Q52: cartebancairerechargeable | R52: 312857 | V52: =CONCATENATE(T52," ",U52) | AD52: sim CEL - valider | AE52: 1095
D53: mes crédits | E53: 15608007 | G53: Emprunter | H53: 3376207 | N53: reglages | O53: 33290 | Q53: cartederetraitnomeaparts | R53: 41 | V53: =CONCATENATE(T53," ",U53) | AD53: sim obseques - valider | AE53: 842
D54: Mon agence | E54: 2370998 | G54: Epargner | H54: 3195 | N54: Montre connectée | O54: 30023 | Q54: carteinterbancaireequilibra | R54: 838 | V54: =CONCATENATE(T54," ",U54) | AD54: aide | AE54: 726
D55: mon coffre fort | E55: 26949 | G55: erreur | H55: 98346 | N55: epargne liquide | O55: 23150 | Q55: cartevisabusiness | R55: 101 | V55: =CONCATENATE(T55," ",U55) | AD55: sim credit immo ptz - valider | AE55: 612
D56: Mon epargne | E56: 268735 | G56: Espace Assurance | H56: 260090 | N56: Montre connectee | O56: 7173 | Q56: cartevisabusiness_pro | R56: 90 | V56: =CONCATENATE(T56," ",U56) | AD56: – valider | AE56: 568
D57: mon épargne | E57: 82977985 | G57: espace_transactionnel | H57: 7992578 | N57: Infos Editeur | O57: 5597 | Q57: cartevisaclassic | R57: 68 | V57: =CONCATENATE(T57," ",U57) | AD57: Prise RDV | AE57: 431
... D83: s assurer | E83: 10787 | G83: marche | H83: 1 | N83: Barre de navgaton | O83: 6 | Q83: cat slr 7 ans | R83: 6558 | V83: =CONCATENATE(T83," ",U83) | AD83: OFF | AE83: 1
D84: S'assurer | E84: 2220884 | G84: mon conseiller/mon agence | H84: 15 | N84: Agences / Dstrbuteurs | O84: 5 | Q84: cat slr 8 ans | R84: 23508 | V84: =CONCATENATE(T84," ",U84)
D85: securpass | E85: 756475 | G85: mon profil | H85: 303772110 | O85: 1 | Q85: cat slr 9 ans | R85: 2879 | V85: =CONCATENATE(T85," ",U85)
D86: sous livret a | E86: 97 | G86: nav_page | H86: 10 | Q86: ce slr 10 ans | R86: 6495 | V86: =CONCATENATE(T86," ",U86)
D87: sous tirelire | E87: 765 | G87: Nos produits pour emprunter | H87: 4 | Q87: ce slr 11 ans | R87: 1046 | V87: =CONCATENATE(T87," ",U87)
D88: souscription client | E88: 3755 | G88: Nos produits pour épargner | H88: 2197756 | Q88: ce slr 12 ans | R88: 1462 | V88: =CONCATENATE(T88," ",U88)
D89: timeout | E89: 157232 | G89: Nos produits pour gérer son quotidien | H89: 989 | Q89: ce slr 13 ans | R89: 175 | V89: =CONCATENATE(T89," ",U89)
D90: TouchID | E90: 556565 | G90: Nos produits pour gérer votre quotidien et vos assurances | H90: 2646 | Q90: ce slr 14 ans | R90: 237 | V90: =CONCATENATE(T90," ",U90)
D91: usage | E91: 209975 | G91: Nos produits pour s’assurer | H91: 31351 | Q91: ce slr 15 ans | R91: 85 | V91: =CONCATENATE(T91," ",U91)
D92: virements | E92: 433608170 | G92: Nos produits pour vos financements | H92: 1100 | Q92: ce slr 16 ans | R92: 168 | V92: =CONCATENATE(T92," ",U92)
G93: Nos produits pour vos placements | H93: 7090 | Q93: ce slr 3 ans | R93: 143 | V93: =CONCATENATE(T93," ",U93)
G94: Nos produits pour votre politique sociale | H94: 142 | Q94: ce slr 4 ans | R94: 4574 | V94: =CONCATENATE(T94," ",U94)
G95: Obtenir tarif | H95: 19 | Q95: ce slr 5 ans | R95: 2933 | V95: =CONCATENATE(T95," ",U95)
G96: OPCVM | H96: 60 | Q96: ce slr 6 ans | R96: 920 | V96: =CONCATENATE(T96," ",U96)
G97: operation | H97: 15 | Q97: ce slr 7 ans | R97: 898 | V97: =CONCATENATE(T97," ",U97)
G98: organisme emetteur - administration famille | H98: 2334 | Q98: ce slr 8 ans | R98: 785 | V98: =CONCATENATE(T98," ",U98)
G99: organisme emetteur - banque finance | H99: 315029 | Q99: ce slr 9 ans | R99: 307 | V99: =CONCATENATE(T99," ",U99)
G100: organisme emetteur - eau electricite gaz | H100: 1 | Q100: CEL | R100: 838 | V100: =CONCATENATE(T100," ",U100)
G101: organisme emetteur - ecommerce | H101: 11 | Q101: cenet | R101: 110 | V101: =CONCATENATE(T101," ",U101)
G102: organisme emetteur - emploi retraite | H102: 1 | Q102: certificatelectroniquecerticeo | R102: 57161 | V102: =CONCATENATE(T102," ",U102)
G103: organisme emetteur - impots | H103: 1 | Q103: certificatelectroniquecerticeo_pro | R103: 222 | V103: =CONCATENATE(T103," ",U103)
G104: organisme emetteur - sante mutuelles de sante | H104: 2 | Q104: cfn | R104: 37 | V104: =CONCATENATE(T104," ",U104)
F105: 6 | G105: organisme emetteur - telephonie internet tv | H105: 14 | Q105: code confidentiel oublie | R105: 349 | V105: =CONCATENATE(T105," ",U105)
G106: organisme emetteur - tous les organismes emetteurs | H106: 2 | Q106: coffrefortnumerique | R106: 62 | V106: =CONCATENATE(T106," ",U106)
G107: page_ccd | H107: 2 | Q107: comprendremarchesfinanciers | R107: 1325328 | V107: =CONCATENATE(T107," ",U107)
G108: page_choix_region | H108: 29 | Q108: compte cantonnement | R108: 1383 | V108: =CONCATENATE(T108," ",U108)
G109: parametres | H109: 484449 | Q109: compte cheque | R109: 106 | V109: =CONCATENATE(T109," ",U109)
G110: paylib | H110: 58599 | Q110: compte excedent prof | R110: 18969
G111: Placement | H111: 84257 | Q111: compte numeraire pea | R111: 22146064
G112: Placer | H112: 3587098 | Q112: compte titres | R112: 124015
G113: Politique sociale | H113: 1900 | Q113: Compte-courant | R113: 81256
G114: popin | H114: 28 | Q114: comptecourantassociation | R114: 22031
G115: produit | H115: 1455 | Q115: comptelivretregional | R115: 5766
G116: profil | H116: 11444955 | Q116: comptetitresordinaires | R116: 238
G117: recherche | H117: 15375233 | Q117: consoplan | R117: 154
G118: recherche_agence | H118: 40312 | Q118: cpt courant ent. | R118: 172
G119: redirect | H119: 2366608 | Q119: cpt courant entrepri | R119: 1234
G120: refus | H120: 603604 | Q120: cpt depot part. | R120: 549271
G121: resultats recherche | H121: 531 | Q121: cpt depot prof. | R121: 168503
... G170: visuel carte | H170: 8361783 | Q170: cslr rhone alpes | R170: 2028
H171: 213438446 | Q171: decouvertadapte | R171: 3474
H172: 170903 | Q172: dediance 1818 | R172: 11538
Q173: dediance-1818 | R173: 623
Q174: dediancecap1818 | R174: 324
...

Sheet Valeurs consolidées
A1: Référentiel de valeurs consolidé
A4: Grille de lecture :
B5: Choisir une/des valeurs pertinentes listées dans cet onglet (et voir le distinguo de valeurs CE et BP dans les onglets BP et CE)
B6: Choisir une/des valeur parmi la liste de cette onglet (valeurs issues de la nomenclature datalayer)
B7: Choisir une/des valeurs parmi la liste en bleu clair pour éviter de créer des doublons
A10: prop1 | B10: prop5 | C10: prop7 | D10: prop8 | F10: prop9 | I10: prop10 | L10: prop14 | M10: prop15 | N10: prop16 | P10: prop17 | S10: prop18 | V10: prop51 | W10: evar 6 | Z10: evar 30 | AA10: evar 31 | AB10: evar 32 | AC10: evar 33 | AD10: evar 34 | AE10: evar 35 | AF10: evar 36 | AG10: evar 37 | AH10: evar 38 | AI10: evar 39 | AJ10: evar 45 | AK10: evar 46
C11: Valeurs ci-dessous | D11: Valeurs en bleu semblent les plus proches des valeurs souhaitées et permettent de ne pas créer de doublon | E11: Référentiel sharepoint | F11: Les valeurs sont issues pour partie du scrapping sur Portail et DEI (nom du dossier dans lequel est rangé le template ez-publish), pour partie de valeurs renseignées en dur. Règle de gestion à compléter pour Mobile, espaces connectés et commerciaux BP | G11: volumes par entrée | H11: Référentiel sharepoint | I11: inutilisable sans le plan de marquage de l'applicatif | K11: Valeurs utilisables | L11: Valeurs à vocation à être adaptatives (+10K valeurs) | M11: Valeurs adaptatives, format de valeurs ci-dessous | N11: Valeurs en bleu permettent de ne pas créer de doublon | O11: volume par entrée | P11: Valeurs en bleu permettent de ne pas créer de doublon | Q11: volumes par entrée | R11: Référentiel sharepoint | S11: Valeurs en bleu permettent de ne pas créer de doublon | T11: volumes par entrée | U11: Référentiel sharepoint | W11: Valeurs ci-dessous | AK11: Valeurs ci-dessous (CE)
A12: 11315 | B12: CEPAC | C12: Banque | D12: Particuliers | F12: acces | G12: 13746 | H12: agences et distributeurs | I12: acces et securite | J12: 897 | K12: conseil | L12: virement | M12: 0 | N12: transactionnel | O12: 4209082103 | P12: Ecran d'identification | Q12: 1103390194 | R12: assurance | S12: 2Roues | T12: 9629 | U12: assepargne | V12: CEPAC | W12: action | X12: 454858765 | Y12: action | AK12: Initial
A13: 11425 | B13: CEN | C13: dei part | D13: Professionnels | F13: accueil | G13: 57 | H13: assistance | I13: accueil | J13: 4 | K13: consultation | L13: Devis Auto | M13: 100 | N13: Commercial | O13: 615808020 | P13: transactionnel | Q13: 1030512453 | R13: bancarisation | S13: 3d nuances | T13: 588 | U13: assurance 2 roues | V13: CEN | W13: annuler | X13: 185298243 | Y13: annuler | AK13: Reprise
A14: 12135 | B14: CEBFC | C14: eCommerce | D14: particulier | F14: Agence | G14: 58002 | H14: assurer | I14: ajout document header | J14: 87 | K14: contact | L14: rendez vous en ligne | M14: 22.1 | N14: interne | O14: 12611021 | P14: Tableau de bord | Q14: 935889488 | R14: credit conso | S14: a booklet | T14: 434682 | U14: assurance auto | V14: CEBFC | W14: cta | X14: 165225679 | Y14: cta
A15: 12579 | B15: CEBCP | C15: selfcare | D15: entreprises | F15: aide | G15: 1434 | H15: au quotidien | I15: ajout document liste | J15: 78119589 | K15: document | L15: credit immo | M15: … | O15: 30435 | P15: Mes comptes | Q15: 218670633 | R15: credit immo | S15: aikido | T15: 41 | U15: assurance emprunteur | V15: CEBCP | W15: envoyer | X15: 161374148 | Y15: envoyer
A16: 13135 | B16: CEMP | C16: cenet | D16: associations fondations mutuelles - mandataires judiciaires la protection des majeurs | F16: assurance | G16: 4 | H16: banque au quotidien et assurance | I16: assurances | J16: 1042 | K16: edito | L16: … | M16: … | O16: 9126 | P16: compte | Q16: 207134076 | R16: credit pro | S16: aïkido | T16: 46 | U16: assurance moyen paiement | V16: CEMP | W16: menu | X16: 56163588 | Y16: menu
A17: 13335 | B17: CEAPC | C17: dei pro | D17: economie sociale et institutionnelle | F17: Assurer | G17: 875 | H17: connexion | I17: Assurer | J17: 116 | K17: erreur | L17: … | M17: … | O17: 2826 | P17: virements | Q17: 182082641 | R17: epargne financiere | S17: alertecureuil | T17: 561 | U17: assurance mrh | V17: CEAPC | W17: navigation | X17: 21440167 | Y17: navigation
A18: 13485 | B18: CELR | C18: DEM | D18: personne protegee | F18: Au quotidien | G18: 93771920 | H18: contact | I18: Attestations | J18: 4672339 | K18: faq | L18: … | O18: 1846 | P18: Barre de navigation | Q18: 165255550 | R18: epargne liquide | S18: applepay | T18: 1625 | U18: assurance resp civile | V18: CELR | W18: plus tard | X18: 17171095 | Y18: plus tard
A19: 13825 | B19: CERA | C19: DEA | D19: Associations, Fondations, Mutuelles - Mandataires Judiciaires a la Protection des Majeurs | F19: authentification | G19: 3004635 | H19: emprunter | I19: Au quotidien | J19: 34 | K19: formulaire | O19: 1042 | P19: erreur | Q19: 54937689 | S19: applismartphone | T19: 69 | U19: assurance voyage | V19: CERA | W19: rechercher | X19: 16900384 | Y19: rechercher
A20: 14265 | B20: CELDA | C20: tunnel | D20: Immobilier professionnel | F20: Avis | G20: 1662701 | H20: epargner | I20: authentification | J20: 445915 | K20: gammes | O20: 706 | P20: Accès rapide | Q20: 34178917 | S20: Ass Compte | T20: 1568 | U20: bourse | V20: CELDA | W20: sortie | X20: 9248357 | Y20: sortie
A21: 14445 | B21: CEBPL | C21: BCP Net Part | D21: logement social - conomie mixte | F21: Banque au quotidien et Assurance | G21: 1059088 | H21: financement | I21: Avis store | J21: 36865238 | K21: home | O21: 380 | P21: Prélèvement | Q21: 26446417 | S21: Ass Epargne | T21: 1649 | U21: carte | V21: CEBPL | W21: telechargement | X21: 5703749 | Y21: telechargement
A22: 14505 | B22: CELC | C22: dei pp | D22: Secteur public | F22: Barre de navigation | G22: 90330464 | H22: gestion privee | I22: Banque au quotidien et Assurance | J22: 1 | K22: information | O22: 374 | P22: Messagerie | Q22: 25844330 | S22: assauto | T22: 625 | U22: cat | V22: CELC | W22: valider | X22: 5068051 | Y22: valider
A23: 15135 | B23: CEGEE | C23: ngi | D23: institutionnels | F23: carte bancaire | G23: 1027335 | H23: ma banque pratique | I23: BCP Net | J23: 1673343 | K23: marche | O23: 351 | P23: Assurances | Q23: 21154370 | S23: assistancevie | T23: 33101 | U23: cel | V23: CEGEE | W23: vignette | X23: 3460771 | Y23: vignette
A24: 16275 | B24: CEHDF | C24: dp mobile | D24: Logement Social - Économie Mixte | F24: cartes bancaires | G24: 67 | H24: ma synthese | I24: beneficiaires | J24: 338895 | K24: operation | O24: 299 | P24: E-Documents | Q24: 19751432 | S24: assistant obsèques financement | T24: 65 | U24: cfn | V24: CEHDF | X24: 3315160
A25: 17515 | B25: CEIDF | C25: deep purple | D25: financements spcialiss | F25: chequiers | G25: 91 | H25: mes assurances | I25: bloc_thematiquemultipanels | J25: 5412292 | K25: page_ccd | O25: 116 | P25: RIB/IBAN | Q25: 17815815 | S25: assur.vie 1818 | T25: 55 | U25: compte-courant | V25: CEIDF | X25: 3266040
A26: 18315 | B26: CECAZ | C26: mbl | D26: profesionnel | F26: choisir sa caisse | G26: 66695 | H26: mes cartes et paiement | I26: carte | J26: 12274731 | K26: popin | O26: 103 | P26: Météo / Agrégation / Budget | Q26: 17720189 | S26: assurance2roues | T26: 203 | U26: credit conso auto | V26: CECAZ | X26: 2954708
A27: 18715 | B27: CEPAL | C27: evi | D27: logement social - économie mixte | F27: code confidentiel oublie | G27: 352126 | H27: mes comptes | I27: code confidentiel oublie | J27: 21344093 | K27: produit | O27: 42 | P27: bancarisation | Q27: 16869593 | S27: Assurance-auto | T27: 4096 | U27: credit conso etudiant | V27: CEPAL | X27: 2714280
A28: 30258 | B28: BTP | C28: harvest | D28: s/o | F28: code confidentiel oublié | G28: 2848679 | H28: mes credits | I28: collecte justificatif | J28: 19202392 | K28: profil | O28: 29 | P28: moyens de paiement | Q28: 14627694 | S28: assuranceautopro | T28: 91 | U28: credit conso travaux | V28: BTP | X28: 2322902
A29: 42559 | B29: CCOOP | C29: lac | D29: particulier | E29: 15798451 | F29: collectivites locales | G29: 2358 | H29: messagerie | I29: compte | J29: 1297924 | K29: recherche | O29: 14 | P29: Contact | Q29: 8800506 | S29: assurancehabitationsante | T29: 4036 | U29: credit conso tresorie | V29: CCOOP | X29: 1999246
A30: 43199 | B30: CFF | C30: hub digital | D30: particuliers | E30: 10828791 | F30: comptes | G30: 1009847926 | H30: mon agence | I30: comptes | J30: 11455 | K30: recherche agence | O30: 11 | P30: Crédit | Q30: 7869611 | S30: Assurance-MRH | T30: 38 | U30: credit immo | V30: CFF | X30: 1644476
A31: 12579 | B31: BCP | C31: BDCL | D31: fonction publique | E31: 4432834 | F31: connexion | G31: 1719 | H31: mon coffre fort | I31: condition_generale | J31: 111504662 | K31: univers | O31: 2 | P31: Paramètres | Q31: 7080764 | S31: assurancemultirisquepro | T31: 340 | U31: credit immo primo | V31: BCP | X31: 1336061
A32: 002 | B32: 002 | C32: dei sp | D32: artisans commerçants | E32: 3014242 | F32: Contact | G32: 12725715 | H32: mon epargne | I32: configuration | J32: 732752270 | K32: simulateur | O32: 2 | P32: Personnaliser tableau de bord | Q32: 6664785 | S32: assuranceprotectionjuridique | T32: 207 | U32: credit pro | V32: BPRI | X32: 1229357
A33: 008 | B33: 008 | C33: CE | D33: gestion privée | E33: 1651975 | F33: Credit | G33: 1686250 | H33: mon profil | I33: confirmation | J33: 96923 | K33: landing page | O33: 2 | P33: credit immo | Q33: 5564038 | S33: assurancesurcomptefamille | T33: 161 | U33: eparfix | V33: BPBFC | X33: 1228508
A34: 009 | B34: 009 | C34: banque | D34: entreprises | E34: 1176493 | F34: Crédit | G34: 6892273 | H34: parametres | I34: conseil | J34: 67457 | O34: 1 | P34: Mot de passe oublie et id oublie | Q34: 4735757 | S34: Assurance-voyage | T34: 3593 | U34: gav | V34: BPACA | X34: 953459
A35: 035 | B35: 035 | C35: communication | D35: professions libérales | E35: 932918 | F35: credits | G35: 3459225 | H35: placement | I35: consultation | J35: 3427581 | O35: 1 | P35: Acces rapide | Q35: 3273880 | S35: assurecureuil | T35: 53 | U35: internet | V35: BPN | X35: 746003
A36: 038 | B36: 038 | C36: 89c3.com | D36: jeunes actifs | E36: 695743 | F36: Didacticiel | G36: 382860 | H36: politique sociale | I36: Consultation contrat | J36: 22994864 | O36: 1 | P36: Simulateurs Epargne | Q36: 2729718 | S36: assurécureuil | T36: 1578 | U36: ldd | V36: BPATL | X36: 705576
A37: 046 | B37: 046 | C37: digital briefcase | D37: institutionnels | E37: 588867 | F37: Ecran d'identification | G37: 1047854905 | H37: prelevements | I37: Consultation devis | J37: 14402 | P37: Simulateurs Crédit | Q37: 2720638 | S37: assurtoit | T37: 2031 | U37: lep | V37: BPMED | X37: 689643
A38: 046 | B38: 046 | C38: store 89c3 | D38: fonctionnaires | E38: 498700 | F38: emprunter | G38: 12149298 | H38: virements | I38: Consultation Edocument | J38: 5318848 | P38: credit conso | Q38: 2612053 | S38: assurtoitjeunes | T38: 3720 | U38: livret a | V38: BPMED | X38: 593881
A39: 046 | B39: 046 | C39: hub digital | D39: banque privée | E39: 399238 | F39: engagements par signature | G39: 5126 | I39: contact | J39: 40056 | P39: DEA | Q39: 2588781 | S39: asvalacarte | T39: 1926 | U39: livret b | V39: BPMED | X39: 544060
A40: 047 | B40: 047 | C40: visa | D40: artisan commerçant | E40: 300904 | F40: enrolement | G40: 10248 | I40: contenus_externes | J40: 2251898 | P40: Agences / Distributeurs | Q40: 2424893 | S40: Auto | T40: 53 | U40: livret grand format | V40: BPALC | X40: 488495
A41: 047 | B41: 047 | C41: cyber | D41: service public | E41: 286061 | F41: Epargner | G41: 5143237 | I41: coordoonnees | J41: 2032125 | P41: Virement | Q41: 2191035 | S41: AUTO3 | T41: 129 | U41: livret grand prix | V41: BPALC | X41: 356839
A42: 066 | B42: 066 | C42: ecommerce | D42: bfc banque privée | E42: 278138 | F42: erreur | G42: 58503977 | I42: credit | J42: 278163 | P42: Prelevement | Q42: 2177643 | S42: AUTO4 | T42: 4409961 | U42: livret jeune | V42: BPS | X42: 197452
A43: 067 | B43: 067 | C43: Banque Pop | D43: entreprise | E43: 207726 | F43: Financement | G43: 141097 | I43: credits | J43: 1601792 | P43: Retrait SMS | Q43: 1924733 | S43: autotaxi | T43: 129486 | U43: obseques | V43: BPO | X43: 140977
A44: 068 | B44: 068 | C44: deep purple | D44: professionnel | E44: 189990 | F44: Financer | G44: 3718 | I44: Dec sin Parabancaire | J44: 143 | P44: Credit | Q44: 1727816 | S44: avancesurbourse | T44: 124434 | U44: opcvm | V44: BPAURA | X44: 108545
A45: 068 | B45: 068 | C45: selfcare | D45: agriculteurs | E45: 165032 | F45: Gérer | G45: 7687 | I45: Dec sin Secur Media | J45: 2520156 | P45: profil | Q45: 816821 | S45: banxo | T45: 51 | U45: paiement | V45: BPAURA | X45: 73628
A46: 068 | B46: 068 | C46: tunnel | D46: enfants etudiants apprentis | E46: 93562 | F46: gestion | G46: 11827 | I46: dei | J46: 60777 | P46: Identification | Q46: 558838 | S46: BCP PATRIMONIO CRESCENTE | T46: 37 | U46: pea | V46: BPAURA | X46: 64072
A47: 078 | B47: 078 | C47: harvest | D47: franchise | E47: 90682 | F47: gestion abonnement | G47: 55581 | I47: devies en ligne | J47: 53121 | P47: Assistance / opposition | Q47: 555094 | S47: bouquet liberte | T47: 100 | U47: pel | V47: BPOC | X47: 24286
A48: 087 | B48: 087 | C48: store 89c3 | D48: lycéens etudiants apprentis | E48: 83819 | F48: hub digital b2b | G48: 16389 | I48: Devis 2Roues | J48: 968722737 | P48: Mes crédits | Q48: 518754 | S48: bouquetliberte | T48: 594 | U48: pj | V48: BPVF | X48: 20987
A49: 552 | B49: 552 | C49: hub digital | D49: 16 ans et plus | E49: 83029 | F49: identifiant oublie | G49: 300821 | I49: Devis Auto | J49: 2 | P49: Informations | Q49: 493174 | S49: bouquetlibertefamille | T49: 167285 | U49: retrait inter | V49: BQSAV | X49: 10954
A50: 013 | B50: 013 | C50: cyber | D50: 16-28 ans | E50: 60594 | F50: identifiant oublié | G50: 1112143 | I50: Devis MRH | J50: 204343 | P50: Mes comptes favoris | Q50: 428509 | S50: bouquetlibertejeunes | T50: 1006 | U50: sante | V50: CASDEN | X50: 10577
A51: 061 | B51: 061 | C51: ecommerce | D51: profession libérale | E51: 57093 | F51: identification | G51: 2357647 | I51: document | J51: 1595497 | P51: Cartes et paiement | Q51: 397449 | S51: bourseopcrecompenses | T51: 125 | U51: securmedia | V51: NAT | X51: 8672
C52: Banque Pop | D52: jeune actif | E52: 55926 | F52: Ma banque pratique | G52: 1101088 | I52: documents recents | J52: 782092 | P52: Didacticiel | Q52: 384132 | S52: campagneassurancevie | T52: 839 | U52: visuel carte | X52: 6929
C53: deep purple | D53: agriculture – viticulture | E53: 31049 | F53: ma messagerie | G53: 80610418 | I53: documents signales | J53: 11583 | P53: Simulateurs Credit | Q53: 360203 | S53: capciel | T53: 37 | X53: 4668
D54: agriculteur viticulteur | E54: 29603 | F54: Ma synthese | G54: 122922952 | I54: dossier | J54: 9111 | P54: Simulateur Immo | Q54: 293442 | S54: captio croissance | T54: 227 | X54: 2741
D55: frontalier | E55: 24287 | F55: Ma synthèse | G55: 1214592660 | I55: dossier a classer | J55: 351 | P55: sav | Q55: 198081 | S55: captio pre. | T55: 19536 | X55: 2675
D56: associations et institutionnels | E56: 22608 | F56: Ma synth�se | G56: 20198095 | I56: dossier bancaire | J56: 480 | P56: Parametres | Q56: 146468 | S56: captioprestance | T56: 1911 | X56: 1766
D57: apprentisetudiants | E57: 19019 | F57: Mes assurances | G57: 23689961 | I57: dossier personnel | J57: 373 | P57: credit pro | Q57: 89149 | S57: Carte | T57: 2719 | X57: 1739
D58: etudiants | E58: 18859 | F58: Mes comptes | G58: 789978312 | I58: dossier_conseil | J58: 706 | P58: Assurance | Q58: 65683 | S58: carteachatpublic_sp | T58: 41 | X58: 1287
D59: agriculteurs viticulteurs | E59: 18067 | F59: Mes credits | G59: 458575 | I59: eagence | J59: 1841 | P59: Simulateur Epargne | Q59: 55155 | S59: cartebancairerechargeable | T59: 312857 | X59: 1095
D60: institutionnels associations | E60: 11861 | F60: mes crédits | G60: 15608007 | I60: Emprunter | J60: 3376207 | P60: reglages | Q60: 33290 | S60: cartederetraitnomeaparts | T60: 41 | X60: 842
D61: associations | E61: 9774 | F61: Mon agence | G61: 2370998 | I61: Epargner | J61: 3195 | P61: Montre connectée | Q61: 30023 | S61: carteinterbancaireequilibra | T61: 838 | X61: 726
D62: jeunes adultes | E62: 6942 | F62: mon coffre fort | G62: 26949 | I62: erreur | J62: 98346 | P62: epargne liquide | Q62: 23150 | S62: cartevisabusiness | T62: 101 | X62: 612
D63: collégiens etudiants apprentis | E63: 3961 | F63: Mon epargne | G63: 268735 | I63: Espace Assurance | J63: 260090 | P63: Montre connectee | Q63: 7173 | S63: cartevisabusiness_pro | T63: 90 | X63: 568
D64: 0-15 ans | E64: 3182 | F64: mon épargne | G64: 82977985 | I64: espace_transactionnel | J64: 7992578 | P64: Infos Editeur | Q64: 5597 | S64: cartevisaclassic | T64: 68 | X64: 431
D65: enfants - étudiants - apprentis | E65: 3181 | F65: mon profil | G65: 19989528 | I65: faq | J65: 168952 | P65: epargne financiere | Q65: 2336 | S65: cartevisacryptogrammedynamique | T65: 51 | X65: 377
... D81: jeune | E81: 3 | F81: Placement | G81: 49532 | I81: historique modification | J81: 12 | P81: Mot de passe ouble et d ouble | Q81: 17 | S81: cat slr 12 ans | T81: 9958 | X81: 49
F82: Placer | G82: 467 | I82: home | J82: 7758121 | P82: Ecran d'identiication | Q82: 17 | S82: cat slr 13 ans | T82: 1142 | X82: 44
F83: Politique sociale | G83: 16957 | I83: identifiant oublie | J83: 380 | P83: cesu prefinance | Q83: 16 | S83: cat slr 14 ans | T83: 2480 | X83: 37
F84: prelevements | G84: 2303 | I84: iframe | J84: 28991 | P84: perco and co | Q84: 13 | S84: cat slr 15 ans | T84: 744 | X84: 27
F85: Prise de rendez-vous | G85: 73231 | I85: information | J85: 609702 | P85: Tableau de ord | Q85: 12 | S85: cat slr 16 ans | T85: 2473 | X85: 23
F86: profil | G86: 1461946 | I86: intermediaire | J86: 1997969 | P86: tradeliner | Q86: 12 | S86: cat slr 3 ans | T86: 1455 | X86: 16
F87: reglages | G87: 13281429 | I87: jeux concours | J87: 268 | P87: lyly | Q87: 9 | S87: cat slr 4 ans | T87: 23161 | X87: 9
F88: releves en ligne | G88: 733 | I88: landing page | J88: 307009 | P88: easyliner | Q88: 9 | S88: cat slr 5 ans | T88: 9188 | X88: 3
F89: Retrait SMS | G89: 159400 | I89: lien | J89: 15 | P89: flash-factures | Q89: 6 | S89: cat slr 6 ans | T89: 3631 | X89: 3
F90: s assurer | G90: 10787 | I90: Ma synthèse | J90: 505 | P90: Barre de navgaton | Q90: 6 | S90: cat slr 7 ans | T90: 6558 | X90: 1
F91: S'assurer | G91: 2220884 | I91: marche | J91: 1 | P91: ghostery | Q91: 5 | S91: cat slr 8 ans | T91: 23508
F92: securpass | G92: 756475 | I92: mon conseiller/mon agence | J92: 15 | P92: Agences / Dstrbuteurs | Q92: 1 | S92: cat slr 9 ans | T92: 2879
F93: sous livret a | G93: 97 | I93: mon profil | J93: 303772110 | P93: banque à distance | S93: ce slr 10 ans | T93: 6495
F94: sous tirelire | G94: 765 | I94: nav_page | J94: 10 | P94: accéder à votre banque 24h24 7 jours7 | S94: ce slr 11 ans | T94: 1046
F95: souscription client | G95: 3755 | I95: Nos produits pour emprunter | J95: 4 | P95: accéder à votre banque 24h24 7jours7 | S95: ce slr 12 ans | T95: 1462
F96: timeout | G96: 157232 | I96: Nos produits pour épargner | J96: 2197756 | P96: accompagnement start-up | S96: ce slr 13 ans | T96: 175
F97: TouchID | G97: 556565 | I97: Nos produits pour gérer son quotidien | J97: 989 | P97: accroître la performance | S97: ce slr 14 ans | T97: 237
F98: usage | G98: 209975 | I98: Nos produits pour gérer votre quotidien et vos assurances | J98: 2646 | P98: acheter sa résidence principale | S98: ce slr 15 ans | T98: 85
F99: virements | G99: 433608170 | I99: Nos produits pour s’assurer | J99: 31351 | P99: acheter un bien immobilier | S99: ce slr 16 ans | T99: 168
F100: accompagner | I100: Nos produits pour vos financements | J100: 1100 | P100: acheter votre résidence principale | S100: ce slr 3 ans | T100: 143
F101: accueil | I101: Nos produits pour vos placements | J101: 7090 | P101: acquérir pour louer | S101: ce slr 4 ans | T101: 4574
F102: aider et transmettre | I102: Nos produits pour votre politique sociale | J102: 142 | P102: acquérir votre voiture | S102: ce slr 5 ans | T102: 2933
F103: aider protéger et transmettre | I103: Obtenir tarif | J103: 19 | P103: acquisition cession transmission | S103: ce slr 6 ans | T103: 920
F104: anticiper les imprévus | I104: OPCVM | J104: 60 | P104: activité au quotidien | S104: ce slr 7 ans | T104: 898
F105: assurance | I105: operation | J105: 15 | P105: affacturage | S105: ce slr 8 ans | T105: 785
F106: assurer | I106: organisme emetteur - administration famille | J106: 2334 | P106: aider mes proches | S106: ce slr 9 ans | T106: 307
F107: au quotidien | I107: organisme emetteur - banque finance | J107: 315029 | P107: aider vos proches | S107: CEL | T107: 838
F108: candidature | I108: organisme emetteur - eau electricite gaz | J108: 1 | P108: améliorer la vie au quotidien | S108: cenet | T108: 110
F109: compte | I109: organisme emetteur - ecommerce | J109: 11 | P109: améliorer leur quotidien | S109: certificatelectroniquecerticeo | T109: 57161
F110: Comptes | I110: organisme emetteur - emploi retraite | J110: 1 | P110: aménagement spécifique | S110: certificatelectroniquecerticeo_pro | T110: 222
F111: concrétiser son projet | I111: organisme emetteur - impots | J111: 1 | P111: analyser votre patrimoine | S111: cfn | T111: 37
F112: connexion | H112: 6 | I112: organisme emetteur - sante mutuelles de sante | J112: 2 | P112: apprendre à gérer son budget | S112: code confidentiel oublie | T112: 349
F113: contact | I113: organisme emetteur - telephonie internet tv | J113: 14 | P113: apprendre à gérer votre budget | S113: coffrefortnumerique | T113: 62
F114: credit | I114: organisme emetteur - tous les organismes emetteurs | J114: 2 | P114: assurance de personnes | S114: comprendremarchesfinanciers | T114: 1325328
F115: crédit | I115: page_ccd | J115: 2 | P115: assurance de responsabilité | S115: compte cantonnement | T115: 1383
F116: créer | I116: page_choix_region | J116: 29 | P116: assurance des appareils nomades | S116: compte cheque | T116: 106
F117: découvrir bfc banque privée | I117: parametres | J117: 484449 | P117: assurance des biens | S117: compte excedent prof | T117: 18969
F118: défiscaliser | I118: paylib | J118: 58599 | P118: assurance des comptes | S118: compte numeraire pea | T118: 22146064
F119: développer | I119: Placement | J119: 84257 | P119: assurance des habitations | S119: compte titres | T119: 124015
...

Sheet Introduction
B2: Version | C2: Date | D2: Auteur | E2: Modifications
B3: v1 | C3: 43922 | D3: Agathe Gourhannic | E3: Ajout des variables client proprevenant du projet enrichissement datalayer (evars 101 à 118)

Sheet Ref à implé Tealium
A1: Baptiste

Sheet Architecture AA
A1: Entité | B1: Nom Report Suites | C1: Type de RS | D1: Description | E1: Filtres appliqués | F1: Méthode d'alimentation | G1: ID visiteur | H1: A faire pour valider
A2: BP | B2: BP-PROD-GLOBAL | C2: RS primaire | D2: Contient l'ensemble des données de production (y compris les données des banques adossées associées Palatine, Crédit Maritime, Banque de Savoie) | F2: Envoyés par Tealium | G2: = ECID (Id aléatoire) | H2: @Baptiste, as-tu plus de précision sur la façon dont tu envoies les données vers les RS (notamment pour distinguer la prod/dev)
A3: BP | B3: BP-PROD-xxxx | C3: RS secondaire | D3: Contient les données de production des clients identifiés pour chaque des banques. Cette duplication des données a été nécessaire du fait du manque de cardinalité des variables (au-delà d'un certain nombre de valeur différente, les valeurs ne remontent plus) qui rendait inexploitable l'Id Client nécessaire aux exploitations CRM (avec Adobe Campaign) | F3: Dupliqués de la RS de prod globale via une VISTA Rule (gérée dictement par Adobe) :_x000D_ - en fonction de la valeur de la prop1 (code etablissement)_x000D_ - si l'evar100 (Id CRM) est remplie La VISTA rule n'impacte aucune autre variable | G3: = evar100 | H3: Validé avec Adobe le 02/06
A4: BP | B4: BP-PROD-xxxx-TRAFFIC | C4: RS virtuel | D4: Contient l'ensemble des données de production provenant du RS global en fonction du code établissement. Ce RS permet aux banques d'analyser uniquement les données qui les concernent sans application de filtres ou de processing spécifiques | F4: Segmentation des données de la RS de primaire sur les valeurs de la prop1, prop5 ou evar1 (code Etablissement Page/Client) | G4: = ECID (Id aléatoire)
A5: CE | B5: CE - Production | C5: RS primaire | D5: Contient l'ensemble des données de production (y compris les données des banques adossées associées BCP, Crédit Coop, BTP (banque travaux publiques)) | F5: Envoyés par Tealium | G5: = ECID (Id aléatoire)
A6: CE | B6: CE - PROD - xxxx | C6: RS secondaire | D6: Contient les données de production des clients identifiés pour chaque des banques. Cette duplication des données a été nécessaire du fait du manque de cardinalité des variables (au-delà d'un certain nombre de valeur différente, les valeurs ne remontent plus) qui rendait inexploitable l'Id Client nécessaire aux exploitations CRM (avec Adobe Campaign) | F6: Dupliqués de la RS de prod globale via une VISTA Rule (gérée dictement par Adobe) :_x000D_ - en fonction de la valeur de la prop1 (code etablissement)_x000D_ - si l'evar100 (Id CRM) est remplie La VISTA rule n'impacte aucune autre variable | G6: = evar100
A7: CE | B7: CE - PRD - xxxx - xxxxx | C7: RS virtuel | D7: Contient l'ensemble des données de production provenant du RS global en fonction du code établissement. Ce RS permet aux caisses d'analyser uniquement les données qui les concernent sans application de filtres ou de processing spécifiques | F7: Segmentation des données de la RS de primaire sur les valeurs de la prop5 (code réduit de la page) | G7: = ECID (Id aléatoire)
A9: /!\ Spécificités d'analyse
A11: Analyses visites mobiles CE : Lors de la navigation sur l'app, les webviews donnent lieu à des ruptures de sessions => lors des analyses sur les visites ou les visiteurs, utiliser un segment "App IDs without webviews" (permet de filtrer les App ID qui contiennent les noms des marque car ce sont ceux qui correspondent aux webviews) - ne pas l'utiliser pour les analyses sur les pages/occurrences
A13: Analyses OS type : Le User Agent iOS ne peut pas être traité actuellement par Tealium => utiliser le segment iOS Tealium (basé sur la variable App SDK) pour distinguer les OS types
A14: => corrigé le 28/05/2020

Sheet Feuil1

Sheet Liens
B2: Liens utiles
B3: https://groupebpce.sharepoint.com/:x:/r/sites/analyticstaggage/_layouts/15/doc2.aspx?sourcedoc=%7Bf2f392ef-d4ee-48f7-8872-ab9b4059db1a%7D&action=default&uid=%7BF2F392EF-D4EE-48F7-8872-AB9B4059DB1A%7D&ListItemId=351&ListId=%7BE0A7B64B-A21A-4DEE-8410-7944A9B70464%7D&odsp=1&env=prod&cid=895c0054-3212-4b49-8656-b4570f239639
B4: https://teams.microsoft.com/l/file/1B93CEC8-8A7E-4CB6-B81E-A38A885435C4?tenantId=d5bb6d35-8a82-4329-b49a-5030bd6497ab&fileType=xlsx&objectUrl=https%3A%2F%2Fgroupebpce.sharepoint.com%2Fsites%2FPerformanceDigitale%2FShared%20Documents%2FImpl%C3%A9mentation%20Tealium%2FRecette%20mobile%2FMapping_Attribut_Tealium_Adobe.xlsx&baseUrl=https%3A%2F%2Fgroupebpce.sharepoint.com%2Fsites%2FPerformanceDigitale&serviceName=teams&threadId=19:13e95a0d857a44d1b7c9fb72f563a475@thread.skype&groupId=c3e35186-da77-43e5-8ff7-35df55c08a37

Sheet Extensions Tealium
A1: ID | B1: Status | C1: Scope | D1: Title | E1: Type | F1: Description (Role)
A2: 1 | B2: active | C2: preload | D2: Flatten - datalayer | E2: Aplanir les objets JSON
A3: 2 | B3: active | C3: preload | D3: JS - Change datalayer name | E3: Code Javascript
A4: 3 | B4: active | C4: global | D4: Set - aa_reportSuite | E4: Table de rÃ©fÃ©rence
A5: 4 | B5: active | C5: global | D5: JS - Merge utag_data into utag.link | E5: Code Javascript
A6: 5 | B6: active | C6: domready | D6: EZ - FormlrContctClickBtnAnnl | E6: jQuery onHandler (1.7 et plus)
A7: 6 | B7: active | C7: domready | D7: EZ - HeaderClicContactAgence | E7: jQuery onHandler (1.7 et plus)
A8: 7 | B8: active | C8: domready | D8: EZ - PagesClickBtnRseauxSocx | E8: jQuery onHandler (1.7 et plus)
A9: 8 | B9: active | C9: domready | D9: EZ - PagesClickButtons | E9: jQuery onHandler (1.7 et plus)
A10: 9 | B10: active | C10: domready | D10: EZ - FormlrContctClickBtnVld | E10: jQuery onHandler (1.7 et plus)
A11: 10 | B11: active | C11: domready | D11: EZ - HeaderClicContactMail | E11: jQuery onHandler (1.7 et plus)
A12: 11 | B12: active | C12: domready | D12: EZ - HeaderClicContactPhone | E12: jQuery onHandler (1.7 et plus)
A13: 12 | B13: inactive | C13: domready | D13: EZ - HomePageClickVignetteMajeure | E13: jQuery onHandler (1.7 et plus)
... A120: 150 | B120: active | C120: global | D120: Set - Visitor Context data | E120: Code Javascript
B121: Tous les tags – Après les règles de chargement (par défaut)
B122: 114
B124: Join - vignette.liste - view
B125: Joindre les valeurs de données
B126: Tous les tags – Après les règles de chargement (par défaut)
B127: 109
B129: Set - vignette.nom et liste - link
B130: Set data values
B131: Tous les tags – Après les règles de chargement (par défaut)
B132: 111
B134: Set - Event28 - View vignette.list
B135: Set data values
B136: Tous les tags – Après les règles de chargement (par défaut)
B137: 142
B139: Set - previous_page_name
B140: Page précédente
B141: Tous les tags – Après les règles de chargement (par défaut)
B142: 121
B144: Set - pages.pageName_event - link
B145: Set data values
B146: Tous les tags – Après les règles de chargement (par défaut)
B147: 123
B149: Set - pages.pageName_event - view
B150: Set data values
B151: Tous les tags – Après les règles de chargement (par défaut)
B152: 124
B154: Set - search.keyword - Portail
B155: Set data values
B156: Tous les tags – Après les règles de chargement (par défaut)
B157: 125
B159: Set - search.notFound - Portail
B160: Set data values
B161: Tous les tags – Après les règles de chargement (par défaut)
B162: 126
B164: JS - Consent Manager - Event Stream
B165: Code Javascript
B166: Tous les tags – Après les règles de chargement (par défaut)
B167: 131
B169: Set - Clics CE - Event10
B170: Set data values
B171: Tous les tags – Après les règles de chargement (par défaut)
B172: 132
B174: Clics CE - Vignettes
B175: Set data values
B176: Tous les tags – Après les règles de chargement (par défaut)
B177: 134
B179: Set - client.IdEnttGrpe
B180: Set data values
B181: Tous les tags – Après les règles de chargement (par défaut)
B182: 138
B184: Set - Event1 & Event2 - RDV en ligne - idEtape fin : 3.2
B185: Table de référence
B186: Tous les tags – Après les règles de chargement (par défaut)
B187: 139
B189: Set - Event1 & Event2 - idEtape fin : 2
B190: Table de référence
B191: Tous les tags – Après les règles de chargement (par défaut)
B192: 141
B194: Persist - idwebview
B195: Conserver les valeurs de données
B196: Tous les tags – Après les règles de chargement (par défaut)
B197: 143
B199: Set - Visitor Context data
B200: Code Javascript
B201: Tous les tags – Après les règles de chargement (par défaut)
B202: 150
B204: EZ - FormlrContctClickBtnAnnl
B205: jQuery onHandler (1.7 et plus)
B206: DOM prêt
B207: 5
B209: EZ - HeaderClicContactAgence
B210: jQuery onHandler (1.7 et plus)
B211: DOM prêt
B212: 6
B214: EZ - PagesClickBtnRseauxSocx
B215: jQuery onHandler (1.7 et plus)
B216: DOM prêt
B217: 7
B219: EZ - PagesClickButtons
B220: jQuery onHandler (1.7 et plus)
B221: DOM prêt
B222: 8
B224: EZ - SimulerPretPerso
B225: jQuery onHandler (1.7 et plus)
B226: DOM prêt
B227: 133
...

Sheet TCD
A1: CATEGORE | B1: (Tous)
A2: TYPOLOGIE | B2: DIMENSION
A4: Étiquettes de lignes | B4: CODE | C4: LIBELLE | D4: DESCRIPTION | E4: Nombre de LIBELLE
A5: AB TESTING | B5: evar11 | C5: ABTesting 1 (evar11) | D5: ABTesting : nom du test ab | E5: 1
B6: evar12 | C6: ABTesting 2 (evar12) | D6: AB Testing : nom de la variation de l'ab test | E6: 1
B7: evar95 | C7: ABTesting 3 (eVar95) | D7: ABTesting : nom du test ab | E7: 1
B8: evar96 | C8: ABTesting 4 (eVar96) | D8: ABTesting : nom du test ab | E8: 1
B9: evar97 | C9: ABTesting 5 (eVar97) | D9: ABTesting : nom du test ab | E9: 1
B10: evar98 | C10: ABTesting 6 (eVar98) | D10: ABTesting : nom du test ab | E10: 1
A11: Total AB TESTING | E11: 6
A12: ASSURANCE | B12: evar57 | C12: CE => Dernier produit (evar57) BP => Profil client (particulier/entreprise) | D12: CE : Dernier produit consulté pour erebond BP : Type d'assurance | E12: 1
B13: evar58 | C13: formule assurance high tech | D13: Type de formule choisi pour l'assurance securi high tech | E13: 1
A14: Total ASSURANCE | E14: 2
A15: ASSURANCE AUTO | B15: evar30 | C15: Designation du véhicule (evar30) | D15: Dans formulaire assurance AUTO étape 1 | E15: 1
B16: evar45 | C16: Type de recherche (evar 45) | D16: Moteur de recherche interne. Permet d'identifier la manière dont le véhicule est rechercher dans le cadre d'une assurance auto | E16: 1
A17: Total ASSURANCE AUTO | E17: 2
A18: ASSURANCE NON VIE | B18: evar34 | C18: proprietaire ou locataire (evar34) | D18: Dans Devis et simulations / Obtenir un tarif (HABITATION) étape 1 | E18: 1
B19: evar35 | C19: je cherche a assurer (evar35) | D19: Dans Devis et simulations / Obtenir un tarif (HABITATION) étape 1 | E19: 1
